Workbook

Sheet Read me
A1: FortiSIEM 7.6.0 rule catalogue: identity, AD, Kerberos, AD CS, credential access, lateral movement, privilege change
A3: Source
A4: Rule pages: https://filestore.fortinet.com/docs.fortinet.com/fsiem/Public_Resource_Access/7_6_0/rules/rule_descriptions.htm (index) plus one page per rule. All 3,857 rule pages fetched on 2026-10-05, single-threaded at about 4 requests/s, cached locally, 0 failures, 0 parse errors.
A5: Rule lists: 760-new-itdr-rules.pdf (57), 760-existing-rules-added-to-itdr.pdf (244), 760-new-rules.pdf (1,041), linked from "What's New in 7.6.0". All 301 ITDR names matched a rule page.
A6: Sizing compared: ITDR log sizing dashboard (claude.ai/artifact/QdAN6guArhemD2qmo1HAVr) and worst-case calculator (claude.ai/artifact/HKjRytjases9eu6exWE6Th), both read on 2026-10-05.
A8: Sheets
A9: Catalogue: 999 in-scope rules, one row each. Sorted new ITDR, then re-tagged ITDR, then identity-core, then tactic-only.
A10: Subpatterns: one row per subpattern with its full query, event types, filters, group-by, aggregate.
A11: Rule-Event map / Rule-DS map / Rule-Row map: long-format helpers the summary formulas count from. Rule-Row map holds one row per distinct rule and sizing row, so sizing-row counts are distinct rules.
A12: Data sources: rules and event types per FortiSIEM data source (counts are live COUNTIFS formulas).
A13: Log channels: rules per log channel and event ID, mapped to your sizing rows.
A14: Coverage - 57 ITDR: each new ITDR rule, what your dashboard assumed, what the rule actually reads, and a verdict.
... A37: This reflects the public rule documentation for 7.6.0 as published on 2026-10-05. Content updates after that date may change rules. Event-type groups and the Event Hub parser routing (MicrosoftAzureEntraParser vs AzureEventHubParser) are not visible in the docs and should be checked in a live 7.6.0 system under Resources > Event Types and on a sample of ingested events.

Sheet Catalogue
A1: Rule ID | B1: Rule name | C1: ITDR status | D1: Scope class | E1: Scope tags | F1: Default status | G1: Severity | H1: Severity label | I1: Category | J1: Detection technology | K1: Rule mode | L1: MITRE tactics | M1: MITRE techniques | N1: FortiSIEM data source(s) | O1: Event types (all subpatterns) | P1: Excluded event types | Q1: # subpatterns | R1: Subpattern logic | S1: Filters (non-eventType conditions) | T1: Group-by attributes | U1: Aggregate constraint(s) | V1: Time window (s) | W1: Global constraint | X1: Log channel : event key (derived) | Y1: Sizing row(s) that carry it (derived) | Z1: Description | AA1: Rule page
A2: PH_Rule_Azure_Entra_ID_Conditional_Access_Disabled | B2: Azure Entra ID: Conditional Access Disabled | C2: New ITDR (7.6.0) | D2: Identity-core | E2: Entra ID, Privilege/account change | F2: Enabled | G2: 9 | H2: High | I2: Security | J2: Correlation | K2: Streaming | L2: Defense Evasion | M2: T1556.001 | N2: Microsoft Entra Activity Logs via Azure Event Hub | O2: MS-Entra-AuditLogs-Policy-Update_policy-success | Q2: 1 | R2: Filter | S2: opName REGEXP ".*(?:Delete conditional access policy|Update conditional access policy).*" | T2: user,opName | U2: COUNT(*) >= 1 | V2: 300 | X2: Entra Event Hub: AuditLogs | Y2: ea | Z2: Detects when a Conditional Access policy is disabled, modified, or deleted. An adversary may modify or remove Conditional Access policies to weaken authentication requirements and bypass security controls. | AA2: https://filestore.fortinet.com/docs.fortinet.com/fsiem/Public_Resource_Access/7_6_0/rules/PH_RULE_Azure_Entra_ID_Conditional_Access_Disabled.htm
A3: PH_Rule_Azure_Entra_ID_Domain_Authentication_Changed | B3: Azure Entra ID: Domain Authentication Changed | C3: New ITDR (7.6.0) | D3: Identity-core | E3: Entra ID, Privilege/account change | F3: Enabled | G3: 10 | H3: High | I3: Security | J3: Correlation | K3: Streaming | L3: Defense Evasion | M3: T1484.002 | N3: Microsoft Entra Activity Logs via Azure Event Hub | O3: MS-Entra-AuditLogs-DirectoryMgmt-Set_domain_authentication-success | Q3: 1 | R3: Filter | S3: — | T3: user,opName,targetDomain | U3: COUNT(*) >= 1 | V3: 300 | X3: Entra Event Hub: AuditLogs | Y3: ea | Z3: Detects when domain authentication settings are modified in Microsoft Entra ID, including switching a domain between managed and federated authentication. An adversary may change domain authentication to redirect authentication to an attacker-controlled identity provider, allowing them to sign in as any user in that domain using forged tokens. This is a known technique for tenant backdooring and persistence. Legitimate administrative activity, approved change windows, service accounts, and known admin tools can also trigger this rule; tune known administrative activity before enabling in production. | AA3: https://filestore.fortinet.com/docs.fortinet.com/fsiem/Public_Resource_Access/7_6_0/rules/PH_RULE_Azure_Entra_ID_Domain_Authentication_Changed.htm
A4: PH_Rule_Azure_Entra_ID_External_User_Added_To_Privileged_Group | B4: Azure Entra ID: External User Added To Privileged Group | C4: New ITDR (7.6.0) | D4: Identity-core | E4: Entra ID, Privilege/account change | F4: Enabled | G4: 8 | H4: Medium | I4: Security | J4: Correlation | K4: Streaming | L4: Persistence | M4: T1098.007 | N4: Microsoft Entra Activity Logs via Azure Event Hub | O4: MS-Entra-AuditLogs-GroupMgmt-Add_member_to_group-success | Q4: 1 | R4: Filter | S4: targetUser CONTAIN "#EXT#" AND groupName CONTAIN "Admin" | T4: user,targetUser,opName,groupName | U4: COUNT(*) >= 1 | V4: 300 | X4: Entra Event Hub: AuditLogs | Y4: ea | Z4: Detects when a guest or external user is added to a group that contains the string "Admin" in Microsoft Entra ID. While adding external users to groups is a routine collaboration activity, adding a guest to a privileged or sensitive group may indicate persistence, privilege escalation, or an attempt to bypass tenant controls by using an outside account. Legitimate B2B collaboration, approved partner onboarding, and known administrative tools can also trigger this rule; tune known administrative activity and approved guest onboarding workflows before enabling in production. | AA4: https://filestore.fortinet.com/docs.fortinet.com/fsiem/Public_Resource_Access/7_6_0/rules/PH_RULE_Azure_Entra_ID_External_User_Added_To_Privileged_Group.htm
A5: PH_Rule_Azure_Entra_ID_MFA_Bypass | B5: Azure Entra ID: MFA Bypass Or Satisfied By Claim | C5: New ITDR (7.6.0) | D5: Identity-core | E5: Entra ID, Credential Access, Privilege/account change | F5: Enabled | G5: 9 | H5: High | I5: Security | J5: Correlation | K5: Streaming | L5: Credential Access | M5: T1556.001 | N5: Microsoft Entra Activity Logs via Azure Event Hub | O5: MS-Entra-SignInLogs-Logon-success | Q5: 1 | R5: Filter | S5: statusDetailedReason REGEXP ".*(?:bypassed|satisfied by claim|not required).*" | T5: user,srcIpAddr,appName,policyStatus | U5: COUNT(*) >= 1 | V5: 300 | X5: Entra Event Hub: SignInLogs (interactive) | Y5: ei | Z5: Detects sign-in events where MFA was bypassed or satisfied by an unexpected claim. Adversaries may modify authentication processes to bypass MFA requirements, allowing unauthorized access without the second factor. | AA5: https://filestore.fortinet.com/docs.fortinet.com/fsiem/Public_Resource_Access/7_6_0/rules/PH_RULE_Azure_Entra_ID_MFA_Bypass.htm
A6: PH_Rule_Azure_Entra_ID_New_Federation_Domain_Added | B6: Azure Entra ID: New Federation Domain Added | C6: New ITDR (7.6.0) | D6: Identity-core | E6: Entra ID, Active Directory, Privilege/account change | F6: Enabled | G6: 10 | H6: High | I6: Security | J6: Correlation | K6: Streaming | L6: Defense Evasion | M6: T1484.002 | N6: Microsoft Entra Activity Logs via Azure Event Hub | O6: MS-Entra-AuditLogs-DirectoryMgmt-Set_federation_settings_on_domain-success | Q6: 1 | R6: Filter | S6: — | T6: user,opName,targetDomain | U6: COUNT(*) >= 1 | V6: 300 | X6: Entra Event Hub: AuditLogs | Y6: ea | Z6: Detects when federation settings are configured on a domain in Microsoft Entra ID. Adversaries may add or modify federation settings to establish an attacker-controlled identity provider for a legitimate domain, allowing them to sign in as any user in the tenant using forged tokens. This is a known technique for persistence and privilege escalation (e.g., Azure AD backdoor federation). Legitimate administrative activity, approved change windows, service accounts, and known admin tools can also trigger this rule; tune known administrative activity before enabling in production. | AA6: https://filestore.fortinet.com/docs.fortinet.com/fsiem/Public_Resource_Access/7_6_0/rules/PH_RULE_Azure_Entra_ID_New_Federation_Domain_Added.htm
A7: PH_Rule_Azure_Entra_ID_OAuth_Secret_Added | B7: Azure Entra ID: OAuth Secret Added | C7: New ITDR (7.6.0) | D7: Identity-core | E7: Entra ID, Privilege/account change | F7: Enabled | G7: 9 | H7: High | I7: Security | J7: Correlation | K7: Streaming | L7: Persistence | M7: T1098.001 | N7: Microsoft Entra Activity Logs via Azure Event Hub | O7: MS-Entra-AuditLogs-ApplicationMgmt-Add_service_principal_credentials-success MS-Entra-AuditLogs-ApplicationMgmt-Update_application_Certificates_and_secrets_Mgmt-success | Q7: 1 | R7: Filter | S7: — | T7: user,targetUser,opName | U7: COUNT(*) >= 1 | V7: 300 | X7: Entra Event Hub: AuditLogs | Y7: ea | Z7: Detects when a credential or secret is added to an OAuth application or service principal. An adversary may add credentials to an application or service principal to establish persistence and access resources using the application's permissions. | AA7: https://filestore.fortinet.com/docs.fortinet.com/fsiem/Public_Resource_Access/7_6_0/rules/PH_RULE_Azure_Entra_ID_OAuth_Secret_Added.htm
A8: PH_Rule_Azure_Entra_ID_User_Added_To_Application_Admin | B8: Azure Entra ID: User Added To Application Admin | C8: New ITDR (7.6.0) | D8: Identity-core | E8: Entra ID, Privilege/account change | F8: Enabled | G8: 9 | H8: High | I8: Security | J8: Correlation | K8: Streaming | L8: Persistence | M8: T1098.003 | N8: Microsoft Entra Activity Logs via Azure Event Hub | O8: MS-Entra-AuditLogs-RoleMgmt-Add_member_to_role-success | Q8: 1 | R8: Filter | S8: role = "Application Administrator" | T8: user,opName,role,targetUser | U8: COUNT(*) >= 1 | V8: 300 | X8: Entra Event Hub: AuditLogs | Y8: ea | Z8: Detects when a user is added to the Application Administrator privileged role in Microsoft Entra ID. An adversary with sufficient privileges may add an account to this role to establish persistence, manage application registrations and service principals, or grant themselves credentials on applications that have sensitive Microsoft Graph permissions. Legitimate administrative activity, approved change windows, service accounts, and known admin tools can also trigger this rule; tune known administrative activity before enabling in production. | AA8: https://filestore.fortinet.com/docs.fortinet.com/fsiem/Public_Resource_Access/7_6_0/rules/PH_RULE_Azure_Entra_ID_User_Added_To_Application_Admin.htm
A9: PH_Rule_Azure_Entra_ID_User_Added_To_Exchange_Admin | B9: Azure Entra ID: User Added To Exchange Admin | C9: New ITDR (7.6.0) | D9: Identity-core | E9: Entra ID, Privilege/account change | F9: Enabled | G9: 9 | H9: High | I9: Security | J9: Correlation | K9: Streaming | L9: Persistence | M9: T1098.003 | N9: Microsoft Entra Activity Logs via Azure Event Hub | O9: MS-Entra-AuditLogs-RoleMgmt-Add_member_to_role-success | Q9: 1 | R9: Filter | S9: role = "Exchange Administrator" | T9: user,opName,role,targetUser | U9: COUNT(*) >= 1 | V9: 300 | X9: Entra Event Hub: AuditLogs | Y9: ea | Z9: Detects when a user is added to the Exchange Administrator role in Microsoft Entra ID. This role can manage all aspects of Exchange Online, including mailboxes, mail flow rules, and transport configuration. An adversary with this role can access email content, create inbox rules for persistence, modify mail flow to intercept or exfiltrate messages, or grant themselves Full Access to any mailbox. Legitimate administrative activity, approved change windows, service accounts, and known admin tools can also trigger this rule; tune known administrative activity before enabling in production. | AA9: https://filestore.fortinet.com/docs.fortinet.com/fsiem/Public_Resource_Access/7_6_0/rules/PH_RULE_Azure_Entra_ID_User_Added_To_Exchange_Admin.htm
A10: PH_Rule_Azure_Entra_ID_User_Added_To_Global_Admin | B10: Azure Entra ID: User Added To Global Admin | C10: New ITDR (7.6.0) | D10: Identity-core | E10: Entra ID, Privilege/account change | F10: Enabled | G10: 10 | H10: High | I10: Security | J10: Correlation | K10: Streaming | L10: Persistence | M10: T1098.003 | N10: Microsoft Entra Activity Logs via Azure Event Hub | O10: MS-Entra-AuditLogs-RoleMgmt-Add_member_to_role-success | Q10: 1 | R10: Filter | S10: role = "Global Administrator" | T10: user,opName,role,targetUser | U10: COUNT(*) >= 1 | V10: 300 | X10: Entra Event Hub: AuditLogs | Y10: ea | Z10: Detects when a user is added to the Global Administrator role in Microsoft Entra ID. This is the most powerful role in Entra ID, providing full access to all administrative features across Microsoft 365 and Azure services. An adversary with this role can perform any administrative action, including managing security controls, accessing all data, creating new admin accounts, and resetting user credentials. Legitimate administrative activity, approved change windows, service accounts, and known admin tools can also trigger this rule; tune known administrative activity before enabling in production. | AA10: https://filestore.fortinet.com/docs.fortinet.com/fsiem/Public_Resource_Access/7_6_0/rules/PH_RULE_Azure_Entra_ID_User_Added_To_Global_Admin.htm
A11: PH_Rule_Azure_Entra_ID_User_Added_To_Privileged_Role_Admin | B11: Azure Entra ID: User Added To Privileged Role Admin | C11: New ITDR (7.6.0) | D11: Identity-core | E11: Entra ID, Privilege/account change | F11: Enabled | G11: 10 | H11: High | I11: Security | J11: Correlation | K11: Streaming | L11: Persistence | M11: T1098.003 | N11: Microsoft Entra Activity Logs via Azure Event Hub | O11: MS-Entra-AuditLogs-RoleMgmt-Add_member_to_role-success | Q11: 1 | R11: Filter | S11: role = "Privileged Role Administrator" | T11: user,opName,role,targetUser | U11: COUNT(*) >= 1 | V11: 300 | X11: Entra Event Hub: AuditLogs | Y11: ea | Z11: Detects when a user is added to the Privileged Administrator role in Microsoft Entra ID. This role can manage all role assignments in Entra ID, including Global Administrator, and is among the most sensitive privileged roles in the tenant. An adversary with control of this role can escalate themselves or others to any privileged role. Legitimate administrative activity, approved change windows, service accounts, and known admin tools can also trigger this rule; tune known administrative activity before enabling in production. | AA11: https://filestore.fortinet.com/docs.fortinet.com/fsiem/Public_Resource_Access/7_6_0/rules/PH_RULE_Azure_Entra_ID_User_Added_To_Privileged_Role_Admin.htm
A12: PH_Rule_Azure_Entra_ID_User_Added_To_Security_Admin | B12: Azure Entra ID: User Added To Security Admin | C12: New ITDR (7.6.0) | D12: Identity-core | E12: Entra ID, Privilege/account change | F12: Enabled | G12: 9 | H12: High | I12: Security | J12: Correlation | K12: Streaming | L12: Persistence | M12: T1098.003 | N12: Microsoft Entra Activity Logs via Azure Event Hub | O12: MS-Entra-AuditLogs-RoleMgmt-Add_member_to_role-success | Q12: 1 | R12: Filter | S12: role = "Security Administrator" | T12: user,opName,role,targetUser | U12: COUNT(*) >= 1 | V12: 300 | X12: Entra Event Hub: AuditLogs | Y12: ea | Z12: Detects when a user is added to the Security Administrator role in Microsoft Entra ID. This role can read all security-related information, manage security configuration, and grant administrative access to other security tools. An adversary with this role can tamper with security controls, alter alerts, or disable security monitoring. Legitimate administrative activity, approved change windows, service accounts, and known admin tools can also trigger this rule; tune known administrative activity before enabling in production. | AA12: https://filestore.fortinet.com/docs.fortinet.com/fsiem/Public_Resource_Access/7_6_0/rules/PH_RULE_Azure_Entra_ID_User_Added_To_Security_Admin.htm
A13: PH_Rule_Linux_etc_shadow_access | B13: Linux: /etc/shadow Access | C13: New ITDR (7.6.0) | D13: Identity-core | E13: Credential Access | F13: Enabled | G13: 9 | H13: High | I13: Security | J13: Correlation | K13: Streaming | L13: Credential Access | M13: T1003.008 | N13: Linux Process Monitoring via Linux Collector | O13: LINUX_Auditd_PATH LINUX_Auditd_SYSCALL LINUX_PROCESS_EXEC | Q13: 1 | R13: Filter | S13: (osObjName="/etc/shadow" OR command REGEXP ".*(?:/etc/shadow|unshadow).*") | T13: hostName,user,procName,command,osObjName | U13: COUNT(*) >= 1 | V13: 300 | X13: Linux Collector: LINUX_Auditd_PATH Linux Collector: LINUX_Auditd_SYSCALL Linux Collector: LINUX_PROCESS_EXEC | Z13: Detects reads or copies of /etc/shadow. The /etc/shadow file stores hashed passwords and is only readable by root. Access by unauthorized users or tools like unshadow may indicate credential dumping activity. | AA13: https://filestore.fortinet.com/docs.fortinet.com/fsiem/Public_Resource_Access/7_6_0/rules/PH_RULE_Linux_etc_shadow_access.htm
A14: PH_Rule_Linux_Root_Equivalent_Account_Command | B14: Linux: Attempt to Create or Modify a Root-Equivalent Account | C14: New ITDR (7.6.0) | D14: Identity-core | E14: Privilege/account change | F14: Enabled | G14: 9 | H14: High | I14: Security | J14: Event-Based | K14: Streaming | L14: Persistence | M14: T1136.001 | N14: Linux Process Monitoring via Linux Collector | O14: LINUX_Auditd_SYSCALL LINUX_PROCESS_EXEC | Q14: 1 | R14: Filter | S14: procName REGEXP "(?i).*(useradd|usermod)$" AND command REGEXP "(?i)\s*(?:-u\s*0|--uid(?:\s+|=)\s*0).*" | T14: hostName,user,procName,command | U14: COUNT(*) >= 1 | V14: 300 | X14: Linux Collector: LINUX_PROCESS_EXEC Linux Collector: LINUX_Auditd_SYSCALL | Z14: Detects execution of useradd or usermod with an option assigning UID 0 to an account. A newly created UID 0 account has root-equivalent privileges, while assigning UID 0 to an existing account can provide persistent privileged access. This rule detects the command attempt and does not necessarily confirm that the account change succeeded. Validate the process exit status and resulting account state in /etc/passwd. Legitimate UID 0 account creation or modification is rare and should be investigated. | AA14: https://filestore.fortinet.com/docs.fortinet.com/fsiem/Public_Resource_Access/7_6_0/rules/PH_RULE_Linux_Root_Equivalent_Account_Command.htm
A15: PH_Rule_Linux_PAM_Configuration_Modified | B15: Linux: PAM Configuration Modified | C15: New ITDR (7.6.0) | D15: Identity-core | E15: Privilege/account change | F15: Enabled | G15: 8 | H15: Medium | I15: Security | J15: Correlation | K15: Streaming | L15: Defense Evasion | M15: T1556.003 | N15: Linux File Monitoring via Linux Collector | O15: FSM_LINUX_FILE_MODIFY | Q15: 1 | R15: Filter | S15: targetOsObjName REGEXP "^/etc/pam\.conf$|^/etc/pam\.d/.*" | T15: hostName,user,targetOsObjName | U15: COUNT(*) >= 1 | V15: 300 | X15: Linux Collector: FSM_LINUX_FILE_MODIFY | Z15: Detects modifications to Linux PAM configuration files under /etc/pam.d/ or to /etc/pam.conf. Adversaries may alter PAM configuration to bypass authentication, capture credentials, execute unauthorized programs during authentication, weaken password controls, or establish persistent access. Legitimate package upgrades, configuration-management systems, and approved authentication-policy changes may also modify these files. Tune approved administrative tools, automation accounts, package managers, and maintenance windows before enabling in production. | AA15: https://filestore.fortinet.com/docs.fortinet.com/fsiem/Public_Resource_Access/7_6_0/rules/PH_RULE_Linux_PAM_Configuration_Modified.htm
A16: PH_Rule_Win_Account_Created_Added_To_Privileged_Group | B16: Windows: Account Created Then Added To Privileged Group | C16: New ITDR (7.6.0) | D16: Identity-core | E16: Active Directory, Windows Security log, Privilege/account change | F16: Enabled | G16: 9 | H16: High | I16: Security | J16: Correlation | K16: Streaming | L16: Persistence | M16: T1136.001, T1136.002, T1098.007 | N16: Microsoft Windows Security Log via OMI or Windows Collector | O16: Win-Security-4720 Win-Security-4728 Win-Security-4732 Win-Security-4756 | Q16: 2 | R16: AccountCreated AND AddedToPrivilegedGroup | S16: [AccountCreated] targetUser IS NOT NULL AND targetUserSID IS NOT NULL [AddedToPrivilegedGroup] targetUser IS NOT NULL AND targetUserSID IS NOT NULL AND groupID REGEXP "(?i)^(?:S-1-5-32-(?:544|548|549|550|551|552|555|556|557|569|573|574|578|580)|S-1-5-21-[0-9]+-[0-9]+-[0-9]+-(?:512|518|519|520|526|527))$" | T16: [AccountCreated] hostName,user,securityId,targetUser,targetUserSID [AddedToPrivilegedGroup] hostName,user,securityId,targetUser,targetUserSID,targetUserGrp,groupID | U16: [AccountCreated] COUNT(*) >= 1 [AddedToPrivilegedGroup] COUNT(*) >= 1 | V16: 1800 | W16: AccountCreated.hostName = AddedToPrivilegedGroup.hostName AND AccountCreated.targetUserSID = AddedToPrivilegedGroup.targetUserSID | X16: Windows Security log: Security 4720 Windows Security log: Security 4728 Windows Security log: Security 4732 Windows Security log: Security 4756 | Y16: a4 | Z16: Detects a newly created local or domain user account that is subsequently added to a commonly privileged Windows or Active Directory security group. Monitored groups include Administrators, Domain Admins, Enterprise Admins, Schema Admins, Group Policy Creator Owners, Key Admins, Enterprise Key Admins, Account Operators, Server Operators, Print Operators, Backup Operators, Replicator, Remote Desktop Users, Network Configuration Operators, Incoming Forest Trust Builders, Cryptographic Operators, Event Log Readers, Certificate Service DCOM Access, Hyper-V Administrators, and Remote Management Users. Adversaries may create an account and grant it elevated, administrative, remote-access, or security-sensitive group membership to establish persistence or gain privileged access. Legitimate provisioning workflows may also trigger this rule; tune approved identity-management systems, service accounts, automation accounts, administrative tools, and change windows before enabling in production. | AA16: https://filestore.fortinet.com/docs.fortinet.com/fsiem/Public_Resource_Access/7_6_0/rules/PH_RULE_Win_Account_Created_Added_To_Privileged_Group.htm
A17: PH_Rule_Win_ADCS_ESC10_Certificate_Mapping_Config_Command | B17: Windows: AD CS ESC10 Certificate Mapping Configuration Changed via Command | C17: New ITDR (7.6.0) | D17: Identity-core | E17: Active Directory, Windows Security log, AD CS | F17: Enabled | G17: 8 | H17: Medium | I17: Security | J17: Correlation | K17: Streaming | L17: Defense Evasion | M17: T1553.004 | N17: Microsoft Windows Powershell Operational Logs via Windows Collector Microsoft Windows Security Log via OMI or Windows Collector Microsoft Windows Sysmon via Windows Collector | O17: Win-PowerShell-4104 Win-Security-4688 Win-Sysmon-1-Create-Process | Q17: 1 | R17: Filter | S17: command REGEXP "(?i).*(?:reg(?:\.exe)?\s+(?:add|delete)|Set-ItemProperty|New-ItemProperty|Remove-ItemProperty).*?(?:StrongCertificateBindingEnforcement|CertificateMappingMethods).*" | T17: hostName,user,procName,command | U17: COUNT(*) >= 1 | V17: 300 | X17: Windows Security log: Security 4688 Sysmon: Sysmon 1 PowerShell Operational: PowerShell 4104 | Y17: s1, s4 | Z17: Detects command-line or PowerShell activity that modifies Windows certificate mapping configuration associated with ESC10, including StrongCertificateBindingEnforcement or CertificateMappingMethods. Weakening these settings may permit certificates to authenticate through weak account mappings. The resulting registry value must be reviewed to determine whether security was weakened. | AA17: https://filestore.fortinet.com/docs.fortinet.com/fsiem/Public_Resource_Access/7_6_0/rules/PH_RULE_Win_ADCS_ESC10_Certificate_Mapping_Config_Command.htm
A18: PH_Rule_Win_ADCS_ESC13_OID_Group_Link_Modified | B18: Windows: AD CS ESC13 OID Group Link Modified | C18: New ITDR (7.6.0) | D18: Identity-core | E18: Active Directory, Windows Security log, AD CS, Credential Access | F18: Enabled | G18: 8 | H18: Medium | I18: Security | J18: Correlation | K18: Streaming | L18: Credential Access | M18: T1606.002 | N18: Microsoft Windows Security Log via OMI or Windows Collector | O18: Win-Security-5136 | Q18: 1 | R18: Filter | S18: propName="msDS-OIDToGroupLink" | T18: hostName,user,osObjName,osObjType,propName,propValue | U18: COUNT(*) >= 1 | V18: 300 | X18: Windows Security log: Security 5136 | Y18: a6 | Z18: Detects modification of the msDS-OIDToGroupLink attribute on an Active Directory issuance-policy OID object. This link can associate a certificate issuance policy with an Active Directory group and may enable ESC13-style privilege escalation when an attacker can enroll for a certificate containing the linked issuance policy. | AA18: https://filestore.fortinet.com/docs.fortinet.com/fsiem/Public_Resource_Access/7_6_0/rules/PH_RULE_Win_ADCS_ESC13_OID_Group_Link_Modified.htm
A19: PH_Rule_Win_ADCS_ESC14_Explicit_Certificate_Mapping_Modified | B19: Windows: AD CS ESC14 Explicit Certificate Mapping Modified | C19: New ITDR (7.6.0) | D19: Identity-core | E19: Active Directory, Windows Security log, AD CS, Credential Access | F19: Enabled | G19: 8 | H19: Medium | I19: Security | J19: Correlation | K19: Streaming | L19: Credential Access | M19: T1606.002 | N19: Microsoft Windows Security Log via OMI or Windows Collector | O19: Win-Security-5136 | Q19: 1 | R19: Filter | S19: propName="altSecurityIdentities" | T19: hostName,user,osObjName,osObjType,propName,propValue | U19: COUNT(*) >= 1 | V19: 300 | X19: Windows Security log: Security 5136 | Y19: a6 | Z19: Detects modification of the altSecurityIdentities attribute on an Active Directory account. This attribute defines explicit certificate-to-account mappings and may be abused in ESC14 to map an attacker-controlled certificate to another user or computer. Legitimate certificate mapping administration may also trigger this rule. | AA19: https://filestore.fortinet.com/docs.fortinet.com/fsiem/Public_Resource_Access/7_6_0/rules/PH_RULE_Win_ADCS_ESC14_Explicit_Certificate_Mapping_Modified.htm
A20: PH_Rule_Win_ADCS_ESC16_SID_Extension_Disabled_Command | B20: Windows: AD CS ESC16 SID Security Extension Disabled via Command | C20: New ITDR (7.6.0) | D20: Identity-core | E20: Active Directory, Windows Security log, AD CS | F20: Enabled | G20: 9 | H20: High | I20: Security | J20: Correlation | K20: Streaming | L20: Defense Evasion | M20: T1553.004 | N20: Microsoft Windows Powershell Operational Logs via Windows Collector Microsoft Windows Security Log via OMI or Windows Collector Microsoft Windows Sysmon via Windows Collector | O20: Win-PowerShell-4104 Win-Security-4688 Win-Sysmon-1-Create-Process | Q20: 1 | R20: Filter | S20: command REGEXP "(?i).*(?:certutil(?:\.exe)?.*-setreg.*DisableExtensionList|Set-ItemProperty.*DisableExtensionList).*1\.3\.6\.1\.4\.1\.311\.25\.2.*" | T20: hostName,user,procName,command | U20: COUNT(*) >= 1 | V20: 300 | X20: Windows Security log: Security 4688 Sysmon: Sysmon 1 PowerShell Operational: PowerShell 4104 | Y20: s1, s4 | Z20: Detects certutil or PowerShell command activity that adds the szOID_NTDS_CA_SECURITY_EXT OID to the certification authority DisableExtensionList. Disabling this extension prevents newly issued certificates from containing the Active Directory SID security extension and may enable ESC16-style certificate mapping abuse. | AA20: https://filestore.fortinet.com/docs.fortinet.com/fsiem/Public_Resource_Access/7_6_0/rules/PH_RULE_Win_ADCS_ESC16_SID_Extension_Disabled_Command.htm
A21: PH_Rule_Win_ADCS_ESC2_Any_Purpose_EKU_Added | B21: Windows: AD CS ESC2 Any Purpose EKU Added to Certificate Template | C21: New ITDR (7.6.0) | D21: Identity-core | E21: Active Directory, Windows Security log, AD CS, Credential Access | F21: Enabled | G21: 7 | H21: Medium | I21: Security | J21: Correlation | K21: Streaming | L21: Credential Access | M21: T1606.002 | N21: Microsoft Windows Security Log via OMI or Windows Collector | O21: Win-Security-5136 | Q21: 1 | R21: Filter | S21: osObjType="pKICertificateTemplate" AND propName="pKIExtendedKeyUsage" AND propValue REGEXP "(?i).*(?:Any Purpose|2\.5\.29\.37\.0).*" | T21: hostName,user,osObjName,propName,propValue | U21: COUNT(*) >= 1 | V21: 300 | X21: Windows Security log: Security 5136 | Y21: a6 | Z21: Detects modification of an AD CS certificate template to include the Any Purpose extended key usage OID. This configuration is associated with ESC2 because certificates issued from the template may be usable for authentication or other unintended purposes. Additional review of enrollment permissions and template settings is required to confirm exploitability. | AA21: https://filestore.fortinet.com/docs.fortinet.com/fsiem/Public_Resource_Access/7_6_0/rules/PH_RULE_Win_ADCS_ESC2_Any_Purpose_EKU_Added.htm
A22: PH_Rule_Win_ADCS_ESC3_Enrollment_Agent_EKU_Added | B22: Windows: AD CS ESC3 Enrollment Agent EKU Added to Certificate Template | C22: New ITDR (7.6.0) | D22: Identity-core | E22: Active Directory, Windows Security log, AD CS, Credential Access | F22: Enabled | G22: 8 | H22: Medium | I22: Security | J22: Correlation | K22: Streaming | L22: Credential Access | M22: T1606.002 | N22: Microsoft Windows Security Log via OMI or Windows Collector | O22: Win-Security-5136 | Q22: 1 | R22: Filter | S22: osObjType="pKICertificateTemplate" AND propName="pKIExtendedKeyUsage" AND propValue REGEXP "(?i).*(?:Certificate Request Agent|1\.3\.6\.1\.4\.1\.311\.20\.2\.1).*" | T22: hostName,user,osObjName,propName,propValue | U22: COUNT(*) >= 1 | V22: 300 | X22: Windows Security log: Security 5136 | Y22: a6 | Z22: Detects modification of an AD CS certificate template to include the Certificate Request Agent extended key usage. This EKU permits an issued certificate to sign certificate requests on behalf of other users and is associated with ESC3. Additional review of enrollment-agent restrictions, issuance requirements, and enrollment permissions is required to confirm exploitability. | AA22: https://filestore.fortinet.com/docs.fortinet.com/fsiem/Public_Resource_Access/7_6_0/rules/PH_RULE_Win_ADCS_ESC3_Enrollment_Agent_EKU_Added.htm
A23: PH_Rule_Win_ADCS_ESC5_PKI_Object_ACL_Modified | B23: Windows: AD CS ESC5 PKI Object ACL Modified | C23: New ITDR (7.6.0) | D23: Identity-core | E23: Active Directory, Windows Security log, AD CS, Credential Access | F23: Enabled | G23: 8 | H23: Medium | I23: Security | J23: Correlation | K23: Streaming | L23: Credential Access | M23: T1606.002 | N23: Microsoft Windows Security Log via OMI or Windows Collector | O23: Win-Security-5136 | Q23: 1 | R23: Filter | S23: propName="nTSecurityDescriptor" AND osObjName REGEXP "(?i).*(?:CN=Public Key Services|CN=Enrollment Services|CN=Certificate Templates|CN=Certification Authorities|CN=AIA|CN=CDP).*" | T23: hostName,user,osObjName,osObjType,propName | U23: COUNT(*) >= 1 | V23: 300 | X23: Windows Security log: Security 5136 | Y23: a6 | Z23: Detects modification of the security descriptor on an Active Directory PKI object beneath the Public Key Services configuration container. Unauthorized control of PKI objects may enable ESC5-style abuse, including modification of certificate templates, certification authorities, enrollment services, or other certificate infrastructure configuration. | AA23: https://filestore.fortinet.com/docs.fortinet.com/fsiem/Public_Resource_Access/7_6_0/rules/PH_RULE_Win_ADCS_ESC5_PKI_Object_ACL_Modified.htm
A24: PH_Rule_Win_ADCS_ESC7_CA_Security_Permissions_Changed | B24: Windows: AD CS ESC7 CA Security Permissions Changed | C24: New ITDR (7.6.0) | D24: Identity-core | E24: Active Directory, Windows Security log, AD CS, Credential Access | F24: Enabled | G24: 8 | H24: Medium | I24: Security | J24: Correlation | K24: Streaming | L24: Credential Access | M24: T1606.002 | N24: Microsoft Windows Security Log via OMI or Windows Collector | O24: Win-Security-4882 | Q24: 1 | R24: Filter | S24: — | T24: hostName,user | U24: COUNT(*) >= 1 | V24: 300 | X24: Windows Security log: Security 4882 | Y24: ca | Z24: Detects a change to Certification Authority security permissions. Such changes may grant or alter CA administration rights such as Manage CA or Manage Certificates and may enable ESC7-style privilege escalation. Legitimate PKI administration may also generate this event, and the resulting access control changes should be reviewed. | AA24: https://filestore.fortinet.com/docs.fortinet.com/fsiem/Public_Resource_Access/7_6_0/rules/PH_RULE_Win_ADCS_ESC7_CA_Security_Permissions_Changed.htm
A25: PH_Rule_Win_ADCS_Web_Enrollment_Certificate_Request | B25: Windows: AD CS Web Enrollment Certificate Request | C25: New ITDR (7.6.0) | D25: Identity-core | E25: Active Directory, AD CS, Credential Access | F25: Enabled | G25: 7 | H25: Medium | I25: Security | J25: Correlation | K25: Streaming | L25: Credential Access | M25: T1606.002 | N25: Microsoft IIS via Windows Collector | O25: IIS-Web-Bad-Request IIS-Web-Client-Access-Denied IIS-Web-Client-Error IIS-Web-Forbidden-Access-Denied IIS-Web-Request-Redirect IIS-Web-Request-Success IIS-Web-Server-Error | Q25: 1 | R25: Filter | S25: httpMethod IN ("POST","post") AND uriStem REGEXP "(?i)^.*/certsrv/(?:certfnsh\.asp|certnew\.cer)$" | T25: reptDevName,srcIpAddr,user,httpMethod,uriStem | U25: COUNT(*) >= 1 | V25: 300 | X25: IIS log: IIS web request | Z25: Detects access to Active Directory Certificate Services Web Enrollment certificate-request submission endpoints. Web enrollment may be used legitimately, but unexpected requests from servers, network appliances, unmanaged systems, or other unusual sources should be investigated for possible NTLM relay or unauthorized certificate enrollment. | AA25: https://filestore.fortinet.com/docs.fortinet.com/fsiem/Public_Resource_Access/7_6_0/rules/PH_RULE_Win_ADCS_Web_Enrollment_Certificate_Request.htm
A26: PH_Rule_Win_AdminSDHolder_Modified | B26: Windows: AdminSDHolder Modified | C26: New ITDR (7.6.0) | D26: Identity-core | E26: Active Directory, Windows Security log, Privilege/account change | F26: Enabled | G26: 9 | H26: High | I26: Security | J26: Correlation | K26: Streaming | L26: Persistence | M26: T1098.001 | N26: Microsoft Windows Security Log via OMI or Windows Collector | O26: Win-Security-5136 | Q26: 1 | R26: Filter | S26: osObjName REGEXP ".*AdminSDHolder.*" | T26: hostName,user,osObjName,propName,propValue | U26: COUNT(*) >= 1 | V26: 300 | X26: Windows Security log: Security 5136 | Y26: a6 | Z26: Detects changes to the AdminSDHolder object in Active Directory. The AdminSDHolder object is a template for permissions on protected accounts (Domain Admins, Enterprise Admins, etc). An adversary may modify AdminSDHolder to establish persistence by granting privileges to non-privileged accounts. | AA26: https://filestore.fortinet.com/docs.fortinet.com/fsiem/Public_Resource_Access/7_6_0/rules/PH_RULE_Win_AdminSDHolder_Modified.htm
A27: PH_Rule_Win_Auth_Package_Modified | B27: Windows: Authentication Package Modified | C27: New ITDR (7.6.0) | D27: Identity-core | E27: Windows Security log | F27: Enabled | G27: 9 | H27: High | I27: Security | J27: Correlation | K27: Streaming | L27: Persistence | M27: T1547.002 | N27: Microsoft Windows Powershell Operational Logs via Windows Collector Microsoft Windows Security Log via OMI or Windows Collector Microsoft Windows Sysmon via Windows Collector | O27: Win-PowerShell-4104 Win-Security-4688 Win-Sysmon-1-Create-Process | Q27: 1 | R27: Filter | S27: command REGEXP ".*(?:Security Packages|Authentication Packages).*" | T27: hostName,user,procName,command | U27: COUNT(*) >= 1 | V27: 300 | X27: Windows Security log: Security 4688 Sysmon: Sysmon 1 PowerShell Operational: PowerShell 4104 | Y27: s1, s4 | Z27: Detects command lines or script blocks that modify LSASS authentication packages by writing to the Security Packages or Authentication Packages registry values. An adversary may register a malicious authentication package to load code into LSASS at boot, enabling credential theft and persistence. | AA27: https://filestore.fortinet.com/docs.fortinet.com/fsiem/Public_Resource_Access/7_6_0/rules/PH_RULE_Win_Auth_Package_Modified.htm
A28: PH_Rule_Win_BloodHound_SharpHound_Execution | B28: Windows: BloodHound or SharpHound Execution | C28: New ITDR (7.6.0) | D28: Identity-core | E28: Active Directory, Windows Security log | F28: Enabled | G28: 9 | H28: High | I28: Security | J28: Correlation | K28: Streaming | L28: Discovery | M28: T1087.002 | N28: Microsoft Windows Powershell Operational Logs via Windows Collector Microsoft Windows Security Log via OMI or Windows Collector Microsoft Windows Sysmon via Windows Collector | O28: Win-PowerShell-4104 Win-Security-4688 Win-Sysmon-1-Create-Process | Q28: 1 | R28: Filter | S28: (procName REGEXP "(?i).*(?:SharpHound|BloodHound)(?:\.exe|\.ps1)?$" OR command REGEXP "(?i).*(?:SharpHound|BloodHound|Invoke-BloodHound|--?CollectionMethods?).*") | T28: hostName,user,procName,command | U28: COUNT(*) >= 1 | V28: 300 | X28: Windows Security log: Security 4688 Sysmon: Sysmon 1 PowerShell Operational: PowerShell 4104 | Y28: s1, s4 | Z28: Detects process names, command lines, or PowerShell script content containing explicit BloodHound or SharpHound collection-tool indicators. These tools collect Active Directory relationship, account, group, session, permission, and trust information for attack-path analysis. Authorized penetration testing and identity-security assessment activity may also trigger this rule. | AA28: https://filestore.fortinet.com/docs.fortinet.com/fsiem/Public_Resource_Access/7_6_0/rules/PH_RULE_Win_BloodHound_SharpHound_Execution.htm
A29: PH_Rule_Win_CA_Configuration_Changed | B29: Windows: CA Configuration Changed | C29: New ITDR (7.6.0) | D29: Identity-core | E29: Active Directory, Windows Security log, AD CS | F29: Enabled | G29: 9 | H29: High | I29: Security | J29: Correlation | K29: Streaming | L29: Resource Development | M29: T1587.003 | N29: Microsoft Windows Security Log via OMI or Windows Collector | O29: Win-Security-4890 Win-Security-4891 Win-Security-4892 Win-Security-4893 Win-Security-4894 | Q29: 1 | R29: Filter | S29: — | T29: hostName,user | U29: COUNT(*) >= 1 | V29: 300 | X29: Windows Security log: Security 4890 Windows Security log: Security 4891 Windows Security log: Security 4892 Windows Security log: Security 4893 Windows Security log: Security 4894 | Y29: ca | Z29: Detects changes to Active Directory Certificate Services certificate authority configuration, including certificate manager settings, configuration entries, CA properties, and key archival or import operations. Such changes may indicate PKI tampering, unauthorized CA reconfiguration, or preparation for certificate-based privilege escalation. Legitimate PKI administration, scheduled CA maintenance, and approved change-window activity may also generate these events. | AA29: https://filestore.fortinet.com/docs.fortinet.com/fsiem/Public_Resource_Access/7_6_0/rules/PH_RULE_Win_CA_Configuration_Changed.htm
A30: PH_Rule_Win_Certificate_Template_Modified | B30: Windows: Certificate Template Modified | C30: New ITDR (7.6.0) | D30: Identity-core | E30: Active Directory, Windows Security log, AD CS, Credential Access | F30: Enabled | G30: 8 | H30: Medium | I30: Security | J30: Correlation | K30: Streaming | L30: Credential Access | M30: T1606.002 | N30: Microsoft Windows Security Log via OMI or Windows Collector | O30: Win-Security-5136 | Q30: 1 | R30: Filter | S30: osObjType = "pKICertificateTemplate" | T30: hostName,user,osObjName,propName | U30: COUNT(*) >= 1 | V30: 300 | X30: Windows Security log: Security 5136 | Y30: a6 | Z30: Detects modification of an Active Directory Certificate Services certificate template. Certificate template changes can alter enrollment permissions, authentication capabilities, subject-name handling, issuance requirements, or other security-sensitive properties. Legitimate PKI administration may also trigger this rule. | AA30: https://filestore.fortinet.com/docs.fortinet.com/fsiem/Public_Resource_Access/7_6_0/rules/PH_RULE_Win_Certificate_Template_Modified.htm
A31: PH_Rule_Win_Certipy_Credential_Abuse | B31: Windows: Certipy Credential Abuse | C31: New ITDR (7.6.0) | D31: Identity-core | E31: Active Directory, Windows Security log, AD CS, Credential Access | F31: Enabled | G31: 9 | H31: High | I31: Security | J31: Correlation | K31: Streaming | L31: Credential Access | M31: T1606.002 | N31: Microsoft Windows Powershell Operational Logs via Windows Collector Microsoft Windows Security Log via OMI or Windows Collector Microsoft Windows Sysmon via Windows Collector | O31: Win-PowerShell-4104 Win-Security-4688 Win-Sysmon-1-Create-Process | Q31: 1 | R31: Filter | S31: command REGEXP ".*certipy.*" | T31: hostName,user,procName,command | U31: COUNT(*) >= 1 | V31: 300 | X31: Windows Security log: Security 4688 Sysmon: Sysmon 1 PowerShell Operational: PowerShell 4104 | Y31: s1, s4 | Z31: Detects command lines or process names associated with Certipy credential abuse. Certipy is a Python tool for enumerating and abusing Active Directory Certificate Services (AD CS), enabling attacks such as certificate template exploitation, ESC1-ESC8 abuse, and forged certificate-based authentication to escalate privileges and impersonate users. | AA31: https://filestore.fortinet.com/docs.fortinet.com/fsiem/Public_Resource_Access/7_6_0/rules/PH_RULE_Win_Certipy_Credential_Abuse.htm
A32: PH_Rule_Win_Comsvcs_MiniDump_LSASS | B32: Windows: comsvcs.dll MiniDump LSASS | C32: New ITDR (7.6.0) | D32: Identity-core | E32: Windows Security log, Credential Access | F32: Enabled | G32: 9 | H32: High | I32: Security | J32: Correlation | K32: Streaming | L32: Credential Access | M32: T1003.001 | N32: Microsoft Windows Security Log via OMI or Windows Collector Microsoft Windows Sysmon via Windows Collector | O32: Win-Security-4688 Win-Sysmon-1-Create-Process | Q32: 1 | R32: Filter | S32: procName REGEXP ".*rundll32.exe$" AND command REGEXP ".*comsvcs.dll.*MiniDump.*lsass.*" | T32: hostName,user,procName,command | U32: COUNT(*) >= 1 | V32: 300 | X32: Windows Security log: Security 4688 Sysmon: Sysmon 1 | Y32: s1 | Z32: Detects rundll32 loading comsvcs.dll to invoke MiniDump against LSASS. This technique abuses the built-in Windows comsvcs.dll MiniDump export to dump LSASS process memory without dropping procdump, evading simple tool-name-based detections and enabling credential theft. | AA32: https://filestore.fortinet.com/docs.fortinet.com/fsiem/Public_Resource_Access/7_6_0/rules/PH_RULE_Win_Comsvcs_MiniDump_LSASS.htm
A33: PH_Rule_Win_Domain_Trust_Modified | B33: Windows: Domain Trust Modified | C33: New ITDR (7.6.0) | D33: Identity-core | E33: Active Directory, Windows Security log | F33: Enabled | G33: 9 | H33: High | I33: Security | J33: Correlation | K33: Streaming | L33: Discovery | M33: T1482 | N33: Microsoft Windows Security Log via OMI or Windows Collector | O33: Win-Security-4706 Win-Security-4707 Win-Security-4716 Win-Security-5136 | Q33: 1 | R33: Filter | S33: ((osObjType REGEXP ".*trustedDomain.*")) | T33: hostName,user,osObjName,osObjType | U33: COUNT(*) >= 1 | V33: 300 | X33: Windows Security log: Security 4706 Windows Security log: Security 4707 Windows Security log: Security 4716 Windows Security log: Security 5136 | Y33: a6 | Z33: Detects domain trust object creation or modification. An adversary may create or modify domain trusts to enable lateral movement across domains or facilitate credential theft and discovery. | AA33: https://filestore.fortinet.com/docs.fortinet.com/fsiem/Public_Resource_Access/7_6_0/rules/PH_RULE_Win_Domain_Trust_Modified.htm
A34: PH_Rule_Win_ESC1_Relevant_Template_Attribute_Modified | B34: Windows: ESC1-Relevant Certificate Template Attribute Modified | C34: New ITDR (7.6.0) | D34: Identity-core | E34: Active Directory, Windows Security log, AD CS, Credential Access | F34: Enabled | G34: 9 | H34: High | I34: Security | J34: Correlation | K34: Streaming | L34: Credential Access | M34: T1606.002 | N34: Microsoft Windows Security Log via OMI or Windows Collector | O34: Win-Security-5136 | Q34: 1 | R34: Filter | S34: osObjType = "pKICertificateTemplate" AND propName REGEXP "(?i)^(?:msPKI-Certificate-Name-Flag|pKIExtendedKeyUsage)$" | T34: hostName,user,osObjName,propName,propValue | U34: COUNT(*) >= 1 | V34: 300 | X34: Windows Security log: Security 5136 | Y34: a6 | Z34: Detects modification of certificate template attributes associated with ESC1 exposure, including subject-name handling and extended key usage. This event does not by itself prove that the template is exploitable; the resulting template configuration, enrollment permissions, issuance requirements, and authentication-capable EKUs should be reviewed. | AA34: https://filestore.fortinet.com/docs.fortinet.com/fsiem/Public_Resource_Access/7_6_0/rules/PH_RULE_Win_ESC1_Relevant_Template_Attribute_Modified.htm
A35: PH_Rule_Win_ESC4_Certificate_Template_ACL_Modified | B35: Windows: ESC4 Certificate Template ACL Modified | C35: New ITDR (7.6.0) | D35: Identity-core | E35: Active Directory, Windows Security log, AD CS, Credential Access | F35: Enabled | G35: 9 | H35: High | I35: Security | J35: Correlation | K35: Streaming | L35: Credential Access | M35: T1606.002 | N35: Microsoft Windows Security Log via OMI or Windows Collector | O35: Win-Security-5136 | Q35: 1 | R35: Filter | S35: osObjType = "pKICertificateTemplate" AND propName REGEXP "(?i)^nTSecurityDescriptor$" | T35: hostName,user,osObjName,propName | U35: COUNT(*) >= 1 | V35: 300 | X35: Windows Security log: Security 5136 | Y35: a6 | Z35: Detects modification of the security descriptor on an Active Directory Certificate Services certificate template. An unauthorized principal with template write permissions may alter security-sensitive template settings or enrollment permissions, creating an ESC4 abuse path. Review the resulting access control entries and the account that performed the change. | AA35: https://filestore.fortinet.com/docs.fortinet.com/fsiem/Public_Resource_Access/7_6_0/rules/PH_RULE_Win_ESC4_Certificate_Template_ACL_Modified.htm
A36: PH_Rule_Win_ESC6_EDITF_ATTRIBUTESUBJECTALTNAME2_Enabled | B36: Windows: ESC6 EDITF-ATTRIBUTESUBJECTALTNAME2 Enabled with Certutil | C36: New ITDR (7.6.0) | D36: Identity-core | E36: Windows Security log, AD CS, Credential Access | F36: Enabled | G36: 10 | H36: High | I36: Security | J36: Correlation | K36: Streaming | L36: Credential Access | M36: T1606.002 | N36: Microsoft Windows Powershell Operational Logs via Windows Collector Microsoft Windows Security Log via OMI or Windows Collector Microsoft Windows Sysmon via Windows Collector | O36: Win-PowerShell-4104 Win-Security-4688 Win-Sysmon-1-Create-Process | Q36: 1 | R36: Filter | S36: command REGEXP "(?i).*certutil(?:\.exe)?.*-setreg.*policy\\EditFlags.*\+EDITF_ATTRIBUTESUBJECTALTNAME2.*" | T36: hostName,user,procName,command | U36: COUNT(*) >= 1 | V36: 300 | X36: Windows Security log: Security 4688 Sysmon: Sysmon 1 PowerShell Operational: PowerShell 4104 | Y36: s1, s4 | Z36: Detects a certutil command that enables the EDITF_ATTRIBUTESUBJECTALTNAME2 certification authority policy flag. This setting permits certificate requesters to provide subject alternative names and can create an ESC6 abuse path when authentication-capable certificate templates are available. Emergency or approved PKI configuration changes may also trigger this rule. | AA36: https://filestore.fortinet.com/docs.fortinet.com/fsiem/Public_Resource_Access/7_6_0/rules/PH_RULE_Win_ESC6_EDITF_ATTRIBUTESUBJECTALTNAME2_Enabled.htm
A37: PH_Rule_Win_Kerberoasting_Multiple_SPNs | B37: Windows: Kerberoasting Multiple SPNs | C37: New ITDR (7.6.0) | D37: Identity-core | E37: Active Directory, Windows Security log, Kerberos, Credential Access | F37: Enabled | G37: 7 | H37: Medium | I37: Security | J37: Correlation | K37: Streaming | L37: Credential Access | M37: T1558.003 | N37: Microsoft Windows Security Log via OMI or Windows Collector | O37: Win-Security-4769-success | Q37: 1 | R37: Filter | S37: serviceName IS NOT NULL AND serviceName != "krbtgt" | T37: user,srcIpAddr | U37: COUNT(DISTINCT serviceName) >= 10 | V37: 600 | X37: Windows Security log: Security 4769 | Y37: a2 | Z37: Detects a single account requesting successful Kerberos service tickets for many distinct service names within a short period. This behavior may indicate Kerberoasting, in which an adversary obtains service-ticket material for offline password cracking, but it may also result from legitimate automated or service-discovery activity. Events are aggregated by user and source IP rather than domain controller hostname so that a single burst distributed across multiple domain controllers is not split into separate groups. | AA37: https://filestore.fortinet.com/docs.fortinet.com/fsiem/Public_Resource_Access/7_6_0/rules/PH_RULE_Win_Kerberoasting_Multiple_SPNs.htm
... A46: PH_Rule_Win_Procdump_LSASS_Dump | B46: Windows: Procdump LSASS Dump | C46: New ITDR (7.6.0) | D46: Identity-core | E46: Windows Security log, Kerberos, Credential Access | F46: Enabled | G46: 9 | H46: High | I46: Security | J46: Correlation | K46: Streaming | L46: Credential Access | M46: T1003.001 | N46: Microsoft Windows Security Log via OMI or Windows Collector Microsoft Windows Sysmon via Windows Collector | O46: Win-Security-4688 Win-Sysmon-1-Create-Process | Q46: 1 | R46: Filter | S46: procName REGEXP ".*procdump.*" AND command REGEXP ".*lsass.*" | T46: hostName,user,procName,command | U46: COUNT(*) >= 1 | V46: 300 | X46: Windows Security log: Security 4688 Sysmon: Sysmon 1 | Y46: s1 | Z46: Detects ProcDump targeting the LSASS process. ProcDump (Sysinternals) is commonly abused by adversaries to create a minidump of LSASS memory, enabling extraction of credentials, NTLM hashes, and Kerberos tickets for credential theft and lateral movement. | AA46: https://filestore.fortinet.com/docs.fortinet.com/fsiem/Public_Resource_Access/7_6_0/rules/PH_RULE_Win_Procdump_LSASS_Dump.htm
A47: PH_Rule_Win_PsExec_Service_Creation | B47: Windows: PsExec Service Creation | C47: New ITDR (7.6.0) | D47: Identity-core | F47: Enabled | G47: 9 | H47: High | I47: Security | J47: Correlation | K47: Streaming | L47: Execution | M47: T1569.002 | N47: Microsoft Windows System Log via OMI or Windows Collector | O47: Win-System-Service-Control-Manager-7045 | Q47: 1 | R47: Filter | S47: (serviceName REGEXP "(?i)^(?:PSEXESVC|PAExec.*|RemComSvc.*)$" OR serviceFileName REGEXP "(?i).*[\\/](?:PSEXESVC|PAExec[^\\/]*|RemComSvc[^\\/]*)\.exe(?:\s.*)?$") | T47: hostName,user,serviceName,serviceFileName | U47: COUNT(*) >= 1 | V47: 300 | X47: Windows System log: System 7045 | Z47: Detects PsExec-style service installation. Adversaries use PsExec and similar tools (PAExec, RemCom) to execute commands remotely by installing and starting a temporary service, enabling lateral movement across hosts. | AA47: https://filestore.fortinet.com/docs.fortinet.com/fsiem/Public_Resource_Access/7_6_0/rules/PH_RULE_Win_PsExec_Service_Creation.htm
A48: PH_Rule_Win_Pypykatz_Credential_Dumping | B48: Windows: Pypykatz Credential Dumping via Process or PowerShell | C48: New ITDR (7.6.0) | D48: Identity-core | E48: Windows Security log, Credential Access | F48: Enabled | G48: 9 | H48: High | I48: Security | J48: Correlation | K48: Streaming | L48: Credential Access | M48: T1003.001 | N48: Microsoft Windows Powershell Operational Logs via Windows Collector Microsoft Windows Security Log via OMI or Windows Collector Microsoft Windows Sysmon via Windows Collector | O48: Win-PowerShell-4104 Win-Security-4688 Win-Sysmon-1-Create-Process | Q48: 1 | R48: Filter | S48: (command REGEXP ".*pypykatz.*" OR procName REGEXP ".*pypykatz.*") | T48: hostName,user,procName,command | U48: COUNT(*) >= 1 | V48: 300 | X48: Windows Security log: Security 4688 Sysmon: Sysmon 1 PowerShell Operational: PowerShell 4104 | Y48: s1, s4 | Z48: Detects command lines or process names associated with Pypykatz credential dumping. Pypykatz is a Python implementation of Mimikatz that extracts credentials from LSASS memory and other credential stores. | AA48: https://filestore.fortinet.com/docs.fortinet.com/fsiem/Public_Resource_Access/7_6_0/rules/PH_RULE_Win_Pypykatz_Credential_Dumping.htm
A49: PH_Rule_Win_RBCD_Attribute_Modified | B49: Windows: RBCD Attribute Modified | C49: New ITDR (7.6.0) | D49: Identity-core | E49: Active Directory, Windows Security log, Privilege/account change | F49: Enabled | G49: 9 | H49: High | I49: Security | J49: Correlation | K49: Streaming | L49: Persistence | M49: T1098.007 | N49: Microsoft Windows Security Log via OMI or Windows Collector | O49: Win-Security-5136 | Q49: 1 | R49: Filter | S49: propName="msDS-AllowedToActOnBehalfOfOtherIdentity" | T49: hostName,user,osObjName,propName | U49: COUNT(*) >= 1 | V49: 300 | X49: Windows Security log: Security 5136 | Y49: a6 | Z49: Detects modification of the msDS-AllowedToActOnBehalfOfOtherIdentity attribute, which configures resource-based constrained delegation (RBCD). An adversary may set RBCD on a target computer to allow a compromised account to impersonate any user to that system. | AA49: https://filestore.fortinet.com/docs.fortinet.com/fsiem/Public_Resource_Access/7_6_0/rules/PH_RULE_Win_RBCD_Attribute_Modified.htm
A50: PH_Rule_Win_Rubeus_Kerberos_Abuse | B50: Windows: Rubeus Kerberos Abuse | C50: New ITDR (7.6.0) | D50: Identity-core | E50: Windows Security log, Kerberos, Credential Access | F50: Enabled | G50: 9 | H50: High | I50: Security | J50: Correlation | K50: Streaming | L50: Credential Access | M50: T1558.003 | N50: Microsoft Windows Powershell Operational Logs via Windows Collector Microsoft Windows Security Log via OMI or Windows Collector Microsoft Windows Sysmon via Windows Collector | O50: Win-PowerShell-4104 Win-Security-4688 Win-Sysmon-1-Create-Process | Q50: 1 | R50: Filter | S50: command REGEXP ".*Rubeus.*" | T50: hostName,user,procName,command | U50: COUNT(*) >= 1 | V50: 300 | X50: Windows Security log: Security 4688 Sysmon: Sysmon 1 PowerShell Operational: PowerShell 4104 | Y50: s1, s4 | Z50: Detects command lines or process names associated with Rubeus Kerberos abuse. Rubeus is a toolkit for Kerberos interaction and abuse, enabling attacks such as Kerberoasting, AS-REP roasting, ticket forging (golden/silver tickets), pass-the-ticket, and credential harvesting from memory. | AA50: https://filestore.fortinet.com/docs.fortinet.com/fsiem/Public_Resource_Access/7_6_0/rules/PH_RULE_Win_Rubeus_Kerberos_Abuse.htm
A51: PH_Rule_Win_SafetyKatz_Credential_Dumping | B51: Windows: SafetyKatz Credential Dumping | C51: New ITDR (7.6.0) | D51: Identity-core | E51: Windows Security log, Credential Access | F51: Enabled | G51: 9 | H51: High | I51: Security | J51: Correlation | K51: Streaming | L51: Credential Access | M51: T1003.001 | N51: Microsoft Windows Powershell Operational Logs via Windows Collector Microsoft Windows Security Log via OMI or Windows Collector Microsoft Windows Sysmon via Windows Collector | O51: Win-PowerShell-4104 Win-Security-4688 Win-Sysmon-1-Create-Process | Q51: 1 | R51: Filter | S51: command REGEXP ".*SafetyKatz.*" | T51: hostName,user,procName,command | U51: COUNT(*) >= 1 | V51: 300 | X51: Windows Security log: Security 4688 Sysmon: Sysmon 1 PowerShell Operational: PowerShell 4104 | Y51: s1, s4 | Z51: Detects command lines or process names associated with SafetyKatz credential dumping. SafetyKatz is a combination of a modified version of the Mimikatz project and a .NET PE Loader that dumps credentials from memory. | AA51: https://filestore.fortinet.com/docs.fortinet.com/fsiem/Public_Resource_Access/7_6_0/rules/PH_RULE_Win_SafetyKatz_Credential_Dumping.htm
A52: PH_Rule_Win_Schema_Modification | B52: Windows: Schema Modification | C52: New ITDR (7.6.0) | D52: Identity-core | E52: Active Directory, Windows Security log, Privilege/account change | F52: Enabled | G52: 9 | H52: High | I52: Security | J52: Correlation | K52: Streaming | L52: Persistence | M52: T1098.001 | N52: Microsoft Windows Security Log via OMI or Windows Collector | O52: Win-Security-5136 | Q52: 1 | R52: Filter | S52: osObjName REGEXP ".*CN=Schema,CN=Configuration.*" | T52: hostName,user,osObjName,propName,propValue | U52: COUNT(*) >= 1 | V52: 300 | X52: Windows Security log: Security 5136 | Y52: a6 | Z52: Detects Active Directory schema changes. The schema defines all object classes and attributes that can be stored in the directory. An adversary may modify the schema to establish persistence or introduce backdoor objects into the directory. | AA52: https://filestore.fortinet.com/docs.fortinet.com/fsiem/Public_Resource_Access/7_6_0/rules/PH_RULE_Win_Schema_Modification.htm
A53: PH_Rule_Win_Secretsdump_Execution | B53: Windows: Secretsdump Execution via Process or PowerShell | C53: New ITDR (7.6.0) | D53: Identity-core | E53: Active Directory, Windows Security log, Credential Access | F53: Enabled | G53: 9 | H53: High | I53: Security | J53: Correlation | K53: Streaming | L53: Credential Access | M53: T1003.003 | N53: Microsoft Windows Powershell Operational Logs via Windows Collector Microsoft Windows Security Log via OMI or Windows Collector Microsoft Windows Sysmon via Windows Collector | O53: Win-PowerShell-4104 Win-Security-4688 Win-Sysmon-1-Create-Process | Q53: 1 | R53: Filter | S53: (command REGEXP ".*secretsdump.*" OR procName REGEXP ".*secretsdump.*") | T53: hostName,user,procName,command | U53: COUNT(*) >= 1 | V53: 300 | X53: Windows Security log: Security 4688 Sysmon: Sysmon 1 PowerShell Operational: PowerShell 4104 | Y53: s1, s4 | Z53: Detects command lines or process names associated with Impacket's secretsdump.py. This tool remotely dumps NTDS.dit and LSA secrets, often used after compromising credentials to extract password hashes from a domain controller. | AA53: https://filestore.fortinet.com/docs.fortinet.com/fsiem/Public_Resource_Access/7_6_0/rules/PH_RULE_Win_Secretsdump_Execution.htm
A54: PH_Rule_Win_Sensitive_Registry_Hive_Save | B54: Windows: Sensitive Registry Hive Save | C54: New ITDR (7.6.0) | D54: Identity-core | E54: Windows Security log, Credential Access | F54: Enabled | G54: 9 | H54: High | I54: Security | J54: Correlation | K54: Streaming | L54: Credential Access | M54: T1003.002 | N54: Microsoft Windows Security Log via OMI or Windows Collector Microsoft Windows Sysmon via Windows Collector | O54: Win-Security-4688 Win-Sysmon-1-Create-Process | Q54: 1 | R54: Filter | S54: command REGEXP "(?i).*reg(?:\.exe)?\s+save\s+.?(?:HKLM|HKEY_LOCAL_MACHINE)\\(?:SAM|SYSTEM|SECURITY).*" | T54: hostName,user,procName,command | U54: COUNT(*) >= 1 | V54: 300 | X54: Windows Security log: Security 4688 Sysmon: Sysmon 1 | Y54: s1 | Z54: Detects use of the reg save command to export the SAM, SYSTEM, or SECURITY registry hives from HKEY_LOCAL_MACHINE. Adversaries may copy these hives for offline credential extraction, including recovery of local account password hashes and LSA secrets. Legitimate backup, forensic, or incident-response activity may also trigger this rule. | AA54: https://filestore.fortinet.com/docs.fortinet.com/fsiem/Public_Resource_Access/7_6_0/rules/PH_RULE_Win_Sensitive_Registry_Hive_Save.htm
A55: PH_Rule_Win_Shadow_Credentials_KeyCredentialLink_Modified | B55: Windows: Shadow Credentials KeyCredentialLink Modified | C55: New ITDR (7.6.0) | D55: Identity-core | E55: Active Directory, Windows Security log, Credential Access | F55: Enabled | G55: 10 | H55: High | I55: Security | J55: Correlation | K55: Streaming | L55: Credential Access | M55: T1606.002 | N55: Microsoft Windows Security Log via OMI or Windows Collector | O55: Win-Security-5136 | Q55: 1 | R55: Filter | S55: propName = "msDS-KeyCredentialLink" | T55: hostName,user,osObjName,propName | U55: COUNT(*) >= 1 | V55: 300 | X55: Windows Security log: Security 5136 | Y55: a6 | Z55: Detects modification of the msDS-KeyCredentialLink attribute on a directory service object. An adversary may write a KeyCredentialLink to a target account to establish shadow credentials, enabling authentication as that account via Windows Hello for Business or PKINIT without changing its password. Legitimate Windows Hello for Business enrollment, device registration, and approved identity-management tooling may also generate this event. | AA55: https://filestore.fortinet.com/docs.fortinet.com/fsiem/Public_Resource_Access/7_6_0/rules/PH_RULE_Win_Shadow_Credentials_KeyCredentialLink_Modified.htm
A56: PH_Rule_Win_SSP_Registration | B56: Windows: SSP Registration | C56: New ITDR (7.6.0) | D56: Identity-core | E56: Windows Security log | F56: Enabled | G56: 9 | H56: High | I56: Security | J56: Correlation | K56: Streaming | L56: Persistence | M56: T1547.005 | N56: Microsoft Windows Powershell Operational Logs via Windows Collector Microsoft Windows Security Log via OMI or Windows Collector Microsoft Windows Sysmon via Windows Collector | O56: Win-PowerShell-4104 Win-Security-4688 Win-Sysmon-1-Create-Process | Q56: 1 | R56: Filter | S56: command REGEXP ".*(?:Security Packages|SSP).*" | T56: hostName,user,procName,command | U56: COUNT(*) >= 1 | V56: 300 | X56: Windows Security log: Security 4688 Sysmon: Sysmon 1 PowerShell Operational: PowerShell 4104 | Y56: s1, s4 | Z56: Detects command lines or script blocks that register a Security Support Provider (SSP) by writing to the Security Packages registry value or referencing an SSP DLL. An adversary may register a malicious SSP to load code into the LSASS process at boot, capturing plaintext and encrypted credentials from logged-on users. | AA56: https://filestore.fortinet.com/docs.fortinet.com/fsiem/Public_Resource_Access/7_6_0/rules/PH_RULE_Win_SSP_Registration.htm
A57: PH_Rule_Win_Suspicious_LSASS_Process_Access | B57: Windows: Suspicious LSASS Process Access | C57: New ITDR (7.6.0) | D57: Identity-core | E57: Credential Access | F57: Enabled | G57: 9 | H57: High | I57: Security | J57: Correlation | K57: Streaming | L57: Credential Access | M57: T1003.001 | N57: Microsoft Windows Sysmon via Windows Collector | O57: Win-Sysmon-10-ProcessAccess | Q57: 1 | R57: LSASS_ACCESS | S57: targetProcName REGEXP "(?i)^.*lsass\.exe$" AND accessKeyId REGEXP "(?i)^0x0*(?:10|40|50|410|1010|1410|1f0fff|1fffff)$" | T57: hostName,user,procName,parentProcName,targetProcName | U57: COUNT(*) >= 1 | V57: 300 | X57: Sysmon: Sysmon 10 | Y57: s2 | Z57: Detects processes accessing LSASS with permissions commonly associated with credential dumping, memory reading, or process-handle duplication. Adversaries may access LSASS memory directly or obtain a reusable LSASS process handle to extract credentials. Legitimate security, diagnostic, backup, crash-dump, and administrative tools may also access LSASS. Tune approved security products, administrative tools, service accounts, executable paths, publishers, hashes, and maintenance activity before enabling in production. | AA57: https://filestore.fortinet.com/docs.fortinet.com/fsiem/Public_Resource_Access/7_6_0/rules/PH_RULE_Win_Suspicious_LSASS_Process_Access.htm
A58: PH_Rule_Win_Token_Impersonation_Tool | B58: Windows: Token Impersonation Tool | C58: New ITDR (7.6.0) | D58: Identity-core | E58: Windows Security log, Privilege Escalation | F58: Enabled | G58: 9 | H58: High | I58: Security | J58: Correlation | K58: Streaming | L58: Privilege Escalation | M58: T1134.001 | N58: Microsoft Windows Powershell Operational Logs via Windows Collector Microsoft Windows Security Log via OMI or Windows Collector Microsoft Windows Sysmon via Windows Collector | O58: Win-PowerShell-4104 Win-Security-4688 Win-Sysmon-1-Create-Process | Q58: 1 | R58: Filter | S58: (procName REGEXP "(?i).*(?:incognito|JuicyPotato|RoguePotato|PrintSpoofer|GodPotato).*" OR command REGEXP "(?i).*(?:incognito|JuicyPotato|RoguePotato|PrintSpoofer|GodPotato).*") | T58: hostName,user,procName,command | U58: COUNT(*) >= 1 | V58: 300 | X58: Windows Security log: Security 4688 Sysmon: Sysmon 1 PowerShell Operational: PowerShell 4104 | Y58: s1, s4 | Z58: Detects execution of token impersonation and privilege escalation tools such as incognito, JuicyPotato, RoguePotato, PrintSpoofer, and GodPotato. These tools abuse Windows access token manipulation and local NTLM relay abuse to escalate privileges and impersonate SYSTEM or other accounts. | AA58: https://filestore.fortinet.com/docs.fortinet.com/fsiem/Public_Resource_Access/7_6_0/rules/PH_RULE_Win_Token_Impersonation_Tool.htm
A59: PH_Rule_Access_51A | B59: Account Locked: Domain | C59: Existing, re-tagged ITDR | D59: Identity-core | E59: Credential Access, Identity event group | F59: Disabled | G59: 6 | H59: Medium | I59: Security | J59: Correlation | K59: Streaming | L59: Credential Access | M59: T1110.001 | N59: Microsoft Windows via OMI or Windows Collector | O59: Group@PH_SYS_EVENT_DomainAccountLocked | Q59: 1 | R59: DomainAcctLockout | S59: — | T59: reptDevName,reptDevIpAddr, user | U59: COUNT (*) >= 1 | V59: 600 | X59: Event-type group (membership not published): Group@PH_SYS_EVENT_DomainAccountLocked | Z59: Detects account lockout caused by excessive logon failures | AA59: https://filestore.fortinet.com/docs.fortinet.com/fsiem/Public_Resource_Access/7_6_0/rules/PH_RULE_ACCOUNT_LOCKOUT_DOMAIN.htm
A60: PH_Rule_Access_51D | B60: Account Locked: FortiSIEM | C60: Existing, re-tagged ITDR | D60: Identity-core | E60: Credential Access | F60: Enabled | G60: 9 | H60: High | I60: Security | J60: Correlation | K60: Streaming | L60: Credential Access | M60: T1110.001 | N60: FortiSIEM via Syslog | O60: PH_AUDIT_ACCOUNT_LOCKED | Q60: 1 | R60: AOLockout | S60: — | T60: srcIpAddr, srcGeoCountry, targetUser, reptDevName | U60: COUNT (*) >= 1 | V60: 600 | X60: Other: PH_AUDIT_ACCOUNT_LOCKED | Z60: Detects system (FortiSIEM) account lockout caused by excessive logon failures | AA60: https://filestore.fortinet.com/docs.fortinet.com/fsiem/Public_Resource_Access/7_6_0/rules/PH_RULE_ACCOUNT_LOCKOUT_SYSTEM.htm
A61: PH_Rule_Access_51B | B61: Account Locked: Network Device | C61: Existing, re-tagged ITDR | D61: Identity-core | E61: Credential Access, Identity event group | F61: Enabled | G61: 9 | H61: High | I61: Security | J61: Correlation | K61: Streaming | L61: Credential Access | M61: T1110.001 | N61: FortiDeceptor via Syslog FortiSwitch via Syslog FortiProxy via Syslog FortiGate via Syslog Cisco IOS via Syslog Cisco ASA via Syslog | O61: Group@PH_SYS_EVENT_HostAccountLocked | Q61: 1 | R61: NetDevAcctLockout | S61: reptDevIpAddr IN (Group@PH_SYS_DEVICE_Network) | T61: srcIpAddr, srcGeoCountry, reptDevName, reptDevIpAddr, user | U61: COUNT (*) >= 1 | V61: 600 | X61: Event-type group (membership not published): Group@PH_SYS_EVENT_HostAccountLocked | Z61: Detects account lockout caused by excessive logon failures | AA61: https://filestore.fortinet.com/docs.fortinet.com/fsiem/Public_Resource_Access/7_6_0/rules/PH_RULE_ACCOUNT_LOCKOUT_NET_DEV.htm
A62: PH_Rule_Access_51C | B62: Account Locked: Server | C62: Existing, re-tagged ITDR | D62: Identity-core | E62: Credential Access, Identity event group | F62: Enabled | G62: 8 | H62: Medium | I62: Security | J62: Correlation | K62: Streaming | L62: Credential Access | M62: T1110.001 | N62: Microsoft Windows via OMI or Windows Collector Linux via Syslog | O62: Group@PH_SYS_EVENT_HostAccountLocked | P62: PH_AUDIT_ACCOUNT_LOCKED | Q62: 1 | R62: ServerAcctLockout | S62: reptDevIpAddr IN (Group@PH_SYS_DEVICE_Server) | T62: reptDevName,reptDevIpAddr, user | U62: COUNT (*) >= 1 | V62: 600 | X62: Event-type group (membership not published): Group@PH_SYS_EVENT_HostAccountLocked | Z62: Detects account lockout caused by excessive logon failures | AA62: https://filestore.fortinet.com/docs.fortinet.com/fsiem/Public_Resource_Access/7_6_0/rules/PH_RULE_ACCOUNT_LOCKOUT_SERVER.htm
A63: PH_Rule_ES_IMPORT_AWS_1 | B63: AWS IAM Brute Force of Assume Role Policy | C63: Existing, re-tagged ITDR | D63: Identity-core | E63: Credential Access | F63: Enabled | G63: 7 | H63: Medium | I63: Security | J63: Correlation | K63: Streaming | L63: Credential Access | M63: T1110.001 | N63: AWS CloudTrail via AWS_CLOUDTRAIL | O63: CONTAIN:AWS-CloudTrail-IAM-UpdateAssumeRolePolicy | Q63: 1 | R63: Filter | S63: errorString = "MalformedPolicyDocumentException" | T63: accountId,user | U63: COUNT(*) >= 5 | V63: 300 | X63: Other: AWS-CloudTrail-IAM-UpdateAssumeRolePolicy | Z63: Identifies a high number of failed attempts to assume an AWS Identity and Access Management (IAM) role. IAM roles are used to delegate access to users or services. An adversary may attempt to enumerate IAM roles in order to determine if a role exists before attempting to assume or hijack the discovered role. | AA63: https://filestore.fortinet.com/docs.fortinet.com/fsiem/Public_Resource_Access/7_6_0/rules/PH_RULE_AWS_IAM_Brute_Force_of_Assume_Role_Policy.htm
A64: PH_Rule_ES_IMPORT_AWS_21 | B64: AWS IAM MFA Device Deactivated | C64: Existing, re-tagged ITDR | D64: Identity-core | E64: Privilege/account change | F64: Enabled | G64: 9 | H64: High | I64: Security | J64: Correlation | K64: Streaming | L64: Impact | M64: T1531 | N64: AWS CloudTrail via AWS_CLOUDTRAIL | O64: CONTAIN:AWS-CloudTrail-IAM-DeactivateMFADevice | Q64: 1 | R64: Filter | S64: — | T64: accountId,user | U64: COUNT(*) >= 1 | V64: 300 | X64: Other: AWS-CloudTrail-IAM-DeactivateMFADevice | Z64: Identifies the deactivation of a specified multi-factor authentication (MFA) device and removes it from association with the user name for which it was originally enabled. In AWS Identity and Access Management (IAM), a device must be deactivated before it can be deleted. | AA64: https://filestore.fortinet.com/docs.fortinet.com/fsiem/Public_Resource_Access/7_6_0/rules/PH_RULE_AWS_IAM_Deactivation_of_MFA_Device.htm
A65: PH_Rule_ES_IMPORT_AWS_26 | B65: AWS IAM Password Recovery Requested | C65: Existing, re-tagged ITDR | D65: Identity-core | E65: Privilege/account change | F65: Enabled | G65: 9 | H65: High | I65: Security | J65: Correlation | K65: Streaming | L65: Initial Access | M65: T1078.004 | N65: AWS CloudTrail via AWS_CLOUDTRAIL | O65: CONTAIN:AWS-CloudTrail-SIGNIN-PasswordRecoveryRequested | Q65: 1 | R65: Filter | S65: — | T65: accountId,user | U65: COUNT(*) >= 1 | V65: 300 | X65: Other: AWS-CloudTrail-SIGNIN-PasswordRecoveryRequested | Z65: Detects AWS IAM password recovery requests. An adversary may attempt to gain unauthorized AWS access by abusing password recovery mechanisms. | AA65: https://filestore.fortinet.com/docs.fortinet.com/fsiem/Public_Resource_Access/7_6_0/rules/PH_RULE_AWS_IAM_Password_Recovery_Requested.htm
A66: PH_Rule_ES_IMPORT_AWS_3 | B66: AWS Management Console Brute Force of Root User Identity | C66: Existing, re-tagged ITDR | D66: Identity-core | E66: Credential Access | F66: Disabled | G66: 10 | H66: High | I66: Security | J66: Correlation | K66: Streaming | L66: Credential Access | M66: T1110.001 | N66: AWS CloudTrail via AWS_CLOUDTRAIL | O66: CONTAIN:AWS-CloudTrail-SIGNIN-ConsoleLogin | Q66: 1 | R66: Filter | S66: identityType = "Root" AND status = "failed" | T66: accountId,accountName,user | U66: COUNT(*) >= 5 | V66: 300 | X66: Other: AWS-CloudTrail-SIGNIN-ConsoleLogin | Z66: Identifies a high number of failed authentication attempts to the AWS management console for the Root user identity. An adversary may attempt to brute force the password for the Root user identity, as it has complete access to all services and resources for the AWS account. | AA66: https://filestore.fortinet.com/docs.fortinet.com/fsiem/Public_Resource_Access/7_6_0/rules/PH_RULE_AWS_Management_Console_Brute_Force_of_Root_User_Identity.htm
A67: PH_Rule_ES_IMPORT_AWS_30 | B67: AWS Root Login Without MFA | C67: Existing, re-tagged ITDR | D67: Identity-core | E67: Privilege/account change | F67: Enabled | G67: 10 | H67: High | I67: Security | J67: Correlation | K67: Streaming | L67: Initial Access | M67: T1078.004 | N67: AWS CloudTrail via AWS_CLOUDTRAIL | O67: AWS-CloudTrail-SIGNIN-ConsoleLogin-Success | Q67: 1 | R67: Filter | S67: identityType = "Root" AND mfaAuthenticated != "Yes" | T67: accountId,accountName,user,srcIpAddr | U67: COUNT(*) >= 1 | V67: 300 | X67: Other: AWS-CloudTrail-SIGNIN-ConsoleLogin-Success | Z67: Identifies attempts to login to AWS as the root user without using multi-factor authentication (MFA). Amazon AWS best practices indicate that the root user should be protected by MFA. | AA67: https://filestore.fortinet.com/docs.fortinet.com/fsiem/Public_Resource_Access/7_6_0/rules/PH_RULE_AWS_Root_Login_Without_MFA.htm
A68: PH_Rule_AWSSecHub_7 | B68: AWS SecHub: Tactics: Credential Access Detected | C68: Existing, re-tagged ITDR | D68: Identity-core | E68: Credential Access | F68: Enabled | G68: 8 | H68: Medium | I68: Security | J68: Correlation | K68: Streaming | L68: Credential Access | N68: AWS Security Hub via AWS_HUB_SDK | O68: AWS-Hub-TTPs-Credential_Access | Q68: 1 | R68: AWSDetect | S68: — | T68: ec2InstanceId,awsRegion | U68: COUNT(*) >= 1 | V68: 300 | X68: Other: AWS-Hub-TTPs-Credential_Access | Z68: AWS Security Hub detected Credential Access tactics. Adversary is trying to steal account names and passwords. | AA68: https://filestore.fortinet.com/docs.fortinet.com/fsiem/Public_Resource_Access/7_6_0/rules/PH_RULE_AWS_SECHUB_TTP_CREDENTIAL_ACCESS.htm
A69: PH_Rule_AWSSecHub_5 | B69: AWS SecHub: Tactics: Privilege Escalation Detected | C69: Existing, re-tagged ITDR | D69: Identity-core | E69: Privilege Escalation, Privilege/account change | F69: Enabled | G69: 9 | H69: High | I69: Security | J69: Correlation | K69: Streaming | L69: Privilege Escalation | M69: T1548.002 | N69: AWS Security Hub via AWS_HUB_SDK | O69: AWS-Hub-TTPs-Privilege_Escalation | Q69: 1 | R69: AWSDetect | S69: — | T69: ec2InstanceId,awsRegion | U69: COUNT(*) >= 1 | V69: 300 | X69: Other: AWS-Hub-TTPs-Privilege_Escalation | Z69: AWS Security Hub detected Privilege Escalation tactics. Adversary is trying to gain privileges. | AA69: https://filestore.fortinet.com/docs.fortinet.com/fsiem/Public_Resource_Access/7_6_0/rules/PH_RULE_AWS_SECHUB_TTP_PRIV_ESCALATION.htm
A70: PH_Rule_ES_IMPORT_AWS_4 | B70: AWS Secret Accessed in Secrets Manager | C70: Existing, re-tagged ITDR | D70: Identity-core | E70: Credential Access | F70: Enabled | G70: 7 | H70: Medium | I70: Security | J70: Correlation | K70: Streaming | L70: Credential Access | M70: T1528 | N70: AWS CloudTrail via AWS_CLOUDTRAIL | O70: CONTAIN:AWS-CloudTrail-SECRETSMANAGER-GetSecretValue | Q70: 1 | R70: Filter | S70: identityType != "AWSService" AND status = "success" | T70: accountId,user | U70: COUNT(*) >= 1 | V70: 300 | X70: Other: AWS-CloudTrail-SECRETSMANAGER-GetSecretValue | Z70: A user that is not an AWS service accessed a secret stored in AWS Secret Manager. | AA70: https://filestore.fortinet.com/docs.fortinet.com/fsiem/Public_Resource_Access/7_6_0/rules/PH_RULE_AWS_Access_Secret_in_Secrets_Manager.htm
A71: PH_Rule_ES_IMPORT_AZURE_17 | B71: Azure Global Administrator Role Added to PIM User | C71: Existing, re-tagged ITDR | D71: Identity-core | E71: Entra ID, Active Directory, Privilege/account change | F71: Enabled | G71: 9 | H71: High | I71: Security | J71: Correlation | K71: Streaming | L71: Persistence | M71: T1098.001 | N71: Microsoft Azure Event Hub via AZURE_PYTHON_SDK | O71: MS_EvtHub_add_eligible_member_to_role_in_pim_completed_permanent MS_EvtHub_add_member_to_role_in_pim_completed_timebound | Q71: 1 | R71: Filter | S71: azureEventCategory = "RoleManagement" AND srcName = "Global Administrator" | T71: azureEventCategory,srcName,user | U71: COUNT(*) >= 1 | V71: 300 | X71: Other: MS_EvtHub_add_member_to_role_in_pim_completed_timebound Other: MS_EvtHub_add_eligible_member_to_role_in_pim_completed_permanent | Z71: Identifies an Azure Active Directory (AD) Global Administrator role addition to a Privileged Identity Management (PIM) user account. PIM is a service that enables you to manage, control, and monitor access to important resources in an organization. Users who are assigned to the Global administrator role can read and modify any administrative setting in your Azure AD organization. | AA71: https://filestore.fortinet.com/docs.fortinet.com/fsiem/Public_Resource_Access/7_6_0/rules/PH_RULE_Azure_Global_Administrator_Role_Addition_to_PIM_User.htm
A72: PH_Rule_Access_75 | B72: Brute Force App Login Success | C72: Existing, re-tagged ITDR | D72: Identity-core | E72: Credential Access | F72: Enabled | G72: 9 | H72: High | I72: Security | J72: Correlation | K72: Streaming | L72: Credential Access | M72: T1110.001 | N72: Microsoft Windows via OMI or Windows Collector Hillstone Firewall via Syslog Palo Alto PAN-OS via Syslog Sophos Firewall via Syslog Juniper SSLVPN via Syslog Juniper JunOS via Syslog Microsoft IIS via Syslog Pulse Secure via Syslog WatchGuard via Syslog FortiProxy via Syslog FortiGate via Syslog Cisco ASA via Syslog SonicOS via Syslog Apache via Syslog JBOSS via Syslog F5 via Syslog | O72: Group@PH_SYS_EVENT_AppLogonFailure Group@PH_SYS_EVENT_AppLogonSuccess Group@PH_SYS_EVENT_DBLogonFailure Group@PH_SYS_EVENT_DBLogonSuccess Group@PH_SYS_EVENT_MultipleAppLogonFailure Group@PH_SYS_EVENT_MultipleDBLogonFailure Group@PH_SYS_EVENT_MultipleVPNLogonFailure Group@PH_SYS_EVENT_MultipleWebLogonFailure Group@PH_SYS_EVENT_VPNLogonFailure Group@PH_SYS_EVENT_VPNLogonSuccess Group@PH_SYS_EVENT_WebLogonFailure Group@PH_SYS_EVENT_WebLogonSuccess | Q72: 3 | R72: FailedLogin OR FailedLogin2 FOLLOWED_BY SuccessLogin | S72: [FailedLogin] user IS NOT NULL [FailedLogin2] user IS NOT NULL [SuccessLogin] user IS NOT NULL | T72: [FailedLogin] srcIpAddr, srcGeoCountry, reptDevIpAddr, user [FailedLogin2] srcIpAddr, srcGeoCountry, reptDevIpAddr, user [SuccessLogin] srcIpAddr, srcGeoCountry, reptDevName, reptDevIpAddr, user | U72: [FailedLogin] COUNT(*) >= 5 [FailedLogin2] COUNT(*) >= 1 [SuccessLogin] COUNT (*) >= 1 | V72: 900 | W72: FailedLogin.reptDevIpAddr = SuccessLogin.reptDevIpAddr AND FailedLogin.srcIpAddr = SuccessLogin.srcIpAddr AND FailedLogin.user = SuccessLogin.user OR FailedLogin2.reptDevIpAddr = SuccessLogin.reptDevIpAddr AND FailedLogin2.srcIpAddr = SuccessLogin.srcIpAddr AND FailedLogin2.user = SuccessLogin.user | X72: Event-type group (membership not published): Group@PH_SYS_EVENT_VPNLogonFailure Event-type group (membership not published): Group@PH_SYS_EVENT_DBLogonFailure Event-type group (membership not published): Group@PH_SYS_EVENT_WebLogonFailure Event-type group (membership not published): Group@PH_SYS_EVENT_AppLogonFailure Event-type group (membership not published): Group@PH_SYS_EVENT_MultipleVPNLogonFailure Event-type group (membership not published): Group@PH_SYS_EVENT_MultipleDBLogonFailure Event-type group (membership not published): Group@PH_SYS_EVENT_MultipleWebLogonFailure Event-type group (membership not published): Group@PH_SYS_EVENT_MultipleAppLogonFailure Event-type group (membership not published): Group@PH_SYS_EVENT_VPNLogonSuccess Event-type group (membership not published): Group@PH_SYS_EVENT_DBLogonSuccess Event-type group (membership not published): Group@PH_SYS_EVENT_WebLogonSuccess Event-type group (membership not published): Group@PH_SYS_EVENT_AppLogonSuccess | Z72: Detects an unusual condition where a source has authentication failures followed by a successful authentication at the same app within 15 minutes | AA72: https://filestore.fortinet.com/docs.fortinet.com/fsiem/Public_Resource_Access/7_6_0/rules/PH_RULE_BRUTEFORCE_APP_LOGON_SUCCESS.htm
A73: PH_Rule_Access_70 | B73: Brute Force Host Login Success | C73: Existing, re-tagged ITDR | D73: Identity-core | E73: Credential Access, Identity event group | F73: Enabled | G73: 9 | H73: High | I73: Security | J73: Correlation | K73: Streaming | L73: Credential Access | M73: T1110.001 | N73: Microsoft Windows via OMI or Windows Collector Office 365 via Management Activity API AWS CloudTrail via AWS_CLOUDTRAIL Hillstone Firewall via Syslog Sophos Firewall via Syslog Juniper JunOS via Syslog Pulse Secure via Syslog Juniper SRX via Syslog HP Procurve via Syslog Juniper SSG via Syslog WatchGuard via Syslog VMware NSX via Syslog FortiProxy via Syslog FortiGate via Syslog Cisco IOS via Syslog Cisco ASA via Syslog NetScaler via Syslog FortiSIEM via Syslog Riverbed via Syslog BlueCoat via Syslog FortiWeb via Syslog IBM AIX via Syslog SonicOS via Syslog Linux via Syslog | O73: Group@PH_SYS_EVENT_DomainLogonFailure Group@PH_SYS_EVENT_DomainLogonSuccess Group@PH_SYS_EVENT_HostLogonFailure Group@PH_SYS_EVENT_HostLogonSuccess Group@PH_SYS_EVENT_MultipleDomainLogonFailure Group@PH_SYS_EVENT_MultipleHostLogonFailure Group@PH_SYS_EVENT_VMware_LogonFailure Group@PH_SYS_EVENT_VMware_LogonSuccess | Q73: 3 | R73: FailedLogin OR FailedLogin2 FOLLOWED_BY SuccessLogin | S73: [FailedLogin] user IS NOT NULL [FailedLogin2] user IS NOT NULL [SuccessLogin] user IS NOT NULL | T73: [FailedLogin] srcIpAddr, srcGeoCountry, reptDevIpAddr, user [FailedLogin2] srcIpAddr, srcGeoCountry, reptDevIpAddr, user [SuccessLogin] srcIpAddr, srcGeoCountry, reptDevName, reptDevIpAddr, user | U73: [FailedLogin] COUNT(*) >= 5 [FailedLogin2] COUNT(*) >= 1 [SuccessLogin] COUNT (*) >= 1 | V73: 900 | W73: FailedLogin.reptDevIpAddr = SuccessLogin.reptDevIpAddr AND FailedLogin.srcIpAddr = SuccessLogin.srcIpAddr AND FailedLogin.user = SuccessLogin.user OR FailedLogin2.reptDevIpAddr = SuccessLogin.reptDevIpAddr AND FailedLogin2.srcIpAddr = SuccessLogin.srcIpAddr AND FailedLogin2.user = SuccessLogin.user | X73: Event-type group (membership not published): Group@PH_SYS_EVENT_HostLogonFailure Event-type group (membership not published): Group@PH_SYS_EVENT_VMware_LogonFailure Event-type group (membership not published): Group@PH_SYS_EVENT_DomainLogonFailure Event-type group (membership not published): Group@PH_SYS_EVENT_MultipleHostLogonFailure Event-type group (membership not published): Group@PH_SYS_EVENT_MultipleDomainLogonFailure Event-type group (membership not published): Group@PH_SYS_EVENT_HostLogonSuccess Event-type group (membership not published): Group@PH_SYS_EVENT_VMware_LogonSuccess Event-type group (membership not published): Group@PH_SYS_EVENT_DomainLogonSuccess | Z73: Detects an unusual condition where a source has authentication failures followed by a successful authentication at the same host within 15 minutes | AA73: https://filestore.fortinet.com/docs.fortinet.com/fsiem/Public_Resource_Access/7_6_0/rules/PH_RULE_BRUTEFORCE_LOGON_SUCCESS.htm
A74: PH_Rule_Access_63 | B74: Concurrent Failed Authentications To Same Account From Multiple Countries | C74: Existing, re-tagged ITDR | D74: Identity-core | E74: Credential Access, Identity event group | F74: Enabled | G74: 9 | H74: High | I74: Security | J74: Correlation | K74: Streaming | L74: Credential Access | M74: T1110.001 | N74: Microsoft Windows via OMI or Windows Collector Office 365 via Management Activity API AWS CloudTrail via AWS_CLOUDTRAIL Hillstone Firewall via Syslog Sophos Firewall via Syslog Juniper JunOS via Syslog Pulse Secure via Syslog Juniper SRX via Syslog HP Procurve via Syslog Juniper SSG via Syslog WatchGuard via Syslog VMware NSX via Syslog FortiProxy via Syslog FortiGate via Syslog Cisco IOS via Syslog Cisco ASA via Syslog NetScaler via Syslog FortiSIEM via Syslog Riverbed via Syslog BlueCoat via Syslog FortiWeb via Syslog IBM AIX via Syslog SonicOS via Syslog Linux via Syslog | O74: Group@PH_SYS_EVENT_DomainLogonFailure Group@PH_SYS_EVENT_HostLogonFailure | Q74: 1 | R74: MultiCountryLogon | S74: user IS NOT NULL AND srcGeoCountry IS NOT NULL | T74: reptDevName,reptDevIpAddr,user | U74: COUNT (DISTINCT srcGeoCountry) >= 2 | V74: 3600 | X74: Event-type group (membership not published): Group@PH_SYS_EVENT_HostLogonFailure Event-type group (membership not published): Group@PH_SYS_EVENT_DomainLogonFailure | Z74: Detects simultaneous failed authentications to the same system and the same account from different countries. This may indicate stolen credentials unless it is an administrative account and is supposed to be accessed by administrators from multiple countries. | AA74: https://filestore.fortinet.com/docs.fortinet.com/fsiem/Public_Resource_Access/7_6_0/rules/PH_RULE_CONCURRENT_FAILED_AUTH_MULTI_COUNTRY.htm
A75: PH_Rule_Access_61 | B75: Concurrent Successful Authentications To Same Account From Multiple Countries | C75: Existing, re-tagged ITDR | D75: Identity-core | E75: Credential Access, Identity event group | F75: Enabled | G75: 9 | H75: High | I75: Security | J75: Correlation | K75: Streaming | L75: Credential Access | M75: T1110.001 | N75: Microsoft Windows via OMI or Windows Collector Office 365 via Management Activity API AWS CloudTrail via AWS_CLOUDTRAIL Hillstone Firewall via Syslog Sophos Firewall via Syslog Juniper JunOS via Syslog Pulse Secure via Syslog Juniper SRX via Syslog HP Procurve via Syslog Juniper SSG via Syslog WatchGuard via Syslog VMware NSX via Syslog FortiProxy via Syslog FortiGate via Syslog Cisco IOS via Syslog Cisco ASA via Syslog NetScaler via Syslog FortiSIEM via Syslog Riverbed via Syslog BlueCoat via Syslog FortiWeb via Syslog IBM AIX via Syslog SonicOS via Syslog Linux via Syslog | O75: Group@PH_SYS_EVENT_DomainLogonSuccess Group@PH_SYS_EVENT_HostLogonSuccess | Q75: 1 | R75: MultiCountryLogon | S75: user IS NOT NULL AND srcGeoCountry IS NOT NULL | T75: reptDevName,reptDevIpAddr,user | U75: COUNT (DISTINCT srcGeoCountry) >= 2 | V75: 3600 | X75: Event-type group (membership not published): Group@PH_SYS_EVENT_HostLogonSuccess Event-type group (membership not published): Group@PH_SYS_EVENT_DomainLogonSuccess | Z75: Detects simultaneous successful server/network device/domain authentications to the same system and the same account from different countries. This may indicate stolen credentials unless it is an administrative account and is supposed to be accessed by administrators from multiple countries. | AA75: https://filestore.fortinet.com/docs.fortinet.com/fsiem/Public_Resource_Access/7_6_0/rules/PH_RULE_CONCURRENT_SUCCESS_AUTH_MULTI_COUNTRY.htm
A76: PH_Rule_Access_65 | B76: Concurrent Successful VPN Authentications To Same Account From Different Countries | C76: Existing, re-tagged ITDR | D76: Identity-core | E76: Credential Access | F76: Enabled | G76: 9 | H76: High | I76: Security | J76: Correlation | K76: Streaming | L76: Credential Access | M76: T1110.001 | N76: Microsoft Windows via OMI or Windows Collector Hillstone Firewall via Syslog Palo Alto PAN-OS via Syslog Sophos Firewall via Syslog Juniper SSLVPN via Syslog Juniper JunOS via Syslog Pulse Secure via Syslog WatchGuard via Syslog FortiProxy via Syslog FortiGate via Syslog Cisco ASA via Syslog SonicOS via Syslog | O76: Group@PH_SYS_EVENT_VPNLogonSuccess | Q76: 1 | R76: VPNLogonDistinctCity | S76: user IS NOT NULL AND user != "N/A" AND srcGeoCountry IS NOT NULL AND srcGeoCountry != "N/A" | T76: user | U76: COUNT(DISTINCT srcGeoCountry) >= 2 | V76: 3600 | X76: Event-type group (membership not published): Group@PH_SYS_EVENT_VPNLogonSuccess | Z76: Detects simultaneous successful VPN authentications to the same account within a short period of time from different countries. This may indicate a stolen credential. | AA76: https://filestore.fortinet.com/docs.fortinet.com/fsiem/Public_Resource_Access/7_6_0/rules/PH_RULE_CONCURRENT_VPN_AUTH_MULTI_COUNTRY.htm
A77: PH_Rule_Exploits_CS_1C | B77: Crowdstrike: Authentication Bypass | C77: Existing, re-tagged ITDR | D77: Identity-core | E77: Privilege Escalation | F77: Enabled | G77: 8 | H77: Medium | I77: Security | J77: Correlation | K77: Streaming | L77: Privilege Escalation | N77: Crowdstrike via FALCON_STREAMING_API or FALCON_DATA_REPLICATOR | O77: Crowdstrike-Falcon-EppDetectionSummaryEvent-authentication-bypass Crowdstrike-Falcon-EppDetectionSummaryEvent-authentication-bypass-block | Q77: 1 | R77: CSDetect | S77: — | T77: hostName,attackTactic,attackTechnique,command,subtype | U77: COUNT(*) >= 1 | V77: 300 | X77: Other: Crowdstrike-Falcon-EppDetectionSummaryEvent-authentication-bypass Other: Crowdstrike-Falcon-EppDetectionSummaryEvent-authentication-bypass-block | Z77: Crowdstrike agent detected and blocked authentication bypass attempt | AA77: https://filestore.fortinet.com/docs.fortinet.com/fsiem/Public_Resource_Access/7_6_0/rules/PH_RULE_CS_AUTH_BYPASS.htm
A78: PH_Rule_Exploits_CS_4 | B78: Crowdstrike: Credential Theft Detected | C78: Existing, re-tagged ITDR | D78: Identity-core | E78: Credential Access | F78: Enabled | G78: 8 | H78: Medium | I78: Security | J78: Correlation | K78: Streaming | L78: Credential Access | N78: Crowdstrike via FALCON_STREAMING_API or FALCON_DATA_REPLICATOR | O78: Crowdstrike-Falcon-EppDetectionSummaryEvent-credential-theft Crowdstrike-Falcon-EppDetectionSummaryEvent-credential-theft-allow Crowdstrike-Falcon-EppDetectionSummaryEvent-credential-theft-block | Q78: 1 | R78: CSDetect | S78: — | T78: hostName,attackTactic,attackTechnique,command,subtype | U78: COUNT(*) >= 1 | V78: 300 | X78: Other: Crowdstrike-Falcon-EppDetectionSummaryEvent-credential-theft Other: Crowdstrike-Falcon-EppDetectionSummaryEvent-credential-theft-block Other: Crowdstrike-Falcon-EppDetectionSummaryEvent-credential-theft-allow | Z78: Crowdstrike agent detected credential theft | AA78: https://filestore.fortinet.com/docs.fortinet.com/fsiem/Public_Resource_Access/7_6_0/rules/PH_RULE_CS_CRED_THEFT.htm
A79: PH_Rule_Exploits_CS_14 | B79: Crowdstrike: Privilege Escalation | C79: Existing, re-tagged ITDR | D79: Identity-core | E79: Privilege Escalation, Privilege/account change | F79: Enabled | G79: 8 | H79: Medium | I79: Security | J79: Correlation | K79: Streaming | L79: Privilege Escalation | M79: T1548.004 | N79: Crowdstrike via FALCON_STREAMING_API or FALCON_DATA_REPLICATOR | O79: Crowdstrike-Falcon-EppDetectionSummaryEvent-privilege-escalation Crowdstrike-Falcon-EppDetectionSummaryEvent-privilege-escalation-allow Crowdstrike-Falcon-EppDetectionSummaryEvent-privilege-escalation-block | Q79: 1 | R79: CSDetect | S79: — | T79: hostName,attackTactic,attackTechnique,command,subtype | U79: COUNT(*) >= 1 | V79: 300 | X79: Other: Crowdstrike-Falcon-EppDetectionSummaryEvent-privilege-escalation Other: Crowdstrike-Falcon-EppDetectionSummaryEvent-privilege-escalation-allow Other: Crowdstrike-Falcon-EppDetectionSummaryEvent-privilege-escalation-block | Z79: Crowdstrike agent detected privilege escalation on a host | AA79: https://filestore.fortinet.com/docs.fortinet.com/fsiem/Public_Resource_Access/7_6_0/rules/PH_RULE_CS_PRIV_ESCALATION.htm
A80: PH_Rule_CyberArk_11 | B80: CyberArk Vault Blocked Operations | C80: Existing, re-tagged ITDR | D80: Identity-core | E80: Credential Access | F80: Enabled | G80: 8 | H80: Medium | I80: Security | J80: Correlation | K80: Streaming | L80: Credential Access | N80: CyberArk Enterprise Password Vault via Syslog | O80: CyberArk-Vault-403 CyberArk-Vault-408 CyberArk-Vault-409 | Q80: 1 | R80: Failure | S80: — | T80: srcIpAddr, srcGeoCountry, user, cyberArkSafe, fileName, reptDevName | U80: COUNT (*) >= 2 | V80: 600 | X80: Other: CyberArk-Vault-403 Other: CyberArk-Vault-408 Other: CyberArk-Vault-409 | Z80: Detects CyberArk Vault blocked operations | AA80: https://filestore.fortinet.com/docs.fortinet.com/fsiem/Public_Resource_Access/7_6_0/rules/PH_RULE_CYBERARK_BLOCKED_OPERATION.htm
A81: PH_Rule_CyberArk_2 | B81: CyberArk Vault Excessive Failed PSM Connections | C81: Existing, re-tagged ITDR | D81: Identity-core | E81: Credential Access | F81: Enabled | G81: 8 | H81: Medium | I81: Security | J81: Correlation | K81: Streaming | L81: Credential Access | N81: CyberArk Enterprise Password Vault via Syslog | O81: CyberArk-Vault-301 CyberArk-Vault-379 | Q81: 1 | R81: Failure | S81: — | T81: srcIpAddr, srcGeoCountry, user, cyberArkSafe, fileName, reptDevName | U81: COUNT (*) >= 3 | V81: 600 | X81: Other: CyberArk-Vault-301 Other: CyberArk-Vault-379 | Z81: Detects excessive failed connections to CyberArk Vault via Privileged Session Manager | AA81: https://filestore.fortinet.com/docs.fortinet.com/fsiem/Public_Resource_Access/7_6_0/rules/PH_RULE_CYBERARK_EXCESS_PSM_CONN_FAILURE.htm
A82: PH_Rule_CyberArk_6 | B82: CyberArk Vault Excessive Impersonations | C82: Existing, re-tagged ITDR | D82: Identity-core | E82: Credential Access | F82: Enabled | G82: 8 | H82: Medium | I82: Security | J82: Correlation | K82: Streaming | L82: Credential Access | N82: CyberArk Enterprise Password Vault via Syslog | O82: CyberArk-Vault-15 CyberArk-Vault-18 | Q82: 1 | R82: Failure | S82: — | T82: srcIpAddr, srcGeoCountry, user, reptDevName | U82: COUNT (*) >= 3 | V82: 600 | X82: Other: CyberArk-Vault-15 Other: CyberArk-Vault-18 | Z82: Detects excessive CyberArk Privileged Session Manager Session Monitoring Failures | AA82: https://filestore.fortinet.com/docs.fortinet.com/fsiem/Public_Resource_Access/7_6_0/rules/PH_RULE_CYBERARK_EXCESS_PSM_IMPERSONATIONS.htm
A83: PH_Rule_CyberArk_1 | B83: CyberArk Vault Excessive Password Release Failure | C83: Existing, re-tagged ITDR | D83: Identity-core | E83: Entra ID, Credential Access | F83: Enabled | G83: 8 | H83: Medium | I83: Security | J83: Correlation | K83: Streaming | L83: Credential Access | M83: T1110.001 | N83: CyberArk Enterprise Password Vault via Syslog | O83: CyberArk-Vault-137 | Q83: 1 | R83: Failure | S83: — | T83: srcIpAddr, srcGeoCountry, user, cyberArkSafe, fileName, reptDevName | U83: COUNT (*) >= 3 | V83: 600 | X83: Other: CyberArk-Vault-137 | Z83: Detects excessive password release failures from CyberArk Vault Central Policy Manager | AA83: https://filestore.fortinet.com/docs.fortinet.com/fsiem/Public_Resource_Access/7_6_0/rules/PH_RULE_CYBERARK_EXCESS_PWD_RELEASE_FAILURE.htm
A84: PH_Rule_CyberArk_3 | B84: CyberArk Vault Excessive PSM Keystroke Logging Failure | C84: Existing, re-tagged ITDR | D84: Identity-core | E84: Credential Access | F84: Enabled | G84: 8 | H84: Medium | I84: Security | J84: Correlation | K84: Streaming | L84: Credential Access | N84: CyberArk Enterprise Password Vault via Syslog | O84: CyberArk-Vault-362 CyberArk-Vault-413 | Q84: 1 | R84: Failure | S84: — | T84: srcIpAddr, srcGeoCountry, user, cyberArkSafe, fileName, reptDevName | U84: COUNT (*) >= 3 | V84: 600 | X84: Other: CyberArk-Vault-362 Other: CyberArk-Vault-413 | Z84: Detects CyberArk vault keystroke logging and audit failures via Privileged Session Manager | AA84: https://filestore.fortinet.com/docs.fortinet.com/fsiem/Public_Resource_Access/7_6_0/rules/PH_RULE_CYBERARK_EXCESS_PSM_LOGGING_FAILURE.htm
A85: PH_Rule_CyberArk_4 | B85: CyberArk Vault Excessive PSM Session Monitoring Failure | C85: Existing, re-tagged ITDR | D85: Identity-core | E85: Credential Access | F85: Enabled | G85: 8 | H85: Medium | I85: Security | J85: Correlation | K85: Streaming | L85: Credential Access | M85: T1110.001 | N85: CyberArk Enterprise Password Vault via Syslog | O85: CyberArk-Vault-375 | Q85: 1 | R85: Failure | S85: — | T85: srcIpAddr, srcGeoCountry, user, cyberArkSafe, fileName, reptDevName | U85: COUNT (*) >= 3 | V85: 600 | X85: Other: CyberArk-Vault-375 | Z85: Detects excessive CyberArk Privileged Session Manager Session Monitoring Failures | AA85: https://filestore.fortinet.com/docs.fortinet.com/fsiem/Public_Resource_Access/7_6_0/rules/PH_RULE_CYBERARK_EXCESS_PSM_MONITOR_FAILURE.htm
A86: PH_Rule_CyberArk_10 | B86: CyberArk Vault File Operation Failure | C86: Existing, re-tagged ITDR | D86: Identity-core | E86: Credential Access | F86: Enabled | G86: 8 | H86: Medium | I86: Security | J86: Correlation | K86: Streaming | L86: Credential Access | N86: CyberArk Enterprise Password Vault via Syslog | O86: CyberArk-Vault-204 CyberArk-Vault-205 | Q86: 1 | R86: Failure | S86: — | T86: srcIpAddr, srcGeoCountry, user, cyberArkSafe, fileName, reptDevName | U86: COUNT (*) >= 2 | V86: 600 | X86: Other: CyberArk-Vault-204 Other: CyberArk-Vault-205 | Z86: Detects CyberArk Vault file operation failures | AA86: https://filestore.fortinet.com/docs.fortinet.com/fsiem/Public_Resource_Access/7_6_0/rules/PH_RULE_CYBERARK_FILE_OPERATION_FAILURE.htm
A87: PH_Rule_CyberArk_9 | B87: CyberArk Vault Object Content Validation Failure | C87: Existing, re-tagged ITDR | D87: Identity-core | E87: Credential Access | F87: Enabled | G87: 8 | H87: Medium | I87: Security | J87: Correlation | K87: Streaming | L87: Credential Access | N87: CyberArk Enterprise Password Vault via Syslog | O87: CyberArk-Vault-366 | Q87: 1 | R87: Failure | S87: — | T87: srcIpAddr, srcGeoCountry, user, cyberArkSafe, fileName, reptDevName | U87: COUNT (*) >= 2 | V87: 600 | X87: Other: CyberArk-Vault-366 | Z87: Detects CyberArk Vault Object Content Validation Failures | AA87: https://filestore.fortinet.com/docs.fortinet.com/fsiem/Public_Resource_Access/7_6_0/rules/PH_RULE_CYBERARK_OBJECT_VALIDATION_FAILURE.htm
A88: PH_Rule_CyberArk_5 | B88: CyberArk Vault Unauthorized User Stations | C88: Existing, re-tagged ITDR | D88: Identity-core | E88: Credential Access | F88: Enabled | G88: 8 | H88: Medium | I88: Security | J88: Correlation | K88: Streaming | L88: Credential Access | N88: CyberArk Enterprise Password Vault via Syslog | O88: CyberArk-Vault-10 CyberArk-Vault-5 | Q88: 1 | R88: Failure | S88: — | T88: srcIpAddr, srcGeoCountry, user, reptDevName | U88: COUNT (*) >= 3 | V88: 600 | X88: Other: CyberArk-Vault-5 Other: CyberArk-Vault-10 | Z88: Detects excessive unauthorized CyberArk user Stations | AA88: https://filestore.fortinet.com/docs.fortinet.com/fsiem/Public_Resource_Access/7_6_0/rules/PH_RULE_CYBERARK_EXCESS_UNAUTH_USER.htm
A89: PH_RULE_FML_Workspace_Sec_AdminUserAdded | B89: FortiMail Workspace: Admin User Added | C89: Existing, re-tagged ITDR | D89: Identity-core | E89: Privilege/account change | F89: Enabled | G89: 9 | H89: High | I89: Security | J89: Correlation | K89: Streaming | L89: Persistence | M89: T1078.004 | N89: FortiMail Workspace Audit logs via Syslog or HTTPS_ADVANCED | O89: FortiMail-Workspace-Audit-send-user-invitation | Q89: 1 | R89: admin_added | S89: — | T89: user,targetUser,role | U89: COUNT(*)>=1 | V89: 300 | X89: Other: FortiMail-Workspace-Audit-send-user-invitation | Z89: FortiMail Workspace reported that an admin user was added and invitation was sent. | AA89: https://filestore.fortinet.com/docs.fortinet.com/fsiem/Public_Resource_Access/7_6_0/rules/PH_RULE_FML_Workspace_Sec_AdminUserAdded.htm
A90: PH_Rule_TH_Linux_35 | B90: Linux Buffer overflow | C90: Existing, re-tagged ITDR | D90: Identity-core | E90: Privilege Escalation | F90: Enabled | G90: 9 | H90: High | I90: Security | J90: Correlation | K90: Streaming | L90: Privilege Escalation | M90: T1547.009 | N90: Linux via Syslog | O90: CONTAIN:Generic_Unix_ | Q90: 1 | R90: Download | S90: (rawEventMsg CONTAIN "attempt to execute code on stack by" OR rawEventMsg REGEXP ".*FTP LOGIN FROM .* 0bin0sh" OR rawEventMsg REGEXP ".*rpc.statd\[\d+\]: gethostbyname error for" OR rawEventMsg CONTAIN "AAAAAAAAAAAAAAAAAAAAAAAAAAAAAAAAAAAAAAA") AND phEventCategory = 0 | T90: reptDevName | U90: COUNT(*) >= 1 | V90: 300 | X90: Other: Generic_Unix_ | Z90: Detects buffer overflow in linux syslog | AA90: https://filestore.fortinet.com/docs.fortinet.com/fsiem/Public_Resource_Access/7_6_0/rules/PH_RULE_LINUX_BUFFER_OVERFLOW.htm
A91: PH_Rule_TH_EQLLIB_LINUX_8 | B91: Linux: Discovery of Domain Groups | C91: Existing, re-tagged ITDR | D91: Identity-core | E91: Active Directory | F91: Enabled | G91: 5 | H91: Medium | I91: Security | J91: Correlation | K91: Streaming | L91: Discovery | M91: T1069.002 | N91: Linux Process Monitoring via Linux Collector | O91: LINUX_PROCESS_EXEC | Q91: 1 | R91: Filter | S91: (procName IN ("dscacheutil","ldapsearch") OR procName = "dscl" AND swParam CONTAIN "-list") | T91: hostName,procName,swParam | U91: COUNT(*) >= 1 | V91: 300 | X91: Linux Collector: LINUX_PROCESS_EXEC | Z91: Detects attempts to use known commands for discovery of local groups | AA91: https://filestore.fortinet.com/docs.fortinet.com/fsiem/Public_Resource_Access/7_6_0/rules/PH_RULE_Linux_Discovery_of_Domain_Groups.htm
A92: PH_Rule_TH_EQLLIB_LINUX_1 | B92: Linux: Searching for Passwords in Files | C92: Existing, re-tagged ITDR | D92: Identity-core | E92: Credential Access | F92: Enabled | G92: 5 | H92: Medium | I92: Security | J92: Correlation | K92: Streaming | L92: Credential Access | M92: T1552.001 | N92: Linux Process Monitoring via Linux Collector | O92: LINUX_PROCESS_EXEC | Q92: 1 | R92: Filter | S92: procName IN ("cat","grep") AND swParam REGEXP ".*\.bash_history.*|.*passwd.*|.*password.*" | T92: hostName,procName,swParam | U92: COUNT(*) >= 1 | V92: 300 | X92: Linux Collector: LINUX_PROCESS_EXEC | Z92: Detects attempt to search local file systems and remote file shares for files containing passwords. | AA92: https://filestore.fortinet.com/docs.fortinet.com/fsiem/Public_Resource_Access/7_6_0/rules/PH_RULE_Linux_Searching_for_Passwords_in_Files.htm
A93: PH_Rule_TH_Linux_29 | B93: Linux: Setgid Bit Set via chmod | C93: Existing, re-tagged ITDR | D93: Identity-core | E93: Privilege Escalation, Privilege/account change | F93: Enabled | G93: 7 | H93: Medium | I93: Security | J93: Correlation | K93: Streaming | L93: Privilege Escalation | M93: T1548.001 | N93: Linux Process Monitoring via Linux Collector | O93: LINUX_PROCESS_EXEC | Q93: 1 | R93: Filter | S93: procName ="chmod" AND user != "root" AND (swParam CONTAIN "g+s" OR swParam REGEXP (".*2[0-9]{3}.*")) | T93: hostName, user, procName | U93: COUNT(*) >= 1 | V93: 300 | X93: Linux Collector: LINUX_PROCESS_EXEC | Z93: Detects setgid bit to a file or directory - this allows adversary to do operations on the file with the privileges of the owning group. An adversary can take advantage of this to either do a shell escape or exploit a vulnerability in an application with the setgid bit to get code running in a different user context. Additionally, adversaries can use this mechanism on their own malware to make sure they're able to execute in elevated contexts in the future. This requires process monitoring via FortiSOC Linux Collector. | AA93: https://filestore.fortinet.com/docs.fortinet.com/fsiem/Public_Resource_Access/7_6_0/rules/PH_RULE_TH_Linux_Setgid_Via_Chmod.htm
A94: PH_Rule_TH_Linux_30 | B94: Linux: Setuid Bit Set via chmod | C94: Existing, re-tagged ITDR | D94: Identity-core | E94: Privilege Escalation, Privilege/account change | F94: Enabled | G94: 7 | H94: Medium | I94: Security | J94: Correlation | K94: Streaming | L94: Privilege Escalation | M94: T1548.001 | N94: Linux Process Monitoring via Linux Collector | O94: LINUX_PROCESS_EXEC | Q94: 1 | R94: Filter | S94: procName ="chmod" AND user != "root" AND (swParam CONTAIN "u+s" OR swParam REGEXP (".*4[0-9]{3}.*")) | T94: hostName, user, procName | U94: COUNT(*) >= 1 | V94: 300 | X94: Linux Collector: LINUX_PROCESS_EXEC | Z94: Detects setuid bit to a file or directory - this allows adversary to do operations on the file with the privileges of the owning user. An adversary can take advantage of this to either do a shell escape or exploit a vulnerability in an application with the setuid bit to get code running in a different user context. Additionally, adversaries can use this mechanism on their own malware to make sure they're able to execute in elevated contexts in the future. This requires process monitoring via FortiSOC Linux Collector. | AA94: https://filestore.fortinet.com/docs.fortinet.com/fsiem/Public_Resource_Access/7_6_0/rules/PH_RULE_TH_Linux_Setuid_Via_Chmod.htm
A95: PH_Rule_TH_EQLLIB_LINUX_12 | B95: Linux: Trap Signals Usage | C95: Existing, re-tagged ITDR | D95: Identity-core | E95: Privilege Escalation | F95: Enabled | G95: 5 | H95: Medium | I95: Security | J95: Correlation | K95: Streaming | L95: Privilege Escalation | M95: T1546.005 | N95: Linux Process Monitoring via Linux Collector | O95: LINUX_PROCESS_EXEC | Q95: 1 | R95: Filter | S95: procName = "trap" AND swParam CONTAIN " signals" | T95: hostName,procName,swParam | U95: COUNT(*) >= 1 | V95: 300 | X95: Linux Collector: LINUX_PROCESS_EXEC | Z95: Detects attempts to run the trap command that allows programs and shells to specify commands that will be executed upon receiving interrupt signals. | AA95: https://filestore.fortinet.com/docs.fortinet.com/fsiem/Public_Resource_Access/7_6_0/rules/PH_RULE_Linux_Trap_Signals_Usage.htm
A96: PH_Rule_Access_2 | B96: Multiple Login Failures: Net Device | C96: Existing, re-tagged ITDR | D96: Identity-core | E96: Credential Access, Identity event group | F96: Enabled | G96: 9 | H96: High | I96: Security | J96: Correlation | K96: Streaming | L96: Credential Access | M96: T1110.001 | N96: Hillstone Firewall via Syslog Sophos Firewall via Syslog Juniper JunOS via Syslog Pulse Secure via Syslog Juniper SRX via Syslog HP Procurve via Syslog Juniper SSG via Syslog WatchGuard via Syslog FortiProxy via Syslog FortiGate via Syslog Cisco IOS via Syslog Cisco ASA via Syslog NetScaler via Syslog Riverbed via Syslog SonicOS via Syslog | O96: Group@PH_SYS_EVENT_HostLogonFailure Group@PH_SYS_EVENT_MultipleHostLogonFailure | Q96: 2 | R96: ExcessNetLoginFailure OR ExcessNetLoginFailure2 | S96: [ExcessNetLoginFailure] reptDevIpAddr IN (Group@PH_SYS_DEVICE_Network) AND srcIpAddr IS NOT NULL [ExcessNetLoginFailure2] reptDevIpAddr IN (Group@PH_SYS_DEVICE_Network) AND srcIpAddr IS NOT NULL | T96: [ExcessNetLoginFailure] srcIpAddr, srcGeoCountry, reptDevName, reptDevIpAddr, user [ExcessNetLoginFailure2] srcIpAddr, srcGeoCountry, reptDevName, reptDevIpAddr, user | U96: [ExcessNetLoginFailure] COUNT (*) >= 5 [ExcessNetLoginFailure2] COUNT (*) >= 1 | V96: 600 | W96: ExcessNetLoginFailure.srcIpAddr = ExcessNetLoginFailure2.srcIpAddr AND ExcessNetLoginFailure.reptDevIpAddr = ExcessNetLoginFailure2.reptDevIpAddr AND ExcessNetLoginFailure.user = ExcessNetLoginFailure2.user | X96: Event-type group (membership not published): Group@PH_SYS_EVENT_HostLogonFailure Event-type group (membership not published): Group@PH_SYS_EVENT_MultipleHostLogonFailure | Z96: Detects excessive logon failures at a network device - 5 consecutive failures in a 10 minute period. This rule triggers for network devices that report a source IP address. | AA96: https://filestore.fortinet.com/docs.fortinet.com/fsiem/Public_Resource_Access/7_6_0/rules/PH_RULE_EXCESS_FAILED_LOGON_2_NET_DEV.htm
A97: PH_Rule_Access_1 | B97: Multiple Login Failures: Net Device: No Source IP | C97: Existing, re-tagged ITDR | D97: Identity-core | E97: Credential Access, Identity event group | F97: Enabled | G97: 9 | H97: High | I97: Security | J97: Correlation | K97: Streaming | L97: Credential Access | M97: T1110.001 | N97: Network devices via Syslog FortiGate via Syslog | O97: Group@PH_SYS_EVENT_HostLogonFailure Group@PH_SYS_EVENT_MultipleHostLogonFailure | Q97: 2 | R97: ExcessNetLoginFailure OR ExcessNetLoginFailure2 | S97: [ExcessNetLoginFailure] reptDevIpAddr IN (Group@PH_SYS_DEVICE_Network) AND srcIpAddr IS NULL [ExcessNetLoginFailure2] reptDevIpAddr IN (Group@PH_SYS_DEVICE_Network) AND srcIpAddr IS NULL | T97: [ExcessNetLoginFailure] reptDevName,reptDevIpAddr, user [ExcessNetLoginFailure2] reptDevName,reptDevIpAddr, user | U97: [ExcessNetLoginFailure] COUNT (*) >= 5 [ExcessNetLoginFailure2] COUNT (*) >= 1 | V97: 600 | W97: ExcessNetLoginFailure.reptDevIpAddr = ExcessNetLoginFailure2.reptDevIpAddr AND ExcessNetLoginFailure.user = ExcessNetLoginFailure2.user | X97: Event-type group (membership not published): Group@PH_SYS_EVENT_HostLogonFailure Event-type group (membership not published): Group@PH_SYS_EVENT_MultipleHostLogonFailure | Z97: Detects multiple logon failures at a network device - 5 consecutive failures in a 10 minute period. This rule triggers for network devices that do not report a source IP address. | AA97: https://filestore.fortinet.com/docs.fortinet.com/fsiem/Public_Resource_Access/7_6_0/rules/PH_RULE_EXCESS_FAILED_LOGON_NET_DEV.htm
A98: PH_Rule_Access_15B | B98: Multiple Logon Failures: Database | C98: Existing, re-tagged ITDR | D98: Identity-core | E98: Credential Access | F98: Enabled | G98: 9 | H98: High | I98: Security | J98: Correlation | K98: Streaming | L98: Credential Access | M98: T1110.001 | N98: Oracle Database Server via JDBC Microsoft SQL Server via JDBC IBM DB2 via JDBC | O98: Group@PH_SYS_EVENT_DBLogonFailure | Q98: 2 | R98: ExcessDBLoginFailure1 OR ExcessDBLoginFailure2 | S98: [ExcessDBLoginFailure1] — [ExcessDBLoginFailure2] — | T98: [ExcessDBLoginFailure1] srcIpAddr, srcGeoCountry, reptDevName, reptDevIpAddr, user [ExcessDBLoginFailure2] srcName, reptDevName, reptDevIpAddr, user | U98: [ExcessDBLoginFailure1] COUNT (*) >= 5 [ExcessDBLoginFailure2] COUNT (*) >= 5 | V98: 600 | W98: ExcessDBLoginFailure1.reptDevIpAddr = ExcessDBLoginFailure2.reptDevIpAddr AND ExcessDBLoginFailure1.user = ExcessDBLoginFailure2.user | X98: Event-type group (membership not published): Group@PH_SYS_EVENT_DBLogonFailure | Z98: Detects excessive database logon failures - 5 consecutive failures in a 10 minute period | AA98: https://filestore.fortinet.com/docs.fortinet.com/fsiem/Public_Resource_Access/7_6_0/rules/PH_RULE_EXCESS_FAILED_LOGON_DB.htm
A99: PH_Rule_Access_20 | B99: Multiple Logon Failures: Domain | C99: Existing, re-tagged ITDR | D99: Identity-core | E99: Credential Access, Identity event group | F99: Disabled | G99: 4 | H99: Low | I99: Security | J99: Correlation | K99: Streaming | L99: Credential Access | M99: T1110.001 | N99: Microsoft Windows via OMI or Windows Collector | O99: Group@PH_SYS_EVENT_DomainLogonFailure | Q99: 1 | R99: ExcessDomainLoginFailure | S99: reptVendor = "Microsoft" AND user NOT CONTAIN "$" | T99: srcIpAddr, srcGeoCountry, reptDevName, reptDevIpAddr, user, domain | U99: COUNT (*) >= 5 | V99: 600 | X99: Event-type group (membership not published): Group@PH_SYS_EVENT_DomainLogonFailure | Z99: Detects multiple Windows domain logon failures - 5 consecutive failures in a 10 minute period | AA99: https://filestore.fortinet.com/docs.fortinet.com/fsiem/Public_Resource_Access/7_6_0/rules/PH_RULE_EXCESS_FAILED_LOGON_DOMAIN.htm
A100: PH_Rule_Access_15C | B100: Multiple Logon Failures: Misc App | C100: Existing, re-tagged ITDR | D100: Identity-core | E100: Credential Access | F100: Enabled | G100: 6 | H100: Medium | I100: Security | J100: Correlation | K100: Streaming | L100: Credential Access | M100: T1110.001 | N100: Oracle Database Server via JDBC Microsoft SQL Server via JDBC IBM DB2 via JDBC | O100: Group@PH_SYS_EVENT_AppLogonFailure | P100: Group@PH_SYS_EVENT_AAALogonFailure | Q100: 2 | R100: ExcessMiscAppLoginFailure1 OR ExcessMiscAppLoginFailure2 | S100: [ExcessMiscAppLoginFailure1] srcIpAddr IS NOT NULL [ExcessMiscAppLoginFailure2] srcIpAddr IS NULL | T100: [ExcessMiscAppLoginFailure1] srcIpAddr, srcGeoCountry, reptDevName, reptDevIpAddr, user [ExcessMiscAppLoginFailure2] reptDevName, reptDevIpAddr, user | U100: [ExcessMiscAppLoginFailure1] COUNT (*) >= 5 [ExcessMiscAppLoginFailure2] COUNT (*) >= 5 | V100: 600 | X100: Event-type group (membership not published): Group@PH_SYS_EVENT_AppLogonFailure | Z100: Detects excessive application logon failures - 5 consecutive failures in a 10 minute period. Application logsons include the one that may require authentication for accessing the authentication, such as HTTP, SNMP, FTP, POP3, IMAP etc. | AA100: https://filestore.fortinet.com/docs.fortinet.com/fsiem/Public_Resource_Access/7_6_0/rules/PH_RULE_EXCESS_FAILED_LOGON_APPL.htm
A101: PH_Rule_Access_55 | B101: Multiple Logon Failures: Same Src and Dest and Multiple Accounts | C101: Existing, re-tagged ITDR | D101: Identity-core | E101: Credential Access, Identity event group | F101: Enabled | G101: 9 | H101: High | I101: Security | J101: Correlation | K101: Streaming | L101: Credential Access | M101: T1110.001 | N101: Microsoft Windows via OMI or Windows Collector Office 365 via Management Activity API AWS CloudTrail via AWS_CLOUDTRAIL Hillstone Firewall via Syslog Sophos Firewall via Syslog Juniper JunOS via Syslog Pulse Secure via Syslog Juniper SRX via Syslog HP Procurve via Syslog Juniper SSG via Syslog WatchGuard via Syslog VMware NSX via Syslog FortiProxy via Syslog FortiGate via Syslog Cisco IOS via Syslog Cisco ASA via Syslog NetScaler via Syslog FortiSIEM via Syslog Riverbed via Syslog BlueCoat via Syslog FortiWeb via Syslog IBM AIX via Syslog SonicOS via Syslog Linux via Syslog | O101: Group@PH_SYS_EVENT_HostLogonFailure | Q101: 1 | R101: PasswordScan_SameDest_ManyAcct | S101: — | T101: srcIpAddr, srcGeoCountry, destIpAddr, destGeoCountry, destName | U101: COUNT (DISTINCT user) >= 3 | V101: 3600 | X101: Event-type group (membership not published): Group@PH_SYS_EVENT_HostLogonFailure | Z101: Detects same source having excessive login failures at the same destination host but multiple distinct accounts are used during the logon failure | AA101: https://filestore.fortinet.com/docs.fortinet.com/fsiem/Public_Resource_Access/7_6_0/rules/PH_RULE_FAILED_LOGON_MULTIPLE_ACCOUNTS.htm
A102: PH_Rule_Access_54 | B102: Multiple Logon Failures: Same Src and Multiple Dest | C102: Existing, re-tagged ITDR | D102: Identity-core | E102: Credential Access, Identity event group | F102: Enabled | G102: 9 | H102: High | I102: Security | J102: Correlation | K102: Streaming | L102: Credential Access | M102: T1110.001 | N102: Microsoft Windows via OMI or Windows Collector Office 365 via Management Activity API AWS CloudTrail via AWS_CLOUDTRAIL Hillstone Firewall via Syslog Sophos Firewall via Syslog Juniper JunOS via Syslog Pulse Secure via Syslog Juniper SRX via Syslog HP Procurve via Syslog Juniper SSG via Syslog WatchGuard via Syslog VMware NSX via Syslog FortiProxy via Syslog FortiGate via Syslog Cisco IOS via Syslog Cisco ASA via Syslog NetScaler via Syslog FortiSIEM via Syslog Riverbed via Syslog BlueCoat via Syslog FortiWeb via Syslog IBM AIX via Syslog SonicOS via Syslog Linux via Syslog | O102: Group@PH_SYS_EVENT_HostLogonFailure | Q102: 1 | R102: PasswordScan_ManyDest | S102: — | T102: srcIpAddr, srcGeoCountry | U102: COUNT (DISTINCT destIpAddr) >= 10 | V102: 3600 | X102: Event-type group (membership not published): Group@PH_SYS_EVENT_HostLogonFailure | Z102: Detects the same source having excessive logon failures at more than 10 distinct hosts | AA102: https://filestore.fortinet.com/docs.fortinet.com/fsiem/Public_Resource_Access/7_6_0/rules/PH_RULE_FAILED_LOGON_MULTIPLE_HOSTS.htm
A103: PH_Rule_Access_5 | B103: Multiple Logon Failures: Server | C103: Existing, re-tagged ITDR | D103: Identity-core | E103: Credential Access, Identity event group | F103: Enabled | G103: 7 | H103: Medium | I103: Security | J103: Correlation | K103: Streaming | L103: Credential Access | M103: T1110.001 | N103: Microsoft Windows via OMI or Windows Collector VMware NSX via Syslog FortiSIEM via Syslog IBM AIX via Syslog Linux via Syslog | O103: Group@PH_SYS_EVENT_HostLogonFailure Group@PH_SYS_EVENT_MultipleHostLogonFailure | Q103: 2 | R103: ExcessServerLoginFailure OR ExcessServerLoginFailure2 | S103: [ExcessServerLoginFailure] reptDevIpAddr IN (Group@PH_SYS_DEVICE_Server) AND user NOT CONTAIN "$" [ExcessServerLoginFailure2] reptDevIpAddr IN (Group@PH_SYS_DEVICE_Server) AND user NOT CONTAIN "$" | T103: [ExcessServerLoginFailure] srcIpAddr, srcGeoCountry, reptDevName, reptDevIpAddr, user [ExcessServerLoginFailure2] srcIpAddr, srcGeoCountry, reptDevName, reptDevIpAddr, user | U103: [ExcessServerLoginFailure] COUNT (*) >= 5 [ExcessServerLoginFailure2] COUNT (*) >= 1 | V103: 600 | W103: ExcessServerLoginFailure.srcIpAddr = ExcessServerLoginFailure2.srcIpAddr AND ExcessServerLoginFailure.reptDevIpAddr = ExcessServerLoginFailure2.reptDevIpAddr AND ExcessServerLoginFailure.user = ExcessServerLoginFailure2.user | X103: Event-type group (membership not published): Group@PH_SYS_EVENT_HostLogonFailure Event-type group (membership not published): Group@PH_SYS_EVENT_MultipleHostLogonFailure | Z103: Detects excessive logon failures at a server - 5 consecutive failures in a 10 minute period | AA103: https://filestore.fortinet.com/docs.fortinet.com/fsiem/Public_Resource_Access/7_6_0/rules/PH_RULE_EXCESS_FAILED_LOGON_SERVER.htm
A104: PH_Rule_Access_25 | B104: Multiple Logon Failures: VPN | C104: Existing, re-tagged ITDR | D104: Identity-core | E104: Credential Access | F104: Enabled | G104: 6 | H104: Medium | I104: Security | J104: Correlation | K104: Streaming | L104: Credential Access | M104: T1110.001 | N104: Microsoft Windows via OMI or Windows Collector Hillstone Firewall via Syslog Palo Alto PAN-OS via Syslog Sophos Firewall via Syslog Juniper SSLVPN via Syslog Juniper JunOS via Syslog Pulse Secure via Syslog WatchGuard via Syslog FortiProxy via Syslog FortiGate via Syslog Cisco ASA via Syslog SonicOS via Syslog | O104: Group@PH_SYS_EVENT_VPNLogonFailure | Q104: 1 | R104: ExcessVPNLoginFailure | S104: — | T104: srcIpAddr, srcGeoCountry, reptDevName, reptDevIpAddr, user | U104: COUNT (*) >= 5 | V104: 600 | X104: Event-type group (membership not published): Group@PH_SYS_EVENT_VPNLogonFailure | Z104: Detects multiple VPN logon failures - 5 consecutive failures in a 10 minute period | AA104: https://filestore.fortinet.com/docs.fortinet.com/fsiem/Public_Resource_Access/7_6_0/rules/PH_RULE_EXCESS_FAILED_LOGON_VPN.htm
A105: PH_Rule_Access_15A | B105: Multiple Logon Failures: Web Server | C105: Existing, re-tagged ITDR | D105: Identity-core | E105: Credential Access | F105: Enabled | G105: 7 | H105: Medium | I105: Security | J105: Correlation | K105: Streaming | L105: Credential Access | M105: T1110.001 | N105: Microsoft Windows via OMI or Windows Collector VMware NSX via Syslog FortiSIEM via Syslog IBM AIX via Syslog Linux via Syslog | O105: Group@PH_SYS_EVENT_WebLogonFailure | Q105: 1 | R105: ExcessWebLoginFailure | S105: srcIpAddr NOT IN (Group@PH_SYS_APP_ACCELOPS,Group@PH_SYS_DEVICE_FSM) | T105: srcIpAddr, srcGeoCountry, reptDevName, reptDevIpAddr, user | U105: COUNT (*) >= 5 | V105: 900 | X105: Event-type group (membership not published): Group@PH_SYS_EVENT_WebLogonFailure | Z105: Detects excessive Web Server logon failures - 5 consecutive failures in a 15 minute period. | AA105: https://filestore.fortinet.com/docs.fortinet.com/fsiem/Public_Resource_Access/7_6_0/rules/PH_RULE_EXCESS_FAILED_LOGON_WEB.htm
A106: PH_Rule_Access_30 | B106: Multiple Logon Failures: WLAN | C106: Existing, re-tagged ITDR | D106: Identity-core | E106: Credential Access | F106: Enabled | G106: 6 | H106: Medium | I106: Security | J106: Correlation | K106: Streaming | L106: Credential Access | M106: T1110.001 | N106: Motorola WiNG WLAN AP via Syslog Motorola AirDefense via Syslog Sophos Firewall via Syslog WatchGuard via Syslog Cisco WLAN via Syslog Aruba WLC via Syslog | O106: Group@PH_SYS_EVENT_WirelessLogonFailure | Q106: 1 | R106: ExcessWLANLoginFailure | S106: — | T106: srcMACAddr,reptDevName, reptDevIpAddr,user,eventType | U106: COUNT (*) >= 5 | V106: 600 | X106: Event-type group (membership not published): Group@PH_SYS_EVENT_WirelessLogonFailure | Z106: Detects multiple Wireless logon failures - 5 consecutive failures in a 10 minute period | AA106: https://filestore.fortinet.com/docs.fortinet.com/fsiem/Public_Resource_Access/7_6_0/rules/PH_RULE_EXCESS_FAILED_LOGON_WIRELESS.htm
A107: PH_Rule_Access_10 | B107: Multiple Privileged Logon Failures: Server | C107: Existing, re-tagged ITDR | D107: Identity-core | E107: Credential Access, Identity event group | F107: Enabled | G107: 9 | H107: High | I107: Security | J107: Correlation | K107: Streaming | L107: Credential Access | M107: T1110.001 | N107: Microsoft Windows via OMI or Windows Collector VMware NSX via Syslog FortiSIEM via Syslog IBM AIX via Syslog Linux via Syslog | O107: Group@PH_SYS_EVENT_HostPrivLogonFailure PH_RULE_EXCESS_FAILED_LOGON_DOMAIN PH_RULE_EXCESS_FAILED_LOGON_SERVER | Q107: 1 | R107: ExcessPrivLoginFailure | S107: ((user CONTAIN "Admin")) AND reptDevIpAddr IN (Group@PH_SYS_DEVICE_Server) | T107: reptDevName, reptDevIpAddr, user | U107: COUNT (*) >= 3 | V107: 600 | X107: Event-type group (membership not published): Group@PH_SYS_EVENT_HostPrivLogonFailure Other: PH_RULE_EXCESS_FAILED_LOGON_SERVER Other: PH_RULE_EXCESS_FAILED_LOGON_DOMAIN | Z107: Detects excessive privileged logon failures at a server - 3 consecutive failures in a 10 minute period | AA107: https://filestore.fortinet.com/docs.fortinet.com/fsiem/Public_Resource_Access/7_6_0/rules/PH_RULE_EXCESS_FAILED_PRIV_LOGON_SERVER.htm
A108: PH_RULE_OracleOci_UserAddedToGroup | B108: OCI: User Added to a Group | C108: Existing, re-tagged ITDR | D108: Identity-core | E108: Privilege/account change | F108: Enabled | G108: 9 | H108: High | I108: Security | J108: Correlation | K108: Streaming | L108: Persistence | M108: T1098.001 | N108: Oracle OCI via OCI_Streaming_SDK | O108: Oracle-OCI-identitycontrolplane-addusertogroup | Q108: 1 | R108: group_member_add | S108: — | T108: targetUserId,user,groupID | U108: COUNT(*) >= 1 | V108: 120 | X108: Other: Oracle-OCI-identitycontrolplane-addusertogroup | Z108: Oracle OCI user was added to a group | AA108: https://filestore.fortinet.com/docs.fortinet.com/fsiem/Public_Resource_Access/7_6_0/rules/PH_RULE_OracleOci_UserAddedToGroup.htm
...

Sheet Subpatterns
A1: Rule ID | B1: Rule name | C1: ITDR status | D1: Subpattern | E1: Event types | F1: Excluded event types | G1: Filters (non-eventType) | H1: Group-by | I1: Aggregate | J1: Full subpattern query | K1: Trigger expression | L1: Time window (s)
A2: PH_Rule_Azure_Entra_ID_Conditional_Access_Disabled | B2: Azure Entra ID: Conditional Access Disabled | C2: New ITDR (7.6.0) | D2: Filter | E2: MS-Entra-AuditLogs-Policy-Update_policy-success | G2: opName REGEXP ".*(?:Delete conditional access policy|Update conditional access policy).*" | H2: user,opName | I2: COUNT(*) >= 1 | J2: eventType = "MS-Entra-AuditLogs-Policy-Update_policy-success" AND opName REGEXP ".*(?:Delete conditional access policy|Update conditional access policy).*" | K2: Filter | L2: 300
A3: PH_Rule_Azure_Entra_ID_Domain_Authentication_Changed | B3: Azure Entra ID: Domain Authentication Changed | C3: New ITDR (7.6.0) | D3: Filter | E3: MS-Entra-AuditLogs-DirectoryMgmt-Set_domain_authentication-success | H3: user,opName,targetDomain | I3: COUNT(*) >= 1 | J3: eventType = "MS-Entra-AuditLogs-DirectoryMgmt-Set_domain_authentication-success" | K3: Filter | L3: 300
A4: PH_Rule_Azure_Entra_ID_External_User_Added_To_Privileged_Group | B4: Azure Entra ID: External User Added To Privileged Group | C4: New ITDR (7.6.0) | D4: Filter | E4: MS-Entra-AuditLogs-GroupMgmt-Add_member_to_group-success | G4: targetUser CONTAIN "#EXT#" AND groupName CONTAIN "Admin" | H4: user,targetUser,opName,groupName | I4: COUNT(*) >= 1 | J4: eventType = "MS-Entra-AuditLogs-GroupMgmt-Add_member_to_group-success" AND targetUser CONTAIN "#EXT#" AND groupName CONTAIN "Admin" | K4: Filter | L4: 300
A5: PH_Rule_Azure_Entra_ID_MFA_Bypass | B5: Azure Entra ID: MFA Bypass Or Satisfied By Claim | C5: New ITDR (7.6.0) | D5: Filter | E5: MS-Entra-SignInLogs-Logon-success | G5: statusDetailedReason REGEXP ".*(?:bypassed|satisfied by claim|not required).*" | H5: user,srcIpAddr,appName,policyStatus | I5: COUNT(*) >= 1 | J5: eventType = "MS-Entra-SignInLogs-Logon-success" AND statusDetailedReason REGEXP ".*(?:bypassed|satisfied by claim|not required).*" | K5: Filter | L5: 300
A6: PH_Rule_Azure_Entra_ID_New_Federation_Domain_Added | B6: Azure Entra ID: New Federation Domain Added | C6: New ITDR (7.6.0) | D6: Filter | E6: MS-Entra-AuditLogs-DirectoryMgmt-Set_federation_settings_on_domain-success | H6: user,opName,targetDomain | I6: COUNT(*) >= 1 | J6: eventType = "MS-Entra-AuditLogs-DirectoryMgmt-Set_federation_settings_on_domain-success" | K6: Filter | L6: 300
A7: PH_Rule_Azure_Entra_ID_OAuth_Secret_Added | B7: Azure Entra ID: OAuth Secret Added | C7: New ITDR (7.6.0) | D7: Filter | E7: MS-Entra-AuditLogs-ApplicationMgmt-Add_service_principal_credentials-success MS-Entra-AuditLogs-ApplicationMgmt-Update_application_Certificates_and_secrets_Mgmt-success | H7: user,targetUser,opName | I7: COUNT(*) >= 1 | J7: eventType IN ("MS-Entra-AuditLogs-ApplicationMgmt-Add_service_principal_credentials-success","MS-Entra-AuditLogs-ApplicationMgmt-Update_application_Certificates_and_secrets_Mgmt-success") | K7: Filter | L7: 300
A8: PH_Rule_Azure_Entra_ID_User_Added_To_Application_Admin | B8: Azure Entra ID: User Added To Application Admin | C8: New ITDR (7.6.0) | D8: Filter | E8: MS-Entra-AuditLogs-RoleMgmt-Add_member_to_role-success | G8: role = "Application Administrator" | H8: user,opName,role,targetUser | I8: COUNT(*) >= 1 | J8: eventType = "MS-Entra-AuditLogs-RoleMgmt-Add_member_to_role-success" AND role = "Application Administrator" | K8: Filter | L8: 300
A9: PH_Rule_Azure_Entra_ID_User_Added_To_Exchange_Admin | B9: Azure Entra ID: User Added To Exchange Admin | C9: New ITDR (7.6.0) | D9: Filter | E9: MS-Entra-AuditLogs-RoleMgmt-Add_member_to_role-success | G9: role = "Exchange Administrator" | H9: user,opName,role,targetUser | I9: COUNT(*) >= 1 | J9: eventType = "MS-Entra-AuditLogs-RoleMgmt-Add_member_to_role-success" AND role = "Exchange Administrator" | K9: Filter | L9: 300
A10: PH_Rule_Azure_Entra_ID_User_Added_To_Global_Admin | B10: Azure Entra ID: User Added To Global Admin | C10: New ITDR (7.6.0) | D10: Filter | E10: MS-Entra-AuditLogs-RoleMgmt-Add_member_to_role-success | G10: role = "Global Administrator" | H10: user,opName,role,targetUser | I10: COUNT(*) >= 1 | J10: eventType = "MS-Entra-AuditLogs-RoleMgmt-Add_member_to_role-success" AND role = "Global Administrator" | K10: Filter | L10: 300
A11: PH_Rule_Azure_Entra_ID_User_Added_To_Privileged_Role_Admin | B11: Azure Entra ID: User Added To Privileged Role Admin | C11: New ITDR (7.6.0) | D11: Filter | E11: MS-Entra-AuditLogs-RoleMgmt-Add_member_to_role-success | G11: role = "Privileged Role Administrator" | H11: user,opName,role,targetUser | I11: COUNT(*) >= 1 | J11: eventType = "MS-Entra-AuditLogs-RoleMgmt-Add_member_to_role-success" AND role = "Privileged Role Administrator" | K11: Filter | L11: 300
A12: PH_Rule_Azure_Entra_ID_User_Added_To_Security_Admin | B12: Azure Entra ID: User Added To Security Admin | C12: New ITDR (7.6.0) | D12: Filter | E12: MS-Entra-AuditLogs-RoleMgmt-Add_member_to_role-success | G12: role = "Security Administrator" | H12: user,opName,role,targetUser | I12: COUNT(*) >= 1 | J12: eventType = "MS-Entra-AuditLogs-RoleMgmt-Add_member_to_role-success" AND role = "Security Administrator" | K12: Filter | L12: 300
A13: PH_Rule_Linux_etc_shadow_access | B13: Linux: /etc/shadow Access | C13: New ITDR (7.6.0) | D13: Filter | E13: LINUX_Auditd_PATH LINUX_Auditd_SYSCALL LINUX_PROCESS_EXEC | G13: (osObjName="/etc/shadow" OR command REGEXP ".*(?:/etc/shadow|unshadow).*") | H13: hostName,user,procName,command,osObjName | I13: COUNT(*) >= 1 | J13: eventType IN ("LINUX_Auditd_PATH","LINUX_Auditd_SYSCALL","LINUX_PROCESS_EXEC") AND (osObjName="/etc/shadow" OR command REGEXP ".*(?:/etc/shadow|unshadow).*") | K13: Filter | L13: 300
A14: PH_Rule_Linux_Root_Equivalent_Account_Command | B14: Linux: Attempt to Create or Modify a Root-Equivalent Account | C14: New ITDR (7.6.0) | D14: Filter | E14: LINUX_PROCESS_EXEC LINUX_Auditd_SYSCALL | G14: procName REGEXP "(?i).*(useradd|usermod)$" AND command REGEXP "(?i)\s*(?:-u\s*0|--uid(?:\s+|=)\s*0).*" | H14: hostName,user,procName,command | I14: COUNT(*) >= 1 | J14: eventType IN ("LINUX_PROCESS_EXEC","LINUX_Auditd_SYSCALL") AND procName REGEXP "(?i).*(useradd|usermod)$" AND command REGEXP "(?i)\s*(?:-u\s*0|--uid(?:\s+|=)\s*0).*" | K14: Filter | L14: 300
A15: PH_Rule_Linux_PAM_Configuration_Modified | B15: Linux: PAM Configuration Modified | C15: New ITDR (7.6.0) | D15: Filter | E15: FSM_LINUX_FILE_MODIFY | G15: targetOsObjName REGEXP "^/etc/pam\.conf$|^/etc/pam\.d/.*" | H15: hostName,user,targetOsObjName | I15: COUNT(*) >= 1 | J15: eventType = "FSM_LINUX_FILE_MODIFY" AND targetOsObjName REGEXP "^/etc/pam\.conf$|^/etc/pam\.d/.*" | K15: Filter | L15: 300
A16: PH_Rule_Win_Account_Created_Added_To_Privileged_Group | B16: Windows: Account Created Then Added To Privileged Group | C16: New ITDR (7.6.0) | D16: AccountCreated | E16: Win-Security-4720 | G16: targetUser IS NOT NULL AND targetUserSID IS NOT NULL | H16: hostName,user,securityId,targetUser,targetUserSID | I16: COUNT(*) >= 1 | J16: eventType = "Win-Security-4720" AND targetUser IS NOT NULL AND targetUserSID IS NOT NULL | K16: AccountCreated AND AddedToPrivilegedGroup | L16: 1800
A17: PH_Rule_Win_Account_Created_Added_To_Privileged_Group | B17: Windows: Account Created Then Added To Privileged Group | C17: New ITDR (7.6.0) | D17: AddedToPrivilegedGroup | E17: Win-Security-4728 Win-Security-4732 Win-Security-4756 | G17: targetUser IS NOT NULL AND targetUserSID IS NOT NULL AND groupID REGEXP "(?i)^(?:S-1-5-32-(?:544|548|549|550|551|552|555|556|557|569|573|574|578|580)|S-1-5-21-[0-9]+-[0-9]+-[0-9]+-(?:512|518|519|520|526|527))$" | H17: hostName,user,securityId,targetUser,targetUserSID,targetUserGrp,groupID | I17: COUNT(*) >= 1 | J17: eventType IN ("Win-Security-4728","Win-Security-4732","Win-Security-4756") AND targetUser IS NOT NULL AND targetUserSID IS NOT NULL AND groupID REGEXP "(?i)^(?:S-1-5-32-(?:544|548|549|550|551|552|555|556|557|569|573|574|578|580)|S-1-5-21-[0-9]+-[0-9]+-[0-9]+-(?:512|518|519|520|526|527))$" | K17: AccountCreated AND AddedToPrivilegedGroup | L17: 1800
A18: PH_Rule_Win_ADCS_ESC10_Certificate_Mapping_Config_Command | B18: Windows: AD CS ESC10 Certificate Mapping Configuration Changed via Command | C18: New ITDR (7.6.0) | D18: Filter | E18: Win-Security-4688 Win-Sysmon-1-Create-Process Win-PowerShell-4104 | G18: command REGEXP "(?i).*(?:reg(?:\.exe)?\s+(?:add|delete)|Set-ItemProperty|New-ItemProperty|Remove-ItemProperty).*?(?:StrongCertificateBindingEnforcement|CertificateMappingMethods).*" | H18: hostName,user,procName,command | I18: COUNT(*) >= 1 | J18: eventType IN ("Win-Security-4688","Win-Sysmon-1-Create-Process","Win-PowerShell-4104") AND command REGEXP "(?i).*(?:reg(?:\.exe)?\s+(?:add|delete)|Set-ItemProperty|New-ItemProperty|Remove-ItemProperty).*?(?:StrongCertificateBindingEnforcement|CertificateMappingMethods).*" | K18: Filter | L18: 300
A19: PH_Rule_Win_ADCS_ESC13_OID_Group_Link_Modified | B19: Windows: AD CS ESC13 OID Group Link Modified | C19: New ITDR (7.6.0) | D19: Filter | E19: Win-Security-5136 | G19: propName="msDS-OIDToGroupLink" | H19: hostName,user,osObjName,osObjType,propName,propValue | I19: COUNT(*) >= 1 | J19: eventType="Win-Security-5136" AND propName="msDS-OIDToGroupLink" | K19: Filter | L19: 300
... A24: PH_Rule_Win_ADCS_ESC5_PKI_Object_ACL_Modified | B24: Windows: AD CS ESC5 PKI Object ACL Modified | C24: New ITDR (7.6.0) | D24: Filter | E24: Win-Security-5136 | G24: propName="nTSecurityDescriptor" AND osObjName REGEXP "(?i).*(?:CN=Public Key Services|CN=Enrollment Services|CN=Certificate Templates|CN=Certification Authorities|CN=AIA|CN=CDP).*" | H24: hostName,user,osObjName,osObjType,propName | I24: COUNT(*) >= 1 | J24: eventType="Win-Security-5136" AND propName="nTSecurityDescriptor" AND osObjName REGEXP "(?i).*(?:CN=Public Key Services|CN=Enrollment Services|CN=Certificate Templates|CN=Certification Authorities|CN=AIA|CN=CDP).*" | K24: Filter | L24: 300
A25: PH_Rule_Win_ADCS_ESC7_CA_Security_Permissions_Changed | B25: Windows: AD CS ESC7 CA Security Permissions Changed | C25: New ITDR (7.6.0) | D25: Filter | E25: Win-Security-4882 | H25: hostName,user | I25: COUNT(*) >= 1 | J25: eventType="Win-Security-4882" | K25: Filter | L25: 300
A26: PH_Rule_Win_ADCS_Web_Enrollment_Certificate_Request | B26: Windows: AD CS Web Enrollment Certificate Request | C26: New ITDR (7.6.0) | D26: Filter | E26: IIS-Web-Request-Success IIS-Web-Client-Access-Denied IIS-Web-Forbidden-Access-Denied IIS-Web-Bad-Request IIS-Web-Request-Redirect IIS-Web-Client-Error IIS-Web-Server-Error | G26: httpMethod IN ("POST","post") AND uriStem REGEXP "(?i)^.*/certsrv/(?:certfnsh\.asp|certnew\.cer)$" | H26: reptDevName,srcIpAddr,user,httpMethod,uriStem | I26: COUNT(*) >= 1 | J26: eventType IN ("IIS-Web-Request-Success","IIS-Web-Client-Access-Denied","IIS-Web-Forbidden-Access-Denied","IIS-Web-Bad-Request","IIS-Web-Request-Redirect","IIS-Web-Client-Error","IIS-Web-Server-Error") AND httpMethod IN ("POST","post") AND uriStem REGEXP "(?i)^.*/certsrv/(?:certfnsh\.asp|certnew\.cer)$" | K26: Filter | L26: 300
A27: PH_Rule_Win_AdminSDHolder_Modified | B27: Windows: AdminSDHolder Modified | C27: New ITDR (7.6.0) | D27: Filter | E27: Win-Security-5136 | G27: osObjName REGEXP ".*AdminSDHolder.*" | H27: hostName,user,osObjName,propName,propValue | I27: COUNT(*) >= 1 | J27: eventType="Win-Security-5136" AND osObjName REGEXP ".*AdminSDHolder.*" | K27: Filter | L27: 300
A28: PH_Rule_Win_Auth_Package_Modified | B28: Windows: Authentication Package Modified | C28: New ITDR (7.6.0) | D28: Filter | E28: Win-Security-4688 Win-Sysmon-1-Create-Process Win-PowerShell-4104 | G28: command REGEXP ".*(?:Security Packages|Authentication Packages).*" | H28: hostName,user,procName,command | I28: COUNT(*) >= 1 | J28: eventType IN ("Win-Security-4688","Win-Sysmon-1-Create-Process","Win-PowerShell-4104") AND command REGEXP ".*(?:Security Packages|Authentication Packages).*" | K28: Filter | L28: 300
A29: PH_Rule_Win_BloodHound_SharpHound_Execution | B29: Windows: BloodHound or SharpHound Execution | C29: New ITDR (7.6.0) | D29: Filter | E29: Win-Security-4688 Win-Sysmon-1-Create-Process Win-PowerShell-4104 | G29: (procName REGEXP "(?i).*(?:SharpHound|BloodHound)(?:\.exe|\.ps1)?$" OR command REGEXP "(?i).*(?:SharpHound|BloodHound|Invoke-BloodHound|--?CollectionMethods?).*") | H29: hostName,user,procName,command | I29: COUNT(*) >= 1 | J29: eventType IN ("Win-Security-4688","Win-Sysmon-1-Create-Process","Win-PowerShell-4104") AND (procName REGEXP "(?i).*(?:SharpHound|BloodHound)(?:\.exe|\.ps1)?$" OR command REGEXP "(?i).*(?:SharpHound|BloodHound|Invoke-BloodHound|--?CollectionMethods?).*") | K29: Filter | L29: 300
A30: PH_Rule_Win_CA_Configuration_Changed | B30: Windows: CA Configuration Changed | C30: New ITDR (7.6.0) | D30: Filter | E30: Win-Security-4890 Win-Security-4891 Win-Security-4892 Win-Security-4893 Win-Security-4894 | H30: hostName,user | I30: COUNT(*) >= 1 | J30: eventType IN ("Win-Security-4890","Win-Security-4891","Win-Security-4892","Win-Security-4893","Win-Security-4894") | K30: Filter | L30: 300
A31: PH_Rule_Win_Certificate_Template_Modified | B31: Windows: Certificate Template Modified | C31: New ITDR (7.6.0) | D31: Filter | E31: Win-Security-5136 | G31: osObjType = "pKICertificateTemplate" | H31: hostName,user,osObjName,propName | I31: COUNT(*) >= 1 | J31: eventType = "Win-Security-5136" AND osObjType = "pKICertificateTemplate" | K31: Filter | L31: 300
A32: PH_Rule_Win_Certipy_Credential_Abuse | B32: Windows: Certipy Credential Abuse | C32: New ITDR (7.6.0) | D32: Filter | E32: Win-Security-4688 Win-Sysmon-1-Create-Process Win-PowerShell-4104 | G32: command REGEXP ".*certipy.*" | H32: hostName,user,procName,command | I32: COUNT(*) >= 1 | J32: eventType IN ("Win-Security-4688","Win-Sysmon-1-Create-Process","Win-PowerShell-4104") AND command REGEXP ".*certipy.*" | K32: Filter | L32: 300
A33: PH_Rule_Win_Comsvcs_MiniDump_LSASS | B33: Windows: comsvcs.dll MiniDump LSASS | C33: New ITDR (7.6.0) | D33: Filter | E33: Win-Security-4688 Win-Sysmon-1-Create-Process | G33: procName REGEXP ".*rundll32.exe$" AND command REGEXP ".*comsvcs.dll.*MiniDump.*lsass.*" | H33: hostName,user,procName,command | I33: COUNT(*) >= 1 | J33: eventType IN ("Win-Security-4688","Win-Sysmon-1-Create-Process") AND procName REGEXP ".*rundll32.exe$" AND command REGEXP ".*comsvcs.dll.*MiniDump.*lsass.*" | K33: Filter | L33: 300
A34: PH_Rule_Win_Domain_Trust_Modified | B34: Windows: Domain Trust Modified | C34: New ITDR (7.6.0) | D34: Filter | E34: Win-Security-4706 Win-Security-4707 Win-Security-4716 Win-Security-5136 | G34: ((osObjType REGEXP ".*trustedDomain.*")) | H34: hostName,user,osObjName,osObjType | I34: COUNT(*) >= 1 | J34: (eventType IN ("Win-Security-4706","Win-Security-4707","Win-Security-4716") OR (eventType="Win-Security-5136" AND osObjType REGEXP ".*trustedDomain.*")) | K34: Filter | L34: 300
A35: PH_Rule_Win_ESC1_Relevant_Template_Attribute_Modified | B35: Windows: ESC1-Relevant Certificate Template Attribute Modified | C35: New ITDR (7.6.0) | D35: Filter | E35: Win-Security-5136 | G35: osObjType = "pKICertificateTemplate" AND propName REGEXP "(?i)^(?:msPKI-Certificate-Name-Flag|pKIExtendedKeyUsage)$" | H35: hostName,user,osObjName,propName,propValue | I35: COUNT(*) >= 1 | J35: eventType = "Win-Security-5136" AND osObjType = "pKICertificateTemplate" AND propName REGEXP "(?i)^(?:msPKI-Certificate-Name-Flag|pKIExtendedKeyUsage)$" | K35: Filter | L35: 300
A36: PH_Rule_Win_ESC4_Certificate_Template_ACL_Modified | B36: Windows: ESC4 Certificate Template ACL Modified | C36: New ITDR (7.6.0) | D36: Filter | E36: Win-Security-5136 | G36: osObjType = "pKICertificateTemplate" AND propName REGEXP "(?i)^nTSecurityDescriptor$" | H36: hostName,user,osObjName,propName | I36: COUNT(*) >= 1 | J36: eventType = "Win-Security-5136" AND osObjType = "pKICertificateTemplate" AND propName REGEXP "(?i)^nTSecurityDescriptor$" | K36: Filter | L36: 300
A37: PH_Rule_Win_ESC6_EDITF_ATTRIBUTESUBJECTALTNAME2_Enabled | B37: Windows: ESC6 EDITF-ATTRIBUTESUBJECTALTNAME2 Enabled with Certutil | C37: New ITDR (7.6.0) | D37: Filter | E37: Win-Security-4688 Win-Sysmon-1-Create-Process Win-PowerShell-4104 | G37: command REGEXP "(?i).*certutil(?:\.exe)?.*-setreg.*policy\\EditFlags.*\+EDITF_ATTRIBUTESUBJECTALTNAME2.*" | H37: hostName,user,procName,command | I37: COUNT(*) >= 1 | J37: eventType IN ("Win-Security-4688","Win-Sysmon-1-Create-Process","Win-PowerShell-4104") AND command REGEXP "(?i).*certutil(?:\.exe)?.*-setreg.*policy\\EditFlags.*\+EDITF_ATTRIBUTESUBJECTALTNAME2.*" | K37: Filter | L37: 300
A38: PH_Rule_Win_Kerberoasting_Multiple_SPNs | B38: Windows: Kerberoasting Multiple SPNs | C38: New ITDR (7.6.0) | D38: Filter | E38: Win-Security-4769-success | G38: serviceName IS NOT NULL AND serviceName != "krbtgt" | H38: user,srcIpAddr | I38: COUNT(DISTINCT serviceName) >= 10 | J38: eventType = "Win-Security-4769-success" AND serviceName IS NOT NULL AND serviceName != "krbtgt" | K38: Filter | L38: 600
A39: PH_Rule_Win_KRBTGT_Password_Reset | B39: Windows: KRBTGT Password Reset | C39: New ITDR (7.6.0) | D39: Filter | E39: Win-Security-4724 | G39: targetUser="krbtgt" | H39: hostName,user,targetUser | I39: COUNT(*) >= 1 | J39: eventType="Win-Security-4724" AND targetUser="krbtgt" | K39: Filter | L39: 300
A40: PH_Rule_Win_LaZagne_Credential_Dumping | B40: Windows: LaZagne Credential Dumping via Process or PowerShell | C40: New ITDR (7.6.0) | D40: Filter | E40: Win-Security-4688 Win-Sysmon-1-Create-Process Win-PowerShell-4104 | G40: (command REGEXP ".*lazagne.*" OR procName REGEXP ".*lazagne.*") | H40: hostName,user,procName,command | I40: COUNT(*) >= 1 | J40: eventType IN ("Win-Security-4688","Win-Sysmon-1-Create-Process","Win-PowerShell-4104") AND (command REGEXP ".*lazagne.*" OR procName REGEXP ".*lazagne.*") | K40: Filter | L40: 300
A41: PH_Rule_Win_LSASS_Access_By_Suspicious_Process | B41: Windows: LSASS Access by Suspicious Process | C41: New ITDR (7.6.0) | D41: Filter | E41: Win-Sysmon-10-ProcessAccess | G41: targetProcName REGEXP "(?i)^.*lsass\.exe$" AND procName REGEXP "(?i)^.*(?:procdump|procdump64|mimikatz|mimikatz64|rundll32|nanodump|dumpert|createdump|sqldumper)(?:\.exe)?$" | H41: hostName,user,procName,targetProcName | I41: COUNT(*) >= 1 | J41: eventType = "Win-Sysmon-10-ProcessAccess" AND targetProcName REGEXP "(?i)^.*lsass\.exe$" AND procName REGEXP "(?i)^.*(?:procdump|procdump64|mimikatz|mimikatz64|rundll32|nanodump|dumpert|createdump|sqldumper)(?:\.exe)?$" | K41: Filter | L41: 300
A42: PH_Rule_Win_Mass_Group_Membership_Changes | B42: Windows: Mass Group Membership Changes | C42: New ITDR (7.6.0) | D42: Filter | E42: Win-Security-4728 Win-Security-4729 Win-Security-4732 Win-Security-4733 Win-Security-4756 Win-Security-4757 | H42: hostName,user,securityId | I42: COUNT(DISTINCT targetUserSID) >= 10 | J42: eventType IN ("Win-Security-4728","Win-Security-4729","Win-Security-4732","Win-Security-4733","Win-Security-4756","Win-Security-4757") | K42: Filter | L42: 600
A43: PH_Rule_Win_Mass_User_Creation_By_One_Actor | B43: Windows: Mass User Creation By One Actor | C43: New ITDR (7.6.0) | D43: Filter | E43: Win-Security-4720 | H43: hostName,user,securityId | I43: COUNT(DISTINCT targetUserSID) >= 10 | J43: eventType = "Win-Security-4720" | K43: Filter | L43: 600
A44: PH_Rule_Win_Mass_User_Disable_By_One_Actor | B44: Windows: Mass User Disable By One Actor | C44: New ITDR (7.6.0) | D44: Filter | E44: Win-Security-4725 | H44: hostName,user,securityId | I44: COUNT(DISTINCT targetUserSID) >= 10 | J44: eventType = "Win-Security-4725" | K44: Filter | L44: 600
A45: PH_Rule_Win_Mimikatz_Command | B45: Windows: Mimikatz Command | C45: New ITDR (7.6.0) | D45: Filter | E45: Win-Security-4688 Win-Sysmon-1-Create-Process Win-PowerShell-4104 | G45: command REGEXP ".*(?:mimikatz|sekurlsa|lsadump|kerberos::|privilege::debug).*" | H45: hostName,user,procName,command | I45: COUNT(*) >= 1 | J45: eventType IN ("Win-Security-4688","Win-Sysmon-1-Create-Process","Win-PowerShell-4104") AND command REGEXP ".*(?:mimikatz|sekurlsa|lsadump|kerberos::|privilege::debug).*" | K45: Filter | L45: 300
A46: PH_Rule_Win_Nanodump_LSASS_Dumping | B46: Windows: Nanodump LSASS Dumping | C46: New ITDR (7.6.0) | D46: Filter | E46: Win-Security-4688 Win-Sysmon-1-Create-Process Win-PowerShell-4104 | G46: command REGEXP ".*nanodump.*" | H46: hostName,user,procName,command | I46: COUNT(*) >= 1 | J46: eventType IN ("Win-Security-4688","Win-Sysmon-1-Create-Process","Win-PowerShell-4104") AND command REGEXP ".*nanodump.*" | K46: Filter | L46: 300
A47: PH_Rule_Win_Procdump_LSASS_Dump | B47: Windows: Procdump LSASS Dump | C47: New ITDR (7.6.0) | D47: Filter | E47: Win-Security-4688 Win-Sysmon-1-Create-Process | G47: procName REGEXP ".*procdump.*" AND command REGEXP ".*lsass.*" | H47: hostName,user,procName,command | I47: COUNT(*) >= 1 | J47: eventType IN ("Win-Security-4688","Win-Sysmon-1-Create-Process") AND procName REGEXP ".*procdump.*" AND command REGEXP ".*lsass.*" | K47: Filter | L47: 300
A48: PH_Rule_Win_PsExec_Service_Creation | B48: Windows: PsExec Service Creation | C48: New ITDR (7.6.0) | D48: Filter | E48: Win-System-Service-Control-Manager-7045 | G48: (serviceName REGEXP "(?i)^(?:PSEXESVC|PAExec.*|RemComSvc.*)$" OR serviceFileName REGEXP "(?i).*[\\/](?:PSEXESVC|PAExec[^\\/]*|RemComSvc[^\\/]*)\.exe(?:\s.*)?$") | H48: hostName,user,serviceName,serviceFileName | I48: COUNT(*) >= 1 | J48: eventType="Win-System-Service-Control-Manager-7045" AND (serviceName REGEXP "(?i)^(?:PSEXESVC|PAExec.*|RemComSvc.*)$" OR serviceFileName REGEXP "(?i).*[\\/](?:PSEXESVC|PAExec[^\\/]*|RemComSvc[^\\/]*)\.exe(?:\s.*)?$") | K48: Filter | L48: 300
A49: PH_Rule_Win_Pypykatz_Credential_Dumping | B49: Windows: Pypykatz Credential Dumping via Process or PowerShell | C49: New ITDR (7.6.0) | D49: Filter | E49: Win-Security-4688 Win-Sysmon-1-Create-Process Win-PowerShell-4104 | G49: (command REGEXP ".*pypykatz.*" OR procName REGEXP ".*pypykatz.*") | H49: hostName,user,procName,command | I49: COUNT(*) >= 1 | J49: eventType IN ("Win-Security-4688","Win-Sysmon-1-Create-Process","Win-PowerShell-4104") AND (command REGEXP ".*pypykatz.*" OR procName REGEXP ".*pypykatz.*") | K49: Filter | L49: 300
A50: PH_Rule_Win_RBCD_Attribute_Modified | B50: Windows: RBCD Attribute Modified | C50: New ITDR (7.6.0) | D50: Filter | E50: Win-Security-5136 | G50: propName="msDS-AllowedToActOnBehalfOfOtherIdentity" | H50: hostName,user,osObjName,propName | I50: COUNT(*) >= 1 | J50: eventType="Win-Security-5136" AND propName="msDS-AllowedToActOnBehalfOfOtherIdentity" | K50: Filter | L50: 300
A51: PH_Rule_Win_Rubeus_Kerberos_Abuse | B51: Windows: Rubeus Kerberos Abuse | C51: New ITDR (7.6.0) | D51: Filter | E51: Win-Security-4688 Win-Sysmon-1-Create-Process Win-PowerShell-4104 | G51: command REGEXP ".*Rubeus.*" | H51: hostName,user,procName,command | I51: COUNT(*) >= 1 | J51: eventType IN ("Win-Security-4688","Win-Sysmon-1-Create-Process","Win-PowerShell-4104") AND command REGEXP ".*Rubeus.*" | K51: Filter | L51: 300
A52: PH_Rule_Win_SafetyKatz_Credential_Dumping | B52: Windows: SafetyKatz Credential Dumping | C52: New ITDR (7.6.0) | D52: Filter | E52: Win-Security-4688 Win-Sysmon-1-Create-Process Win-PowerShell-4104 | G52: command REGEXP ".*SafetyKatz.*" | H52: hostName,user,procName,command | I52: COUNT(*) >= 1 | J52: eventType IN ("Win-Security-4688","Win-Sysmon-1-Create-Process","Win-PowerShell-4104") AND command REGEXP ".*SafetyKatz.*" | K52: Filter | L52: 300
A53: PH_Rule_Win_Schema_Modification | B53: Windows: Schema Modification | C53: New ITDR (7.6.0) | D53: Filter | E53: Win-Security-5136 | G53: osObjName REGEXP ".*CN=Schema,CN=Configuration.*" | H53: hostName,user,osObjName,propName,propValue | I53: COUNT(*) >= 1 | J53: eventType="Win-Security-5136" AND osObjName REGEXP ".*CN=Schema,CN=Configuration.*" | K53: Filter | L53: 300
A54: PH_Rule_Win_Secretsdump_Execution | B54: Windows: Secretsdump Execution via Process or PowerShell | C54: New ITDR (7.6.0) | D54: Filter | E54: Win-Security-4688 Win-Sysmon-1-Create-Process Win-PowerShell-4104 | G54: (command REGEXP ".*secretsdump.*" OR procName REGEXP ".*secretsdump.*") | H54: hostName,user,procName,command | I54: COUNT(*) >= 1 | J54: eventType IN ("Win-Security-4688","Win-Sysmon-1-Create-Process","Win-PowerShell-4104") AND (command REGEXP ".*secretsdump.*" OR procName REGEXP ".*secretsdump.*") | K54: Filter | L54: 300
A55: PH_Rule_Win_Sensitive_Registry_Hive_Save | B55: Windows: Sensitive Registry Hive Save | C55: New ITDR (7.6.0) | D55: Filter | E55: Win-Security-4688 Win-Sysmon-1-Create-Process | G55: command REGEXP "(?i).*reg(?:\.exe)?\s+save\s+.?(?:HKLM|HKEY_LOCAL_MACHINE)\\(?:SAM|SYSTEM|SECURITY).*" | H55: hostName,user,procName,command | I55: COUNT(*) >= 1 | J55: eventType IN ("Win-Security-4688","Win-Sysmon-1-Create-Process") AND command REGEXP "(?i).*reg(?:\.exe)?\s+save\s+.?(?:HKLM|HKEY_LOCAL_MACHINE)\\(?:SAM|SYSTEM|SECURITY).*" | K55: Filter | L55: 300
A56: PH_Rule_Win_Shadow_Credentials_KeyCredentialLink_Modified | B56: Windows: Shadow Credentials KeyCredentialLink Modified | C56: New ITDR (7.6.0) | D56: Filter | E56: Win-Security-5136 | G56: propName = "msDS-KeyCredentialLink" | H56: hostName,user,osObjName,propName | I56: COUNT(*) >= 1 | J56: eventType = "Win-Security-5136" AND propName = "msDS-KeyCredentialLink" | K56: Filter | L56: 300
... A59: PH_Rule_Win_Token_Impersonation_Tool | B59: Windows: Token Impersonation Tool | C59: New ITDR (7.6.0) | D59: Filter | E59: Win-Security-4688 Win-Sysmon-1-Create-Process Win-PowerShell-4104 | G59: (procName REGEXP "(?i).*(?:incognito|JuicyPotato|RoguePotato|PrintSpoofer|GodPotato).*" OR command REGEXP "(?i).*(?:incognito|JuicyPotato|RoguePotato|PrintSpoofer|GodPotato).*") | H59: hostName,user,procName,command | I59: COUNT(*) >= 1 | J59: eventType IN ("Win-Security-4688","Win-Sysmon-1-Create-Process","Win-PowerShell-4104") AND (procName REGEXP "(?i).*(?:incognito|JuicyPotato|RoguePotato|PrintSpoofer|GodPotato).*" OR command REGEXP "(?i).*(?:incognito|JuicyPotato|RoguePotato|PrintSpoofer|GodPotato).*") | K59: Filter | L59: 300
A60: PH_Rule_Access_51A | B60: Account Locked: Domain | C60: Existing, re-tagged ITDR | D60: DomainAcctLockout | E60: Group@PH_SYS_EVENT_DomainAccountLocked | H60: reptDevName,reptDevIpAddr, user | I60: COUNT (*) >= 1 | J60: eventType IN (Group@PH_SYS_EVENT_DomainAccountLocked) | K60: DomainAcctLockout | L60: 600
A61: PH_Rule_Access_51D | B61: Account Locked: FortiSIEM | C61: Existing, re-tagged ITDR | D61: AOLockout | E61: PH_AUDIT_ACCOUNT_LOCKED | H61: srcIpAddr, srcGeoCountry, targetUser, reptDevName | I61: COUNT (*) >= 1 | J61: eventType = "PH_AUDIT_ACCOUNT_LOCKED" | K61: AOLockout | L61: 600
A62: PH_Rule_Access_51B | B62: Account Locked: Network Device | C62: Existing, re-tagged ITDR | D62: NetDevAcctLockout | E62: Group@PH_SYS_EVENT_HostAccountLocked | G62: reptDevIpAddr IN (Group@PH_SYS_DEVICE_Network) | H62: srcIpAddr, srcGeoCountry, reptDevName, reptDevIpAddr, user | I62: COUNT (*) >= 1 | J62: eventType IN (Group@PH_SYS_EVENT_HostAccountLocked) AND reptDevIpAddr IN (Group@PH_SYS_DEVICE_Network) | K62: NetDevAcctLockout | L62: 600
A63: PH_Rule_Access_51C | B63: Account Locked: Server | C63: Existing, re-tagged ITDR | D63: ServerAcctLockout | E63: Group@PH_SYS_EVENT_HostAccountLocked | F63: PH_AUDIT_ACCOUNT_LOCKED | G63: reptDevIpAddr IN (Group@PH_SYS_DEVICE_Server) | H63: reptDevName,reptDevIpAddr, user | I63: COUNT (*) >= 1 | J63: eventType IN (Group@PH_SYS_EVENT_HostAccountLocked) AND reptDevIpAddr IN (Group@PH_SYS_DEVICE_Server) AND eventType != "PH_AUDIT_ACCOUNT_LOCKED" | K63: ServerAcctLockout | L63: 600
A64: PH_Rule_ES_IMPORT_AWS_1 | B64: AWS IAM Brute Force of Assume Role Policy | C64: Existing, re-tagged ITDR | D64: Filter | E64: CONTAIN:AWS-CloudTrail-IAM-UpdateAssumeRolePolicy | G64: errorString = "MalformedPolicyDocumentException" | H64: accountId,user | I64: COUNT(*) >= 5 | J64: eventType CONTAIN "AWS-CloudTrail-IAM-UpdateAssumeRolePolicy" AND errorString = "MalformedPolicyDocumentException" | K64: Filter | L64: 300
A65: PH_Rule_ES_IMPORT_AWS_21 | B65: AWS IAM MFA Device Deactivated | C65: Existing, re-tagged ITDR | D65: Filter | E65: CONTAIN:AWS-CloudTrail-IAM-DeactivateMFADevice | H65: accountId,user | I65: COUNT(*) >= 1 | J65: eventType CONTAIN "AWS-CloudTrail-IAM-DeactivateMFADevice" | K65: Filter | L65: 300
A66: PH_Rule_ES_IMPORT_AWS_26 | B66: AWS IAM Password Recovery Requested | C66: Existing, re-tagged ITDR | D66: Filter | E66: CONTAIN:AWS-CloudTrail-SIGNIN-PasswordRecoveryRequested | H66: accountId,user | I66: COUNT(*) >= 1 | J66: eventType CONTAIN "AWS-CloudTrail-SIGNIN-PasswordRecoveryRequested" | K66: Filter | L66: 300
A67: PH_Rule_ES_IMPORT_AWS_3 | B67: AWS Management Console Brute Force of Root User Identity | C67: Existing, re-tagged ITDR | D67: Filter | E67: CONTAIN:AWS-CloudTrail-SIGNIN-ConsoleLogin | G67: identityType = "Root" AND status = "failed" | H67: accountId,accountName,user | I67: COUNT(*) >= 5 | J67: eventType CONTAIN "AWS-CloudTrail-SIGNIN-ConsoleLogin" AND identityType = "Root" AND status = "failed" | K67: Filter | L67: 300
A68: PH_Rule_ES_IMPORT_AWS_30 | B68: AWS Root Login Without MFA | C68: Existing, re-tagged ITDR | D68: Filter | E68: AWS-CloudTrail-SIGNIN-ConsoleLogin-Success | G68: identityType = "Root" AND mfaAuthenticated != "Yes" | H68: accountId,accountName,user,srcIpAddr | I68: COUNT(*) >= 1 | J68: eventType = "AWS-CloudTrail-SIGNIN-ConsoleLogin-Success" AND identityType = "Root" AND mfaAuthenticated != "Yes" | K68: Filter | L68: 300
A69: PH_Rule_AWSSecHub_7 | B69: AWS SecHub: Tactics: Credential Access Detected | C69: Existing, re-tagged ITDR | D69: AWSDetect | E69: AWS-Hub-TTPs-Credential_Access | H69: ec2InstanceId,awsRegion | I69: COUNT(*) >= 1 | J69: eventType = "AWS-Hub-TTPs-Credential_Access" | K69: AWSDetect | L69: 300
A70: PH_Rule_AWSSecHub_5 | B70: AWS SecHub: Tactics: Privilege Escalation Detected | C70: Existing, re-tagged ITDR | D70: AWSDetect | E70: AWS-Hub-TTPs-Privilege_Escalation | H70: ec2InstanceId,awsRegion | I70: COUNT(*) >= 1 | J70: eventType = "AWS-Hub-TTPs-Privilege_Escalation" | K70: AWSDetect | L70: 300
A71: PH_Rule_ES_IMPORT_AWS_4 | B71: AWS Secret Accessed in Secrets Manager | C71: Existing, re-tagged ITDR | D71: Filter | E71: CONTAIN:AWS-CloudTrail-SECRETSMANAGER-GetSecretValue | G71: identityType != "AWSService" AND status = "success" | H71: accountId,user | I71: COUNT(*) >= 1 | J71: eventType CONTAIN "AWS-CloudTrail-SECRETSMANAGER-GetSecretValue" AND identityType != "AWSService" AND status = "success" | K71: Filter | L71: 300
A72: PH_Rule_ES_IMPORT_AZURE_17 | B72: Azure Global Administrator Role Added to PIM User | C72: Existing, re-tagged ITDR | D72: Filter | E72: MS_EvtHub_add_member_to_role_in_pim_completed_timebound MS_EvtHub_add_eligible_member_to_role_in_pim_completed_permanent | G72: azureEventCategory = "RoleManagement" AND srcName = "Global Administrator" | H72: azureEventCategory,srcName,user | I72: COUNT(*) >= 1 | J72: azureEventCategory = "RoleManagement" AND eventType IN ("MS_EvtHub_add_member_to_role_in_pim_completed_timebound","MS_EvtHub_add_eligible_member_to_role_in_pim_completed_permanent") AND srcName = "Global Administrator" | K72: Filter | L72: 300
A73: PH_Rule_Access_75 | B73: Brute Force App Login Success | C73: Existing, re-tagged ITDR | D73: FailedLogin | E73: Group@PH_SYS_EVENT_VPNLogonFailure Group@PH_SYS_EVENT_DBLogonFailure Group@PH_SYS_EVENT_WebLogonFailure Group@PH_SYS_EVENT_AppLogonFailure | G73: user IS NOT NULL | H73: srcIpAddr, srcGeoCountry, reptDevIpAddr, user | I73: COUNT(*) >= 5 | J73: eventType IN (Group@PH_SYS_EVENT_VPNLogonFailure,Group@PH_SYS_EVENT_DBLogonFailure,Group@PH_SYS_EVENT_WebLogonFailure,Group@PH_SYS_EVENT_AppLogonFailure) AND user IS NOT NULL | K73: FailedLogin OR FailedLogin2 FOLLOWED_BY SuccessLogin | L73: 900
A74: PH_Rule_Access_75 | B74: Brute Force App Login Success | C74: Existing, re-tagged ITDR | D74: FailedLogin2 | E74: Group@PH_SYS_EVENT_MultipleVPNLogonFailure Group@PH_SYS_EVENT_MultipleDBLogonFailure Group@PH_SYS_EVENT_MultipleWebLogonFailure Group@PH_SYS_EVENT_MultipleAppLogonFailure | G74: user IS NOT NULL | H74: srcIpAddr, srcGeoCountry, reptDevIpAddr, user | I74: COUNT(*) >= 1 | J74: eventType IN (Group@PH_SYS_EVENT_MultipleVPNLogonFailure,Group@PH_SYS_EVENT_MultipleDBLogonFailure,Group@PH_SYS_EVENT_MultipleWebLogonFailure,Group@PH_SYS_EVENT_MultipleAppLogonFailure) AND user IS NOT NULL | K74: FailedLogin OR FailedLogin2 FOLLOWED_BY SuccessLogin | L74: 900
A75: PH_Rule_Access_75 | B75: Brute Force App Login Success | C75: Existing, re-tagged ITDR | D75: SuccessLogin | E75: Group@PH_SYS_EVENT_VPNLogonSuccess Group@PH_SYS_EVENT_DBLogonSuccess Group@PH_SYS_EVENT_WebLogonSuccess Group@PH_SYS_EVENT_AppLogonSuccess | G75: user IS NOT NULL | H75: srcIpAddr, srcGeoCountry, reptDevName, reptDevIpAddr, user | I75: COUNT (*) >= 1 | J75: eventType IN (Group@PH_SYS_EVENT_VPNLogonSuccess,Group@PH_SYS_EVENT_DBLogonSuccess,Group@PH_SYS_EVENT_WebLogonSuccess,Group@PH_SYS_EVENT_AppLogonSuccess) AND user IS NOT NULL | K75: FailedLogin OR FailedLogin2 FOLLOWED_BY SuccessLogin | L75: 900
A76: PH_Rule_Access_70 | B76: Brute Force Host Login Success | C76: Existing, re-tagged ITDR | D76: FailedLogin | E76: Group@PH_SYS_EVENT_HostLogonFailure Group@PH_SYS_EVENT_VMware_LogonFailure Group@PH_SYS_EVENT_DomainLogonFailure | G76: user IS NOT NULL | H76: srcIpAddr, srcGeoCountry, reptDevIpAddr, user | I76: COUNT(*) >= 5 | J76: eventType IN (Group@PH_SYS_EVENT_HostLogonFailure,Group@PH_SYS_EVENT_VMware_LogonFailure,Group@PH_SYS_EVENT_DomainLogonFailure) AND user IS NOT NULL | K76: FailedLogin OR FailedLogin2 FOLLOWED_BY SuccessLogin | L76: 900
A77: PH_Rule_Access_70 | B77: Brute Force Host Login Success | C77: Existing, re-tagged ITDR | D77: FailedLogin2 | E77: Group@PH_SYS_EVENT_MultipleHostLogonFailure Group@PH_SYS_EVENT_MultipleDomainLogonFailure | G77: user IS NOT NULL | H77: srcIpAddr, srcGeoCountry, reptDevIpAddr, user | I77: COUNT(*) >= 1 | J77: eventType IN (Group@PH_SYS_EVENT_MultipleHostLogonFailure,Group@PH_SYS_EVENT_MultipleDomainLogonFailure) AND user IS NOT NULL | K77: FailedLogin OR FailedLogin2 FOLLOWED_BY SuccessLogin | L77: 900
A78: PH_Rule_Access_70 | B78: Brute Force Host Login Success | C78: Existing, re-tagged ITDR | D78: SuccessLogin | E78: Group@PH_SYS_EVENT_HostLogonSuccess Group@PH_SYS_EVENT_VMware_LogonSuccess Group@PH_SYS_EVENT_DomainLogonSuccess | G78: user IS NOT NULL | H78: srcIpAddr, srcGeoCountry, reptDevName, reptDevIpAddr, user | I78: COUNT (*) >= 1 | J78: eventType IN (Group@PH_SYS_EVENT_HostLogonSuccess,Group@PH_SYS_EVENT_VMware_LogonSuccess,Group@PH_SYS_EVENT_DomainLogonSuccess) AND user IS NOT NULL | K78: FailedLogin OR FailedLogin2 FOLLOWED_BY SuccessLogin | L78: 900
A79: PH_Rule_Access_63 | B79: Concurrent Failed Authentications To Same Account From Multiple Countries | C79: Existing, re-tagged ITDR | D79: MultiCountryLogon | E79: Group@PH_SYS_EVENT_HostLogonFailure Group@PH_SYS_EVENT_DomainLogonFailure | G79: user IS NOT NULL AND srcGeoCountry IS NOT NULL | H79: reptDevName,reptDevIpAddr,user | I79: COUNT (DISTINCT srcGeoCountry) >= 2 | J79: eventType IN (Group@PH_SYS_EVENT_HostLogonFailure,Group@PH_SYS_EVENT_DomainLogonFailure) AND user IS NOT NULL AND srcGeoCountry IS NOT NULL | K79: MultiCountryLogon | L79: 3600
A80: PH_Rule_Access_61 | B80: Concurrent Successful Authentications To Same Account From Multiple Countries | C80: Existing, re-tagged ITDR | D80: MultiCountryLogon | E80: Group@PH_SYS_EVENT_HostLogonSuccess Group@PH_SYS_EVENT_DomainLogonSuccess | G80: user IS NOT NULL AND srcGeoCountry IS NOT NULL | H80: reptDevName,reptDevIpAddr,user | I80: COUNT (DISTINCT srcGeoCountry) >= 2 | J80: eventType IN (Group@PH_SYS_EVENT_HostLogonSuccess,Group@PH_SYS_EVENT_DomainLogonSuccess) AND user IS NOT NULL AND srcGeoCountry IS NOT NULL | K80: MultiCountryLogon | L80: 3600
A81: PH_Rule_Access_65 | B81: Concurrent Successful VPN Authentications To Same Account From Different Countries | C81: Existing, re-tagged ITDR | D81: VPNLogonDistinctCity | E81: Group@PH_SYS_EVENT_VPNLogonSuccess | G81: user IS NOT NULL AND user != "N/A" AND srcGeoCountry IS NOT NULL AND srcGeoCountry != "N/A" | H81: user | I81: COUNT(DISTINCT srcGeoCountry) >= 2 | J81: eventType IN (Group@PH_SYS_EVENT_VPNLogonSuccess) AND user IS NOT NULL AND user != "N/A" AND srcGeoCountry IS NOT NULL AND srcGeoCountry != "N/A" | K81: VPNLogonDistinctCity | L81: 3600
A82: PH_Rule_Exploits_CS_1C | B82: Crowdstrike: Authentication Bypass | C82: Existing, re-tagged ITDR | D82: CSDetect | E82: Crowdstrike-Falcon-EppDetectionSummaryEvent-authentication-bypass Crowdstrike-Falcon-EppDetectionSummaryEvent-authentication-bypass-block | H82: hostName,attackTactic,attackTechnique,command,subtype | I82: COUNT(*) >= 1 | J82: eventType IN ("Crowdstrike-Falcon-EppDetectionSummaryEvent-authentication-bypass","Crowdstrike-Falcon-EppDetectionSummaryEvent-authentication-bypass-block") | K82: CSDetect | L82: 300
A83: PH_Rule_Exploits_CS_4 | B83: Crowdstrike: Credential Theft Detected | C83: Existing, re-tagged ITDR | D83: CSDetect | E83: Crowdstrike-Falcon-EppDetectionSummaryEvent-credential-theft Crowdstrike-Falcon-EppDetectionSummaryEvent-credential-theft-block Crowdstrike-Falcon-EppDetectionSummaryEvent-credential-theft-allow | H83: hostName,attackTactic,attackTechnique,command,subtype | I83: COUNT(*) >= 1 | J83: eventType IN ("Crowdstrike-Falcon-EppDetectionSummaryEvent-credential-theft","Crowdstrike-Falcon-EppDetectionSummaryEvent-credential-theft-block","Crowdstrike-Falcon-EppDetectionSummaryEvent-credential-theft-allow") | K83: CSDetect | L83: 300
A84: PH_Rule_Exploits_CS_14 | B84: Crowdstrike: Privilege Escalation | C84: Existing, re-tagged ITDR | D84: CSDetect | E84: Crowdstrike-Falcon-EppDetectionSummaryEvent-privilege-escalation Crowdstrike-Falcon-EppDetectionSummaryEvent-privilege-escalation-allow Crowdstrike-Falcon-EppDetectionSummaryEvent-privilege-escalation-block | H84: hostName,attackTactic,attackTechnique,command,subtype | I84: COUNT(*) >= 1 | J84: eventType IN ("Crowdstrike-Falcon-EppDetectionSummaryEvent-privilege-escalation","Crowdstrike-Falcon-EppDetectionSummaryEvent-privilege-escalation-allow","Crowdstrike-Falcon-EppDetectionSummaryEvent-privilege-escalation-block") | K84: CSDetect | L84: 300
A85: PH_Rule_CyberArk_11 | B85: CyberArk Vault Blocked Operations | C85: Existing, re-tagged ITDR | D85: Failure | E85: CyberArk-Vault-403 CyberArk-Vault-408 CyberArk-Vault-409 | H85: srcIpAddr, srcGeoCountry, user, cyberArkSafe, fileName, reptDevName | I85: COUNT (*) >= 2 | J85: eventType IN ("CyberArk-Vault-403","CyberArk-Vault-408","CyberArk-Vault-409") | K85: Failure | L85: 600
A86: PH_Rule_CyberArk_2 | B86: CyberArk Vault Excessive Failed PSM Connections | C86: Existing, re-tagged ITDR | D86: Failure | E86: CyberArk-Vault-301 CyberArk-Vault-379 | H86: srcIpAddr, srcGeoCountry, user, cyberArkSafe, fileName, reptDevName | I86: COUNT (*) >= 3 | J86: eventType IN ("CyberArk-Vault-301","CyberArk-Vault-379") | K86: Failure | L86: 600
A87: PH_Rule_CyberArk_6 | B87: CyberArk Vault Excessive Impersonations | C87: Existing, re-tagged ITDR | D87: Failure | E87: CyberArk-Vault-15 CyberArk-Vault-18 | H87: srcIpAddr, srcGeoCountry, user, reptDevName | I87: COUNT (*) >= 3 | J87: eventType IN ("CyberArk-Vault-15","CyberArk-Vault-18") | K87: Failure | L87: 600
A88: PH_Rule_CyberArk_1 | B88: CyberArk Vault Excessive Password Release Failure | C88: Existing, re-tagged ITDR | D88: Failure | E88: CyberArk-Vault-137 | H88: srcIpAddr, srcGeoCountry, user, cyberArkSafe, fileName, reptDevName | I88: COUNT (*) >= 3 | J88: eventType = "CyberArk-Vault-137" | K88: Failure | L88: 600
A89: PH_Rule_CyberArk_3 | B89: CyberArk Vault Excessive PSM Keystroke Logging Failure | C89: Existing, re-tagged ITDR | D89: Failure | E89: CyberArk-Vault-362 CyberArk-Vault-413 | H89: srcIpAddr, srcGeoCountry, user, cyberArkSafe, fileName, reptDevName | I89: COUNT (*) >= 3 | J89: eventType IN ("CyberArk-Vault-362","CyberArk-Vault-413") | K89: Failure | L89: 600
A90: PH_Rule_CyberArk_4 | B90: CyberArk Vault Excessive PSM Session Monitoring Failure | C90: Existing, re-tagged ITDR | D90: Failure | E90: CyberArk-Vault-375 | H90: srcIpAddr, srcGeoCountry, user, cyberArkSafe, fileName, reptDevName | I90: COUNT (*) >= 3 | J90: eventType = "CyberArk-Vault-375" | K90: Failure | L90: 600
A91: PH_Rule_CyberArk_10 | B91: CyberArk Vault File Operation Failure | C91: Existing, re-tagged ITDR | D91: Failure | E91: CyberArk-Vault-204 CyberArk-Vault-205 | H91: srcIpAddr, srcGeoCountry, user, cyberArkSafe, fileName, reptDevName | I91: COUNT (*) >= 2 | J91: eventType IN ("CyberArk-Vault-204","CyberArk-Vault-205") | K91: Failure | L91: 600
A92: PH_Rule_CyberArk_9 | B92: CyberArk Vault Object Content Validation Failure | C92: Existing, re-tagged ITDR | D92: Failure | E92: CyberArk-Vault-366 | H92: srcIpAddr, srcGeoCountry, user, cyberArkSafe, fileName, reptDevName | I92: COUNT (*) >= 2 | J92: eventType = "CyberArk-Vault-366" | K92: Failure | L92: 600
A93: PH_Rule_CyberArk_5 | B93: CyberArk Vault Unauthorized User Stations | C93: Existing, re-tagged ITDR | D93: Failure | E93: CyberArk-Vault-5 CyberArk-Vault-10 | H93: srcIpAddr, srcGeoCountry, user, reptDevName | I93: COUNT (*) >= 3 | J93: eventType IN ("CyberArk-Vault-5","CyberArk-Vault-10") | K93: Failure | L93: 600
A94: PH_RULE_FML_Workspace_Sec_AdminUserAdded | B94: FortiMail Workspace: Admin User Added | C94: Existing, re-tagged ITDR | D94: admin_added | E94: FortiMail-Workspace-Audit-send-user-invitation | H94: user,targetUser,role | I94: COUNT(*)>=1 | J94: eventType="FortiMail-Workspace-Audit-send-user-invitation" | K94: admin_added | L94: 300
A95: PH_Rule_TH_Linux_35 | B95: Linux Buffer overflow | C95: Existing, re-tagged ITDR | D95: Download | E95: CONTAIN:Generic_Unix_ | G95: (rawEventMsg CONTAIN "attempt to execute code on stack by" OR rawEventMsg REGEXP ".*FTP LOGIN FROM .* 0bin0sh" OR rawEventMsg REGEXP ".*rpc.statd\[\d+\]: gethostbyname error for" OR rawEventMsg CONTAIN "AAAAAAAAAAAAAAAAAAAAAAAAAAAAAAAAAAAAAAA") AND phEventCategory = 0 | H95: reptDevName | I95: COUNT(*) >= 1 | J95: eventType CONTAIN "Generic_Unix_" AND (rawEventMsg CONTAIN "attempt to execute code on stack by" OR rawEventMsg REGEXP ".*FTP LOGIN FROM .* 0bin0sh" OR rawEventMsg REGEXP ".*rpc.statd\[\d+\]: gethostbyname error for" OR rawEventMsg CONTAIN "AAAAAAAAAAAAAAAAAAAAAAAAAAAAAAAAAAAAAAA") AND phEventCategory = 0 | K95: Download | L95: 300
A96: PH_Rule_TH_EQLLIB_LINUX_8 | B96: Linux: Discovery of Domain Groups | C96: Existing, re-tagged ITDR | D96: Filter | E96: LINUX_PROCESS_EXEC | G96: (procName IN ("dscacheutil","ldapsearch") OR procName = "dscl" AND swParam CONTAIN "-list") | H96: hostName,procName,swParam | I96: COUNT(*) >= 1 | J96: eventType = "LINUX_PROCESS_EXEC" AND (procName IN ("dscacheutil","ldapsearch") OR procName = "dscl" AND swParam CONTAIN "-list") | K96: Filter | L96: 300
A97: PH_Rule_TH_EQLLIB_LINUX_1 | B97: Linux: Searching for Passwords in Files | C97: Existing, re-tagged ITDR | D97: Filter | E97: LINUX_PROCESS_EXEC | G97: procName IN ("cat","grep") AND swParam REGEXP ".*\.bash_history.*|.*passwd.*|.*password.*" | H97: hostName,procName,swParam | I97: COUNT(*) >= 1 | J97: eventType = "LINUX_PROCESS_EXEC" AND procName IN ("cat","grep") AND swParam REGEXP ".*\.bash_history.*|.*passwd.*|.*password.*" | K97: Filter | L97: 300
A98: PH_Rule_TH_Linux_29 | B98: Linux: Setgid Bit Set via chmod | C98: Existing, re-tagged ITDR | D98: Filter | E98: LINUX_PROCESS_EXEC | G98: procName ="chmod" AND user != "root" AND (swParam CONTAIN "g+s" OR swParam REGEXP (".*2[0-9]{3}.*")) | H98: hostName, user, procName | I98: COUNT(*) >= 1 | J98: eventType = "LINUX_PROCESS_EXEC" AND procName ="chmod" AND user != "root" AND (swParam CONTAIN "g+s" OR swParam REGEXP (".*2[0-9]{3}.*")) | K98: Filter | L98: 300
A99: PH_Rule_TH_Linux_30 | B99: Linux: Setuid Bit Set via chmod | C99: Existing, re-tagged ITDR | D99: Filter | E99: LINUX_PROCESS_EXEC | G99: procName ="chmod" AND user != "root" AND (swParam CONTAIN "u+s" OR swParam REGEXP (".*4[0-9]{3}.*")) | H99: hostName, user, procName | I99: COUNT(*) >= 1 | J99: eventType = "LINUX_PROCESS_EXEC" AND procName ="chmod" AND user != "root" AND (swParam CONTAIN "u+s" OR swParam REGEXP (".*4[0-9]{3}.*")) | K99: Filter | L99: 300
A100: PH_Rule_TH_EQLLIB_LINUX_12 | B100: Linux: Trap Signals Usage | C100: Existing, re-tagged ITDR | D100: Filter | E100: LINUX_PROCESS_EXEC | G100: procName = "trap" AND swParam CONTAIN " signals" | H100: hostName,procName,swParam | I100: COUNT(*) >= 1 | J100: eventType = "LINUX_PROCESS_EXEC" AND procName = "trap" AND swParam CONTAIN " signals" | K100: Filter | L100: 300
A101: PH_Rule_Access_2 | B101: Multiple Login Failures: Net Device | C101: Existing, re-tagged ITDR | D101: ExcessNetLoginFailure | E101: Group@PH_SYS_EVENT_HostLogonFailure | G101: reptDevIpAddr IN (Group@PH_SYS_DEVICE_Network) AND srcIpAddr IS NOT NULL | H101: srcIpAddr, srcGeoCountry, reptDevName, reptDevIpAddr, user | I101: COUNT (*) >= 5 | J101: eventType IN (Group@PH_SYS_EVENT_HostLogonFailure) AND reptDevIpAddr IN (Group@PH_SYS_DEVICE_Network) AND srcIpAddr IS NOT NULL | K101: ExcessNetLoginFailure OR ExcessNetLoginFailure2 | L101: 600
A102: PH_Rule_Access_2 | B102: Multiple Login Failures: Net Device | C102: Existing, re-tagged ITDR | D102: ExcessNetLoginFailure2 | E102: Group@PH_SYS_EVENT_MultipleHostLogonFailure | G102: reptDevIpAddr IN (Group@PH_SYS_DEVICE_Network) AND srcIpAddr IS NOT NULL | H102: srcIpAddr, srcGeoCountry, reptDevName, reptDevIpAddr, user | I102: COUNT (*) >= 1 | J102: eventType IN (Group@PH_SYS_EVENT_MultipleHostLogonFailure) AND reptDevIpAddr IN (Group@PH_SYS_DEVICE_Network) AND srcIpAddr IS NOT NULL | K102: ExcessNetLoginFailure OR ExcessNetLoginFailure2 | L102: 600
A103: PH_Rule_Access_1 | B103: Multiple Login Failures: Net Device: No Source IP | C103: Existing, re-tagged ITDR | D103: ExcessNetLoginFailure | E103: Group@PH_SYS_EVENT_HostLogonFailure | G103: reptDevIpAddr IN (Group@PH_SYS_DEVICE_Network) AND srcIpAddr IS NULL | H103: reptDevName,reptDevIpAddr, user | I103: COUNT (*) >= 5 | J103: eventType IN (Group@PH_SYS_EVENT_HostLogonFailure) AND reptDevIpAddr IN (Group@PH_SYS_DEVICE_Network) AND srcIpAddr IS NULL | K103: ExcessNetLoginFailure OR ExcessNetLoginFailure2 | L103: 600
A104: PH_Rule_Access_1 | B104: Multiple Login Failures: Net Device: No Source IP | C104: Existing, re-tagged ITDR | D104: ExcessNetLoginFailure2 | E104: Group@PH_SYS_EVENT_MultipleHostLogonFailure | G104: reptDevIpAddr IN (Group@PH_SYS_DEVICE_Network) AND srcIpAddr IS NULL | H104: reptDevName,reptDevIpAddr, user | I104: COUNT (*) >= 1 | J104: eventType IN (Group@PH_SYS_EVENT_MultipleHostLogonFailure) AND reptDevIpAddr IN (Group@PH_SYS_DEVICE_Network) AND srcIpAddr IS NULL | K104: ExcessNetLoginFailure OR ExcessNetLoginFailure2 | L104: 600
A105: PH_Rule_Access_15B | B105: Multiple Logon Failures: Database | C105: Existing, re-tagged ITDR | D105: ExcessDBLoginFailure1 | E105: Group@PH_SYS_EVENT_DBLogonFailure | H105: srcIpAddr, srcGeoCountry, reptDevName, reptDevIpAddr, user | I105: COUNT (*) >= 5 | J105: eventType IN (Group@PH_SYS_EVENT_DBLogonFailure) | K105: ExcessDBLoginFailure1 OR ExcessDBLoginFailure2 | L105: 600
A106: PH_Rule_Access_15B | B106: Multiple Logon Failures: Database | C106: Existing, re-tagged ITDR | D106: ExcessDBLoginFailure2 | E106: Group@PH_SYS_EVENT_DBLogonFailure | H106: srcName, reptDevName, reptDevIpAddr, user | I106: COUNT (*) >= 5 | J106: eventType IN (Group@PH_SYS_EVENT_DBLogonFailure) | K106: ExcessDBLoginFailure1 OR ExcessDBLoginFailure2 | L106: 600
...

Sheet Rule-Event map
A1: Rule ID | B1: Rule name | C1: ITDR status | D1: Scope class | E1: Default status | F1: Log channel | G1: Event key | H1: Sizing row | I1: Raw eventType value
A2: PH_Rule_Azure_Entra_ID_Conditional_Access_Disabled | B2: Azure Entra ID: Conditional Access Disabled | C2: New ITDR (7.6.0) | D2: Identity-core | E2: Enabled | F2: Entra Event Hub | G2: AuditLogs | H2: ea | I2: MS-Entra-AuditLogs-Policy-Update_policy-success
A3: PH_Rule_Azure_Entra_ID_Domain_Authentication_Changed | B3: Azure Entra ID: Domain Authentication Changed | C3: New ITDR (7.6.0) | D3: Identity-core | E3: Enabled | F3: Entra Event Hub | G3: AuditLogs | H3: ea | I3: MS-Entra-AuditLogs-DirectoryMgmt-Set_domain_authentication-success
A4: PH_Rule_Azure_Entra_ID_External_User_Added_To_Privileged_Group | B4: Azure Entra ID: External User Added To Privileged Group | C4: New ITDR (7.6.0) | D4: Identity-core | E4: Enabled | F4: Entra Event Hub | G4: AuditLogs | H4: ea | I4: MS-Entra-AuditLogs-GroupMgmt-Add_member_to_group-success
A5: PH_Rule_Azure_Entra_ID_MFA_Bypass | B5: Azure Entra ID: MFA Bypass Or Satisfied By Claim | C5: New ITDR (7.6.0) | D5: Identity-core | E5: Enabled | F5: Entra Event Hub | G5: SignInLogs (interactive) | H5: ei | I5: MS-Entra-SignInLogs-Logon-success
A6: PH_Rule_Azure_Entra_ID_New_Federation_Domain_Added | B6: Azure Entra ID: New Federation Domain Added | C6: New ITDR (7.6.0) | D6: Identity-core | E6: Enabled | F6: Entra Event Hub | G6: AuditLogs | H6: ea | I6: MS-Entra-AuditLogs-DirectoryMgmt-Set_federation_settings_on_domain-success
A7: PH_Rule_Azure_Entra_ID_OAuth_Secret_Added | B7: Azure Entra ID: OAuth Secret Added | C7: New ITDR (7.6.0) | D7: Identity-core | E7: Enabled | F7: Entra Event Hub | G7: AuditLogs | H7: ea | I7: MS-Entra-AuditLogs-ApplicationMgmt-Add_service_principal_credentials-success
A8: PH_Rule_Azure_Entra_ID_User_Added_To_Application_Admin | B8: Azure Entra ID: User Added To Application Admin | C8: New ITDR (7.6.0) | D8: Identity-core | E8: Enabled | F8: Entra Event Hub | G8: AuditLogs | H8: ea | I8: MS-Entra-AuditLogs-RoleMgmt-Add_member_to_role-success
A9: PH_Rule_Azure_Entra_ID_User_Added_To_Exchange_Admin | B9: Azure Entra ID: User Added To Exchange Admin | C9: New ITDR (7.6.0) | D9: Identity-core | E9: Enabled | F9: Entra Event Hub | G9: AuditLogs | H9: ea | I9: MS-Entra-AuditLogs-RoleMgmt-Add_member_to_role-success
A10: PH_Rule_Azure_Entra_ID_User_Added_To_Global_Admin | B10: Azure Entra ID: User Added To Global Admin | C10: New ITDR (7.6.0) | D10: Identity-core | E10: Enabled | F10: Entra Event Hub | G10: AuditLogs | H10: ea | I10: MS-Entra-AuditLogs-RoleMgmt-Add_member_to_role-success
A11: PH_Rule_Azure_Entra_ID_User_Added_To_Privileged_Role_Admin | B11: Azure Entra ID: User Added To Privileged Role Admin | C11: New ITDR (7.6.0) | D11: Identity-core | E11: Enabled | F11: Entra Event Hub | G11: AuditLogs | H11: ea | I11: MS-Entra-AuditLogs-RoleMgmt-Add_member_to_role-success
A12: PH_Rule_Azure_Entra_ID_User_Added_To_Security_Admin | B12: Azure Entra ID: User Added To Security Admin | C12: New ITDR (7.6.0) | D12: Identity-core | E12: Enabled | F12: Entra Event Hub | G12: AuditLogs | H12: ea | I12: MS-Entra-AuditLogs-RoleMgmt-Add_member_to_role-success
A13: PH_Rule_Linux_etc_shadow_access | B13: Linux: /etc/shadow Access | C13: New ITDR (7.6.0) | D13: Identity-core | E13: Enabled | F13: Linux Collector | G13: LINUX_Auditd_PATH | I13: LINUX_Auditd_PATH
A14: PH_Rule_Linux_etc_shadow_access | B14: Linux: /etc/shadow Access | C14: New ITDR (7.6.0) | D14: Identity-core | E14: Enabled | F14: Linux Collector | G14: LINUX_Auditd_SYSCALL | I14: LINUX_Auditd_SYSCALL
A15: PH_Rule_Linux_etc_shadow_access | B15: Linux: /etc/shadow Access | C15: New ITDR (7.6.0) | D15: Identity-core | E15: Enabled | F15: Linux Collector | G15: LINUX_PROCESS_EXEC | I15: LINUX_PROCESS_EXEC
A16: PH_Rule_Linux_Root_Equivalent_Account_Command | B16: Linux: Attempt to Create or Modify a Root-Equivalent Account | C16: New ITDR (7.6.0) | D16: Identity-core | E16: Enabled | F16: Linux Collector | G16: LINUX_PROCESS_EXEC | I16: LINUX_PROCESS_EXEC
A17: PH_Rule_Linux_Root_Equivalent_Account_Command | B17: Linux: Attempt to Create or Modify a Root-Equivalent Account | C17: New ITDR (7.6.0) | D17: Identity-core | E17: Enabled | F17: Linux Collector | G17: LINUX_Auditd_SYSCALL | I17: LINUX_Auditd_SYSCALL
A18: PH_Rule_Linux_PAM_Configuration_Modified | B18: Linux: PAM Configuration Modified | C18: New ITDR (7.6.0) | D18: Identity-core | E18: Enabled | F18: Linux Collector | G18: FSM_LINUX_FILE_MODIFY | I18: FSM_LINUX_FILE_MODIFY
A19: PH_Rule_Win_Account_Created_Added_To_Privileged_Group | B19: Windows: Account Created Then Added To Privileged Group | C19: New ITDR (7.6.0) | D19: Identity-core | E19: Enabled | F19: Windows Security log | G19: Security 4720 | H19: a4 | I19: Win-Security-4720
A20: PH_Rule_Win_Account_Created_Added_To_Privileged_Group | B20: Windows: Account Created Then Added To Privileged Group | C20: New ITDR (7.6.0) | D20: Identity-core | E20: Enabled | F20: Windows Security log | G20: Security 4728 | H20: a4 | I20: Win-Security-4728
A21: PH_Rule_Win_Account_Created_Added_To_Privileged_Group | B21: Windows: Account Created Then Added To Privileged Group | C21: New ITDR (7.6.0) | D21: Identity-core | E21: Enabled | F21: Windows Security log | G21: Security 4732 | H21: a4 | I21: Win-Security-4732
A22: PH_Rule_Win_Account_Created_Added_To_Privileged_Group | B22: Windows: Account Created Then Added To Privileged Group | C22: New ITDR (7.6.0) | D22: Identity-core | E22: Enabled | F22: Windows Security log | G22: Security 4756 | H22: a4 | I22: Win-Security-4756
A23: PH_Rule_Win_ADCS_ESC10_Certificate_Mapping_Config_Command | B23: Windows: AD CS ESC10 Certificate Mapping Configuration Changed via Command | C23: New ITDR (7.6.0) | D23: Identity-core | E23: Enabled | F23: Windows Security log | G23: Security 4688 | I23: Win-Security-4688
A24: PH_Rule_Win_ADCS_ESC10_Certificate_Mapping_Config_Command | B24: Windows: AD CS ESC10 Certificate Mapping Configuration Changed via Command | C24: New ITDR (7.6.0) | D24: Identity-core | E24: Enabled | F24: Sysmon | G24: Sysmon 1 | H24: s1 | I24: Win-Sysmon-1-Create-Process
A25: PH_Rule_Win_ADCS_ESC10_Certificate_Mapping_Config_Command | B25: Windows: AD CS ESC10 Certificate Mapping Configuration Changed via Command | C25: New ITDR (7.6.0) | D25: Identity-core | E25: Enabled | F25: PowerShell Operational | G25: PowerShell 4104 | H25: s4 | I25: Win-PowerShell-4104
A26: PH_Rule_Win_ADCS_ESC13_OID_Group_Link_Modified | B26: Windows: AD CS ESC13 OID Group Link Modified | C26: New ITDR (7.6.0) | D26: Identity-core | E26: Enabled | F26: Windows Security log | G26: Security 5136 | H26: a6 | I26: Win-Security-5136
A27: PH_Rule_Win_ADCS_ESC14_Explicit_Certificate_Mapping_Modified | B27: Windows: AD CS ESC14 Explicit Certificate Mapping Modified | C27: New ITDR (7.6.0) | D27: Identity-core | E27: Enabled | F27: Windows Security log | G27: Security 5136 | H27: a6 | I27: Win-Security-5136
A28: PH_Rule_Win_ADCS_ESC16_SID_Extension_Disabled_Command | B28: Windows: AD CS ESC16 SID Security Extension Disabled via Command | C28: New ITDR (7.6.0) | D28: Identity-core | E28: Enabled | F28: Windows Security log | G28: Security 4688 | I28: Win-Security-4688
A29: PH_Rule_Win_ADCS_ESC16_SID_Extension_Disabled_Command | B29: Windows: AD CS ESC16 SID Security Extension Disabled via Command | C29: New ITDR (7.6.0) | D29: Identity-core | E29: Enabled | F29: Sysmon | G29: Sysmon 1 | H29: s1 | I29: Win-Sysmon-1-Create-Process
A30: PH_Rule_Win_ADCS_ESC16_SID_Extension_Disabled_Command | B30: Windows: AD CS ESC16 SID Security Extension Disabled via Command | C30: New ITDR (7.6.0) | D30: Identity-core | E30: Enabled | F30: PowerShell Operational | G30: PowerShell 4104 | H30: s4 | I30: Win-PowerShell-4104
A31: PH_Rule_Win_ADCS_ESC2_Any_Purpose_EKU_Added | B31: Windows: AD CS ESC2 Any Purpose EKU Added to Certificate Template | C31: New ITDR (7.6.0) | D31: Identity-core | E31: Enabled | F31: Windows Security log | G31: Security 5136 | H31: a6 | I31: Win-Security-5136
A32: PH_Rule_Win_ADCS_ESC3_Enrollment_Agent_EKU_Added | B32: Windows: AD CS ESC3 Enrollment Agent EKU Added to Certificate Template | C32: New ITDR (7.6.0) | D32: Identity-core | E32: Enabled | F32: Windows Security log | G32: Security 5136 | H32: a6 | I32: Win-Security-5136
A33: PH_Rule_Win_ADCS_ESC5_PKI_Object_ACL_Modified | B33: Windows: AD CS ESC5 PKI Object ACL Modified | C33: New ITDR (7.6.0) | D33: Identity-core | E33: Enabled | F33: Windows Security log | G33: Security 5136 | H33: a6 | I33: Win-Security-5136
A34: PH_Rule_Win_ADCS_ESC7_CA_Security_Permissions_Changed | B34: Windows: AD CS ESC7 CA Security Permissions Changed | C34: New ITDR (7.6.0) | D34: Identity-core | E34: Enabled | F34: Windows Security log | G34: Security 4882 | H34: ca | I34: Win-Security-4882
A35: PH_Rule_Win_ADCS_Web_Enrollment_Certificate_Request | B35: Windows: AD CS Web Enrollment Certificate Request | C35: New ITDR (7.6.0) | D35: Identity-core | E35: Enabled | F35: IIS log | G35: IIS web request | I35: IIS-Web-Request-Success
A36: PH_Rule_Win_AdminSDHolder_Modified | B36: Windows: AdminSDHolder Modified | C36: New ITDR (7.6.0) | D36: Identity-core | E36: Enabled | F36: Windows Security log | G36: Security 5136 | H36: a6 | I36: Win-Security-5136
A37: PH_Rule_Win_Auth_Package_Modified | B37: Windows: Authentication Package Modified | C37: New ITDR (7.6.0) | D37: Identity-core | E37: Enabled | F37: Windows Security log | G37: Security 4688 | I37: Win-Security-4688
A38: PH_Rule_Win_Auth_Package_Modified | B38: Windows: Authentication Package Modified | C38: New ITDR (7.6.0) | D38: Identity-core | E38: Enabled | F38: Sysmon | G38: Sysmon 1 | H38: s1 | I38: Win-Sysmon-1-Create-Process
A39: PH_Rule_Win_Auth_Package_Modified | B39: Windows: Authentication Package Modified | C39: New ITDR (7.6.0) | D39: Identity-core | E39: Enabled | F39: PowerShell Operational | G39: PowerShell 4104 | H39: s4 | I39: Win-PowerShell-4104
A40: PH_Rule_Win_BloodHound_SharpHound_Execution | B40: Windows: BloodHound or SharpHound Execution | C40: New ITDR (7.6.0) | D40: Identity-core | E40: Enabled | F40: Windows Security log | G40: Security 4688 | I40: Win-Security-4688
A41: PH_Rule_Win_BloodHound_SharpHound_Execution | B41: Windows: BloodHound or SharpHound Execution | C41: New ITDR (7.6.0) | D41: Identity-core | E41: Enabled | F41: Sysmon | G41: Sysmon 1 | H41: s1 | I41: Win-Sysmon-1-Create-Process
A42: PH_Rule_Win_BloodHound_SharpHound_Execution | B42: Windows: BloodHound or SharpHound Execution | C42: New ITDR (7.6.0) | D42: Identity-core | E42: Enabled | F42: PowerShell Operational | G42: PowerShell 4104 | H42: s4 | I42: Win-PowerShell-4104
A43: PH_Rule_Win_CA_Configuration_Changed | B43: Windows: CA Configuration Changed | C43: New ITDR (7.6.0) | D43: Identity-core | E43: Enabled | F43: Windows Security log | G43: Security 4890 | H43: ca | I43: Win-Security-4890
A44: PH_Rule_Win_CA_Configuration_Changed | B44: Windows: CA Configuration Changed | C44: New ITDR (7.6.0) | D44: Identity-core | E44: Enabled | F44: Windows Security log | G44: Security 4891 | I44: Win-Security-4891
A45: PH_Rule_Win_CA_Configuration_Changed | B45: Windows: CA Configuration Changed | C45: New ITDR (7.6.0) | D45: Identity-core | E45: Enabled | F45: Windows Security log | G45: Security 4892 | I45: Win-Security-4892
A46: PH_Rule_Win_CA_Configuration_Changed | B46: Windows: CA Configuration Changed | C46: New ITDR (7.6.0) | D46: Identity-core | E46: Enabled | F46: Windows Security log | G46: Security 4893 | I46: Win-Security-4893
A47: PH_Rule_Win_CA_Configuration_Changed | B47: Windows: CA Configuration Changed | C47: New ITDR (7.6.0) | D47: Identity-core | E47: Enabled | F47: Windows Security log | G47: Security 4894 | I47: Win-Security-4894
A48: PH_Rule_Win_Certificate_Template_Modified | B48: Windows: Certificate Template Modified | C48: New ITDR (7.6.0) | D48: Identity-core | E48: Enabled | F48: Windows Security log | G48: Security 5136 | H48: a6 | I48: Win-Security-5136
A49: PH_Rule_Win_Certipy_Credential_Abuse | B49: Windows: Certipy Credential Abuse | C49: New ITDR (7.6.0) | D49: Identity-core | E49: Enabled | F49: Windows Security log | G49: Security 4688 | I49: Win-Security-4688
A50: PH_Rule_Win_Certipy_Credential_Abuse | B50: Windows: Certipy Credential Abuse | C50: New ITDR (7.6.0) | D50: Identity-core | E50: Enabled | F50: Sysmon | G50: Sysmon 1 | H50: s1 | I50: Win-Sysmon-1-Create-Process
A51: PH_Rule_Win_Certipy_Credential_Abuse | B51: Windows: Certipy Credential Abuse | C51: New ITDR (7.6.0) | D51: Identity-core | E51: Enabled | F51: PowerShell Operational | G51: PowerShell 4104 | H51: s4 | I51: Win-PowerShell-4104
A52: PH_Rule_Win_Comsvcs_MiniDump_LSASS | B52: Windows: comsvcs.dll MiniDump LSASS | C52: New ITDR (7.6.0) | D52: Identity-core | E52: Enabled | F52: Windows Security log | G52: Security 4688 | I52: Win-Security-4688
A53: PH_Rule_Win_Comsvcs_MiniDump_LSASS | B53: Windows: comsvcs.dll MiniDump LSASS | C53: New ITDR (7.6.0) | D53: Identity-core | E53: Enabled | F53: Sysmon | G53: Sysmon 1 | H53: s1 | I53: Win-Sysmon-1-Create-Process
A54: PH_Rule_Win_Domain_Trust_Modified | B54: Windows: Domain Trust Modified | C54: New ITDR (7.6.0) | D54: Identity-core | E54: Enabled | F54: Windows Security log | G54: Security 4706 | H54: a6 | I54: Win-Security-4706
A55: PH_Rule_Win_Domain_Trust_Modified | B55: Windows: Domain Trust Modified | C55: New ITDR (7.6.0) | D55: Identity-core | E55: Enabled | F55: Windows Security log | G55: Security 4707 | H55: a6 | I55: Win-Security-4707
A56: PH_Rule_Win_Domain_Trust_Modified | B56: Windows: Domain Trust Modified | C56: New ITDR (7.6.0) | D56: Identity-core | E56: Enabled | F56: Windows Security log | G56: Security 4716 | H56: a6 | I56: Win-Security-4716
A57: PH_Rule_Win_Domain_Trust_Modified | B57: Windows: Domain Trust Modified | C57: New ITDR (7.6.0) | D57: Identity-core | E57: Enabled | F57: Windows Security log | G57: Security 5136 | H57: a6 | I57: Win-Security-5136
A58: PH_Rule_Win_ESC1_Relevant_Template_Attribute_Modified | B58: Windows: ESC1-Relevant Certificate Template Attribute Modified | C58: New ITDR (7.6.0) | D58: Identity-core | E58: Enabled | F58: Windows Security log | G58: Security 5136 | H58: a6 | I58: Win-Security-5136
A59: PH_Rule_Win_ESC4_Certificate_Template_ACL_Modified | B59: Windows: ESC4 Certificate Template ACL Modified | C59: New ITDR (7.6.0) | D59: Identity-core | E59: Enabled | F59: Windows Security log | G59: Security 5136 | H59: a6 | I59: Win-Security-5136
A60: PH_Rule_Win_ESC6_EDITF_ATTRIBUTESUBJECTALTNAME2_Enabled | B60: Windows: ESC6 EDITF-ATTRIBUTESUBJECTALTNAME2 Enabled with Certutil | C60: New ITDR (7.6.0) | D60: Identity-core | E60: Enabled | F60: Windows Security log | G60: Security 4688 | I60: Win-Security-4688
A61: PH_Rule_Win_ESC6_EDITF_ATTRIBUTESUBJECTALTNAME2_Enabled | B61: Windows: ESC6 EDITF-ATTRIBUTESUBJECTALTNAME2 Enabled with Certutil | C61: New ITDR (7.6.0) | D61: Identity-core | E61: Enabled | F61: Sysmon | G61: Sysmon 1 | H61: s1 | I61: Win-Sysmon-1-Create-Process
A62: PH_Rule_Win_ESC6_EDITF_ATTRIBUTESUBJECTALTNAME2_Enabled | B62: Windows: ESC6 EDITF-ATTRIBUTESUBJECTALTNAME2 Enabled with Certutil | C62: New ITDR (7.6.0) | D62: Identity-core | E62: Enabled | F62: PowerShell Operational | G62: PowerShell 4104 | H62: s4 | I62: Win-PowerShell-4104
A63: PH_Rule_Win_Kerberoasting_Multiple_SPNs | B63: Windows: Kerberoasting Multiple SPNs | C63: New ITDR (7.6.0) | D63: Identity-core | E63: Enabled | F63: Windows Security log | G63: Security 4769 | H63: a2 | I63: Win-Security-4769-success
A64: PH_Rule_Win_KRBTGT_Password_Reset | B64: Windows: KRBTGT Password Reset | C64: New ITDR (7.6.0) | D64: Identity-core | E64: Enabled | F64: Windows Security log | G64: Security 4724 | H64: a4 | I64: Win-Security-4724
A65: PH_Rule_Win_LaZagne_Credential_Dumping | B65: Windows: LaZagne Credential Dumping via Process or PowerShell | C65: New ITDR (7.6.0) | D65: Identity-core | E65: Enabled | F65: Windows Security log | G65: Security 4688 | I65: Win-Security-4688
A66: PH_Rule_Win_LaZagne_Credential_Dumping | B66: Windows: LaZagne Credential Dumping via Process or PowerShell | C66: New ITDR (7.6.0) | D66: Identity-core | E66: Enabled | F66: Sysmon | G66: Sysmon 1 | H66: s1 | I66: Win-Sysmon-1-Create-Process
A67: PH_Rule_Win_LaZagne_Credential_Dumping | B67: Windows: LaZagne Credential Dumping via Process or PowerShell | C67: New ITDR (7.6.0) | D67: Identity-core | E67: Enabled | F67: PowerShell Operational | G67: PowerShell 4104 | H67: s4 | I67: Win-PowerShell-4104
A68: PH_Rule_Win_LSASS_Access_By_Suspicious_Process | B68: Windows: LSASS Access by Suspicious Process | C68: New ITDR (7.6.0) | D68: Identity-core | E68: Enabled | F68: Sysmon | G68: Sysmon 10 | H68: s2 | I68: Win-Sysmon-10-ProcessAccess
A69: PH_Rule_Win_Mass_Group_Membership_Changes | B69: Windows: Mass Group Membership Changes | C69: New ITDR (7.6.0) | D69: Identity-core | E69: Enabled | F69: Windows Security log | G69: Security 4728 | H69: a4 | I69: Win-Security-4728
A70: PH_Rule_Win_Mass_Group_Membership_Changes | B70: Windows: Mass Group Membership Changes | C70: New ITDR (7.6.0) | D70: Identity-core | E70: Enabled | F70: Windows Security log | G70: Security 4729 | H70: a4 | I70: Win-Security-4729
A71: PH_Rule_Win_Mass_Group_Membership_Changes | B71: Windows: Mass Group Membership Changes | C71: New ITDR (7.6.0) | D71: Identity-core | E71: Enabled | F71: Windows Security log | G71: Security 4732 | H71: a4 | I71: Win-Security-4732
A72: PH_Rule_Win_Mass_Group_Membership_Changes | B72: Windows: Mass Group Membership Changes | C72: New ITDR (7.6.0) | D72: Identity-core | E72: Enabled | F72: Windows Security log | G72: Security 4733 | H72: a4 | I72: Win-Security-4733
A73: PH_Rule_Win_Mass_Group_Membership_Changes | B73: Windows: Mass Group Membership Changes | C73: New ITDR (7.6.0) | D73: Identity-core | E73: Enabled | F73: Windows Security log | G73: Security 4756 | H73: a4 | I73: Win-Security-4756
A74: PH_Rule_Win_Mass_Group_Membership_Changes | B74: Windows: Mass Group Membership Changes | C74: New ITDR (7.6.0) | D74: Identity-core | E74: Enabled | F74: Windows Security log | G74: Security 4757 | H74: a4 | I74: Win-Security-4757
A75: PH_Rule_Win_Mass_User_Creation_By_One_Actor | B75: Windows: Mass User Creation By One Actor | C75: New ITDR (7.6.0) | D75: Identity-core | E75: Enabled | F75: Windows Security log | G75: Security 4720 | H75: a4 | I75: Win-Security-4720
A76: PH_Rule_Win_Mass_User_Disable_By_One_Actor | B76: Windows: Mass User Disable By One Actor | C76: New ITDR (7.6.0) | D76: Identity-core | E76: Enabled | F76: Windows Security log | G76: Security 4725 | H76: a4 | I76: Win-Security-4725
A77: PH_Rule_Win_Mimikatz_Command | B77: Windows: Mimikatz Command | C77: New ITDR (7.6.0) | D77: Identity-core | E77: Enabled | F77: Windows Security log | G77: Security 4688 | I77: Win-Security-4688
A78: PH_Rule_Win_Mimikatz_Command | B78: Windows: Mimikatz Command | C78: New ITDR (7.6.0) | D78: Identity-core | E78: Enabled | F78: Sysmon | G78: Sysmon 1 | H78: s1 | I78: Win-Sysmon-1-Create-Process
A79: PH_Rule_Win_Mimikatz_Command | B79: Windows: Mimikatz Command | C79: New ITDR (7.6.0) | D79: Identity-core | E79: Enabled | F79: PowerShell Operational | G79: PowerShell 4104 | H79: s4 | I79: Win-PowerShell-4104
A80: PH_Rule_Win_Nanodump_LSASS_Dumping | B80: Windows: Nanodump LSASS Dumping | C80: New ITDR (7.6.0) | D80: Identity-core | E80: Enabled | F80: Windows Security log | G80: Security 4688 | I80: Win-Security-4688
A81: PH_Rule_Win_Nanodump_LSASS_Dumping | B81: Windows: Nanodump LSASS Dumping | C81: New ITDR (7.6.0) | D81: Identity-core | E81: Enabled | F81: Sysmon | G81: Sysmon 1 | H81: s1 | I81: Win-Sysmon-1-Create-Process
A82: PH_Rule_Win_Nanodump_LSASS_Dumping | B82: Windows: Nanodump LSASS Dumping | C82: New ITDR (7.6.0) | D82: Identity-core | E82: Enabled | F82: PowerShell Operational | G82: PowerShell 4104 | H82: s4 | I82: Win-PowerShell-4104
A83: PH_Rule_Win_Procdump_LSASS_Dump | B83: Windows: Procdump LSASS Dump | C83: New ITDR (7.6.0) | D83: Identity-core | E83: Enabled | F83: Windows Security log | G83: Security 4688 | I83: Win-Security-4688
A84: PH_Rule_Win_Procdump_LSASS_Dump | B84: Windows: Procdump LSASS Dump | C84: New ITDR (7.6.0) | D84: Identity-core | E84: Enabled | F84: Sysmon | G84: Sysmon 1 | H84: s1 | I84: Win-Sysmon-1-Create-Process
A85: PH_Rule_Win_PsExec_Service_Creation | B85: Windows: PsExec Service Creation | C85: New ITDR (7.6.0) | D85: Identity-core | E85: Enabled | F85: Windows System log | G85: System 7045 | I85: Win-System-Service-Control-Manager-7045
A86: PH_Rule_Win_Pypykatz_Credential_Dumping | B86: Windows: Pypykatz Credential Dumping via Process or PowerShell | C86: New ITDR (7.6.0) | D86: Identity-core | E86: Enabled | F86: Windows Security log | G86: Security 4688 | I86: Win-Security-4688
A87: PH_Rule_Win_Pypykatz_Credential_Dumping | B87: Windows: Pypykatz Credential Dumping via Process or PowerShell | C87: New ITDR (7.6.0) | D87: Identity-core | E87: Enabled | F87: Sysmon | G87: Sysmon 1 | H87: s1 | I87: Win-Sysmon-1-Create-Process
A88: PH_Rule_Win_Pypykatz_Credential_Dumping | B88: Windows: Pypykatz Credential Dumping via Process or PowerShell | C88: New ITDR (7.6.0) | D88: Identity-core | E88: Enabled | F88: PowerShell Operational | G88: PowerShell 4104 | H88: s4 | I88: Win-PowerShell-4104
A89: PH_Rule_Win_RBCD_Attribute_Modified | B89: Windows: RBCD Attribute Modified | C89: New ITDR (7.6.0) | D89: Identity-core | E89: Enabled | F89: Windows Security log | G89: Security 5136 | H89: a6 | I89: Win-Security-5136
A90: PH_Rule_Win_Rubeus_Kerberos_Abuse | B90: Windows: Rubeus Kerberos Abuse | C90: New ITDR (7.6.0) | D90: Identity-core | E90: Enabled | F90: Windows Security log | G90: Security 4688 | I90: Win-Security-4688
A91: PH_Rule_Win_Rubeus_Kerberos_Abuse | B91: Windows: Rubeus Kerberos Abuse | C91: New ITDR (7.6.0) | D91: Identity-core | E91: Enabled | F91: Sysmon | G91: Sysmon 1 | H91: s1 | I91: Win-Sysmon-1-Create-Process
A92: PH_Rule_Win_Rubeus_Kerberos_Abuse | B92: Windows: Rubeus Kerberos Abuse | C92: New ITDR (7.6.0) | D92: Identity-core | E92: Enabled | F92: PowerShell Operational | G92: PowerShell 4104 | H92: s4 | I92: Win-PowerShell-4104
A93: PH_Rule_Win_SafetyKatz_Credential_Dumping | B93: Windows: SafetyKatz Credential Dumping | C93: New ITDR (7.6.0) | D93: Identity-core | E93: Enabled | F93: Windows Security log | G93: Security 4688 | I93: Win-Security-4688
A94: PH_Rule_Win_SafetyKatz_Credential_Dumping | B94: Windows: SafetyKatz Credential Dumping | C94: New ITDR (7.6.0) | D94: Identity-core | E94: Enabled | F94: Sysmon | G94: Sysmon 1 | H94: s1 | I94: Win-Sysmon-1-Create-Process
A95: PH_Rule_Win_SafetyKatz_Credential_Dumping | B95: Windows: SafetyKatz Credential Dumping | C95: New ITDR (7.6.0) | D95: Identity-core | E95: Enabled | F95: PowerShell Operational | G95: PowerShell 4104 | H95: s4 | I95: Win-PowerShell-4104
A96: PH_Rule_Win_Schema_Modification | B96: Windows: Schema Modification | C96: New ITDR (7.6.0) | D96: Identity-core | E96: Enabled | F96: Windows Security log | G96: Security 5136 | H96: a6 | I96: Win-Security-5136
A97: PH_Rule_Win_Secretsdump_Execution | B97: Windows: Secretsdump Execution via Process or PowerShell | C97: New ITDR (7.6.0) | D97: Identity-core | E97: Enabled | F97: Windows Security log | G97: Security 4688 | I97: Win-Security-4688
A98: PH_Rule_Win_Secretsdump_Execution | B98: Windows: Secretsdump Execution via Process or PowerShell | C98: New ITDR (7.6.0) | D98: Identity-core | E98: Enabled | F98: Sysmon | G98: Sysmon 1 | H98: s1 | I98: Win-Sysmon-1-Create-Process
A99: PH_Rule_Win_Secretsdump_Execution | B99: Windows: Secretsdump Execution via Process or PowerShell | C99: New ITDR (7.6.0) | D99: Identity-core | E99: Enabled | F99: PowerShell Operational | G99: PowerShell 4104 | H99: s4 | I99: Win-PowerShell-4104
A100: PH_Rule_Win_Sensitive_Registry_Hive_Save | B100: Windows: Sensitive Registry Hive Save | C100: New ITDR (7.6.0) | D100: Identity-core | E100: Enabled | F100: Windows Security log | G100: Security 4688 | I100: Win-Security-4688
...

Sheet Rule-Row map
A1: Rule ID | B1: Rule name | C1: ITDR status | D1: Default status | E1: Sizing row
A2: PH_Rule_Azure_Entra_ID_Conditional_Access_Disabled | B2: Azure Entra ID: Conditional Access Disabled | C2: New ITDR (7.6.0) | D2: Enabled | E2: ea
A3: PH_Rule_Azure_Entra_ID_Domain_Authentication_Changed | B3: Azure Entra ID: Domain Authentication Changed | C3: New ITDR (7.6.0) | D3: Enabled | E3: ea
A4: PH_Rule_Azure_Entra_ID_External_User_Added_To_Privileged_Group | B4: Azure Entra ID: External User Added To Privileged Group | C4: New ITDR (7.6.0) | D4: Enabled | E4: ea
A5: PH_Rule_Azure_Entra_ID_MFA_Bypass | B5: Azure Entra ID: MFA Bypass Or Satisfied By Claim | C5: New ITDR (7.6.0) | D5: Enabled | E5: ei
A6: PH_Rule_Azure_Entra_ID_New_Federation_Domain_Added | B6: Azure Entra ID: New Federation Domain Added | C6: New ITDR (7.6.0) | D6: Enabled | E6: ea
A7: PH_Rule_Azure_Entra_ID_OAuth_Secret_Added | B7: Azure Entra ID: OAuth Secret Added | C7: New ITDR (7.6.0) | D7: Enabled | E7: ea
A8: PH_Rule_Azure_Entra_ID_User_Added_To_Application_Admin | B8: Azure Entra ID: User Added To Application Admin | C8: New ITDR (7.6.0) | D8: Enabled | E8: ea
A9: PH_Rule_Azure_Entra_ID_User_Added_To_Exchange_Admin | B9: Azure Entra ID: User Added To Exchange Admin | C9: New ITDR (7.6.0) | D9: Enabled | E9: ea
A10: PH_Rule_Azure_Entra_ID_User_Added_To_Global_Admin | B10: Azure Entra ID: User Added To Global Admin | C10: New ITDR (7.6.0) | D10: Enabled | E10: ea
A11: PH_Rule_Azure_Entra_ID_User_Added_To_Privileged_Role_Admin | B11: Azure Entra ID: User Added To Privileged Role Admin | C11: New ITDR (7.6.0) | D11: Enabled | E11: ea
A12: PH_Rule_Azure_Entra_ID_User_Added_To_Security_Admin | B12: Azure Entra ID: User Added To Security Admin | C12: New ITDR (7.6.0) | D12: Enabled | E12: ea
... A405: PH_Rule_windows_SIGMA_3593 | B405: Windows: Winrs Local Command Execution | C405: New in 7.6.0 (not ITDR) | D405: Disabled | E405: s1

Sheet Rule-DS map
A1: Rule ID | B1: Rule name | C1: ITDR status | D1: Scope class | E1: Default status | F1: FortiSIEM data source
A2: PH_Rule_Azure_Entra_ID_Conditional_Access_Disabled | B2: Azure Entra ID: Conditional Access Disabled | C2: New ITDR (7.6.0) | D2: Identity-core | E2: Enabled | F2: Microsoft Entra Activity Logs via Azure Event Hub
A3: PH_Rule_Azure_Entra_ID_Domain_Authentication_Changed | B3: Azure Entra ID: Domain Authentication Changed | C3: New ITDR (7.6.0) | D3: Identity-core | E3: Enabled | F3: Microsoft Entra Activity Logs via Azure Event Hub
A4: PH_Rule_Azure_Entra_ID_External_User_Added_To_Privileged_Group | B4: Azure Entra ID: External User Added To Privileged Group | C4: New ITDR (7.6.0) | D4: Identity-core | E4: Enabled | F4: Microsoft Entra Activity Logs via Azure Event Hub
A5: PH_Rule_Azure_Entra_ID_MFA_Bypass | B5: Azure Entra ID: MFA Bypass Or Satisfied By Claim | C5: New ITDR (7.6.0) | D5: Identity-core | E5: Enabled | F5: Microsoft Entra Activity Logs via Azure Event Hub
A6: PH_Rule_Azure_Entra_ID_New_Federation_Domain_Added | B6: Azure Entra ID: New Federation Domain Added | C6: New ITDR (7.6.0) | D6: Identity-core | E6: Enabled | F6: Microsoft Entra Activity Logs via Azure Event Hub
A7: PH_Rule_Azure_Entra_ID_OAuth_Secret_Added | B7: Azure Entra ID: OAuth Secret Added | C7: New ITDR (7.6.0) | D7: Identity-core | E7: Enabled | F7: Microsoft Entra Activity Logs via Azure Event Hub
A8: PH_Rule_Azure_Entra_ID_User_Added_To_Application_Admin | B8: Azure Entra ID: User Added To Application Admin | C8: New ITDR (7.6.0) | D8: Identity-core | E8: Enabled | F8: Microsoft Entra Activity Logs via Azure Event Hub
A9: PH_Rule_Azure_Entra_ID_User_Added_To_Exchange_Admin | B9: Azure Entra ID: User Added To Exchange Admin | C9: New ITDR (7.6.0) | D9: Identity-core | E9: Enabled | F9: Microsoft Entra Activity Logs via Azure Event Hub
A10: PH_Rule_Azure_Entra_ID_User_Added_To_Global_Admin | B10: Azure Entra ID: User Added To Global Admin | C10: New ITDR (7.6.0) | D10: Identity-core | E10: Enabled | F10: Microsoft Entra Activity Logs via Azure Event Hub
A11: PH_Rule_Azure_Entra_ID_User_Added_To_Privileged_Role_Admin | B11: Azure Entra ID: User Added To Privileged Role Admin | C11: New ITDR (7.6.0) | D11: Identity-core | E11: Enabled | F11: Microsoft Entra Activity Logs via Azure Event Hub
A12: PH_Rule_Azure_Entra_ID_User_Added_To_Security_Admin | B12: Azure Entra ID: User Added To Security Admin | C12: New ITDR (7.6.0) | D12: Identity-core | E12: Enabled | F12: Microsoft Entra Activity Logs via Azure Event Hub
... A1613: PH_Rule_windows_SIGMA_2859 | B1613: Windows: Zerologon Exploitation Using Well-known Tools | C1613: New in 7.6.0 (not ITDR) | D1613: Tactic match only | E1613: Disabled | F1613: Microsoft Windows System Log via OMI or Windows Collector

Sheet Data sources
A1: FortiSIEM data source | B1: In-scope rules | C1: New ITDR (7.6.0) | D1: Re-tagged ITDR | E1: Identity-core | F1: Enabled by default | G1: Distinct event types read | H1: Event types read by these rules (derived; multi-source rules list all their types)
